Workbook
Name Accesorios: OFFSET(#REF!,0,0,COUNTA(#REF!)-2,1)
Name Alcatel: Catalogo!$B$2:$B$10
Name Apple: Catalogo!$C$2:$C$209
Name GOOGLE: Catalogo!$N$2:$N$15
Name Hisense: Catalogo!$D$2:$D$10
Name Honor: Catalogo!$H$2:$H$84
Name Huawei: Catalogo!$E$2:$E$49
Name Marca: Catalogo!$A$2:$A$12
Name Motorola: Catalogo!$F$2:$F$100
Name NUBIA: Catalogo!$M$2:$M$3
Name OPPO: Catalogo!$J$2:$J$89
Name REALME: Catalogo!$L$2:$L$6
Name Samsung: Catalogo!$G$2:$G$183
Name Xiaomi: Catalogo!$I$2:$I$89
Name ZTE: Catalogo!$K$2:$K$10

Sheet Cotizador
B2: Cotizador Precios Ármalo Negocios
B4: FECHA PRECIO VIGENTE | C4: =TODAY() -> 46279
F5: PRECIO VIGENTE
B6: Marca | C6: SAMSUNG | F6: Activación & Renovación - AT&T Ármalo Negocios
F7: Plan | G7: 299 | H7: 399 | I7: 499 | J7: 599 | K7: 799 | L7: 1299 | M7: 1499
B8: Equipo | C8: SAMSUNG GALAXY S26 FE 256GB 5G | F8: 12 Meses | G8: =IF(SUMIFS(Precios!$G:$G,Precios!$E:$E,$C$8,Precios!$AP:$AP,"<="&$C$4,Precios!$AQ:$AQ,">="&$C$4)>=0,SUMIFS(Precios!$G:$G,Precios!$E:$E,$C$8,Precios!$AP:$AP,"<="&$C$4,Precios!$AQ:$AQ,">="&$C$4)) -> 12989 | H8: =IF(SUMIFS(Precios!$L:$L,Precios!$E:$E,$C$8,Precios!$AP:$AP,"<="&$C$4,Precios!$AQ:$AQ,">="&$C$4)>=0,SUMIFS(Precios!$L:$L,Precios!$E:$E,$C$8,Precios!$AP:$AP,"<="&$C$4,Precios!$AQ:$AQ,">="&$C$4)) -> 12839 | I8: =IF(SUMIFS(Precios!$Q:$Q,Precios!$E:$E,$C$8,Precios!$AP:$AP,"<="&$C$4,Precios!$AQ:$AQ,">="&$C$4)>=0,SUMIFS(Precios!$Q:$Q,Precios!$E:$E,$C$8,Precios!$AP:$AP,"<="&$C$4,Precios!$AQ:$AQ,">="&$C$4)) -> 12689 | J8: =IF(SUMIFS(Precios!$V:$V,Precios!$E:$E,$C$8,Precios!$AP:$AP,"<="&$C$4,Precios!$AQ:$AQ,">="&$C$4)>=0,SUMIFS(Precios!$V:$V,Precios!$E:$E,$C$8,Precios!$AP:$AP,"<="&$C$4,Precios!$AQ:$AQ,">="&$C$4)) -> 12539 | K8: =IF(SUMIFS(Precios!$AA:$AA,Precios!$E:$E,$C$8,Precios!$AP:$AP,"<="&$C$4,Precios!$AQ:$AQ,">="&$C$4)>=0,SUMIFS(Precios!$AA:$AA,Precios!$E:$E,$C$8,Precios!$AP:$AP,"<="&$C$4,Precios!$AQ:$AQ,">="&$C$4)) -> 12229 | L8: =IF(SUMIFS(Precios!$AF:$AF,Precios!$E:$E,$C$8,Precios!$AP:$AP,"<="&$C$4,Precios!$AQ:$AQ,">="&$C$4)>=0,SUMIFS(Precios!$AF:$AF,Precios!$E:$E,$C$8,Precios!$AP:$AP,"<="&$C$4,Precios!$AQ:$AQ,">="&$C$4)) -> 11479 | M8: =IF(SUMIFS(Precios!$AK:$AK,Precios!$E:$E,$C$8,Precios!$AP:$AP,"<="&$C$4,Precios!$AQ:$AQ,">="&$C$4)>=0,SUMIFS(Precios!$AK:$AK,Precios!$E:$E,$C$8,Precios!$AP:$AP,"<="&$C$4,Precios!$AQ:$AQ,">="&$C$4)) -> 11169
F9: 18 Meses | G9: =IF(SUMIFS(Precios!$H:$H,Precios!$E:$E,$C$8,Precios!$AP:$AP,"<="&$C$4,Precios!$AQ:$AQ,">="&$C$4)>=0,SUMIFS(Precios!$H:$H,Precios!$E:$E,$C$8,Precios!$AP:$AP,"<="&$C$4,Precios!$AQ:$AQ,">="&$C$4)) -> 12759 | H9: =IF(SUMIFS(Precios!$M:$M,Precios!$E:$E,$C$8,Precios!$AP:$AP,"<="&$C$4,Precios!$AQ:$AQ,">="&$C$4)>=0,SUMIFS(Precios!$M:$M,Precios!$E:$E,$C$8,Precios!$AP:$AP,"<="&$C$4,Precios!$AQ:$AQ,">="&$C$4)) -> 12539 | I9: =IF(SUMIFS(Precios!$R:$R,Precios!$E:$E,$C$8,Precios!$AP:$AP,"<="&$C$4,Precios!$AQ:$AQ,">="&$C$4)>=0,SUMIFS(Precios!$R:$R,Precios!$E:$E,$C$8,Precios!$AP:$AP,"<="&$C$4,Precios!$AQ:$AQ,">="&$C$4)) -> 12309 | J9: =IF(SUMIFS(Precios!$W:$W,Precios!$E:$E,$C$8,Precios!$AP:$AP,"<="&$C$4,Precios!$AQ:$AQ,">="&$C$4)>=0,SUMIFS(Precios!$W:$W,Precios!$E:$E,$C$8,Precios!$AP:$AP,"<="&$C$4,Precios!$AQ:$AQ,">="&$C$4)) -> 12079 | K9: =IF(SUMIFS(Precios!$AB:$AB,Precios!$E:$E,$C$8,Precios!$AP:$AP,"<="&$C$4,Precios!$AQ:$AQ,">="&$C$4)>=0,SUMIFS(Precios!$AB:$AB,Precios!$E:$E,$C$8,Precios!$AP:$AP,"<="&$C$4,Precios!$AQ:$AQ,">="&$C$4)) -> 11629 | L9: =IF(SUMIFS(Precios!$AG:$AG,Precios!$E:$E,$C$8,Precios!$AP:$AP,"<="&$C$4,Precios!$AQ:$AQ,">="&$C$4)>=0,SUMIFS(Precios!$AG:$AG,Precios!$E:$E,$C$8,Precios!$AP:$AP,"<="&$C$4,Precios!$AQ:$AQ,">="&$C$4)) -> 10489 | M9: =IF(SUMIFS(Precios!$AL:$AL,Precios!$E:$E,$C$8,Precios!$AP:$AP,"<="&$C$4,Precios!$AQ:$AQ,">="&$C$4)>=0,SUMIFS(Precios!$AL:$AL,Precios!$E:$E,$C$8,Precios!$AP:$AP,"<="&$C$4,Precios!$AQ:$AQ,">="&$C$4)) -> 10039
B10: PRECIO LISTA | C10: =VLOOKUP(C8,Precios!E:F,2,0) -> 19299 | F10: 24 Meses | G10: =IF(SUMIFS(Precios!$I:$I,Precios!$E:$E,$C$8,Precios!$AP:$AP,"<="&$C$4,Precios!$AQ:$AQ,">="&$C$4)>=0,SUMIFS(Precios!$I:$I,Precios!$E:$E,$C$8,Precios!$AP:$AP,"<="&$C$4,Precios!$AQ:$AQ,">="&$C$4)) -> 12539 | H10: =IF(SUMIFS(Precios!$N:$N,Precios!$E:$E,$C$8,Precios!$AP:$AP,"<="&$C$4,Precios!$AQ:$AQ,">="&$C$4)>=0,SUMIFS(Precios!$N:$N,Precios!$E:$E,$C$8,Precios!$AP:$AP,"<="&$C$4,Precios!$AQ:$AQ,">="&$C$4)) -> 12239 | I10: =IF(SUMIFS(Precios!$S:$S,Precios!$E:$E,$C$8,Precios!$AP:$AP,"<="&$C$4,Precios!$AQ:$AQ,">="&$C$4)>=0,SUMIFS(Precios!$S:$S,Precios!$E:$E,$C$8,Precios!$AP:$AP,"<="&$C$4,Precios!$AQ:$AQ,">="&$C$4)) -> 11929 | J10: =IF(SUMIFS(Precios!$X:$X,Precios!$E:$E,$C$8,Precios!$AP:$AP,"<="&$C$4,Precios!$AQ:$AQ,">="&$C$4)>=0,SUMIFS(Precios!$X:$X,Precios!$E:$E,$C$8,Precios!$AP:$AP,"<="&$C$4,Precios!$AQ:$AQ,">="&$C$4)) -> 11629 | K10: =IF(SUMIFS(Precios!$AC:$AC,Precios!$E:$E,$C$8,Precios!$AP:$AP,"<="&$C$4,Precios!$AQ:$AQ,">="&$C$4)>=0,SUMIFS(Precios!$AC:$AC,Precios!$E:$E,$C$8,Precios!$AP:$AP,"<="&$C$4,Precios!$AQ:$AQ,">="&$C$4)) -> 11019 | L10: =IF(SUMIFS(Precios!$AH:$AH,Precios!$E:$E,$C$8,Precios!$AP:$AP,"<="&$C$4,Precios!$AQ:$AQ,">="&$C$4)>=0,SUMIFS(Precios!$AH:$AH,Precios!$E:$E,$C$8,Precios!$AP:$AP,"<="&$C$4,Precios!$AQ:$AQ,">="&$C$4)) -> 9509 | M10: =IF(SUMIFS(Precios!$AM:$AM,Precios!$E:$E,$C$8,Precios!$AP:$AP,"<="&$C$4,Precios!$AQ:$AQ,">="&$C$4)>=0,SUMIFS(Precios!$AM:$AM,Precios!$E:$E,$C$8,Precios!$AP:$AP,"<="&$C$4,Precios!$AQ:$AQ,">="&$C$4)) -> 8899
F11: 36 Meses | G11: =IF(SUMIFS(Precios!$J:$J,Precios!$E:$E,$C$8,Precios!$AP:$AP,"<="&$C$4,Precios!$AQ:$AQ,">="&$C$4)>=0,SUMIFS(Precios!$J:$J,Precios!$E:$E,$C$8,Precios!$AP:$AP,"<="&$C$4,Precios!$AQ:$AQ,">="&$C$4)) -> 12089 | H11: =IF(SUMIFS(Precios!$O:$O,Precios!$E:$E,$C$8,Precios!$AP:$AP,"<="&$C$4,Precios!$AQ:$AQ,">="&$C$4)>=0,SUMIFS(Precios!$O:$O,Precios!$E:$E,$C$8,Precios!$AP:$AP,"<="&$C$4,Precios!$AQ:$AQ,">="&$C$4)) -> 11629 | I11: =IF(SUMIFS(Precios!$T:$T,Precios!$E:$E,$C$8,Precios!$AP:$AP,"<="&$C$4,Precios!$AQ:$AQ,">="&$C$4)>=0,SUMIFS(Precios!$T:$T,Precios!$E:$E,$C$8,Precios!$AP:$AP,"<="&$C$4,Precios!$AQ:$AQ,">="&$C$4)) -> 11179 | J11: =IF(SUMIFS(Precios!$Y:$Y,Precios!$E:$E,$C$8,Precios!$AP:$AP,"<="&$C$4,Precios!$AQ:$AQ,">="&$C$4)>=0,SUMIFS(Precios!$Y:$Y,Precios!$E:$E,$C$8,Precios!$AP:$AP,"<="&$C$4,Precios!$AQ:$AQ,">="&$C$4)) -> 10719 | K11: =IF(SUMIFS(Precios!$AD:$AD,Precios!$E:$E,$C$8,Precios!$AP:$AP,"<="&$C$4,Precios!$AQ:$AQ,">="&$C$4)>=0,SUMIFS(Precios!$AD:$AD,Precios!$E:$E,$C$8,Precios!$AP:$AP,"<="&$C$4,Precios!$AQ:$AQ,">="&$C$4)) -> 9809 | L11: =IF(SUMIFS(Precios!$AI:$AI,Precios!$E:$E,$C$8,Precios!$AP:$AP,"<="&$C$4,Precios!$AQ:$AQ,">="&$C$4)>=0,SUMIFS(Precios!$AI:$AI,Precios!$E:$E,$C$8,Precios!$AP:$AP,"<="&$C$4,Precios!$AQ:$AQ,">="&$C$4)) -> 7539 | M11: =IF(SUMIFS(Precios!$AN:$AN,Precios!$E:$E,$C$8,Precios!$AP:$AP,"<="&$C$4,Precios!$AQ:$AQ,">="&$C$4)>=0,SUMIFS(Precios!$AN:$AN,Precios!$E:$E,$C$8,Precios!$AP:$AP,"<="&$C$4,Precios!$AQ:$AQ,">="&$C$4)) -> 6629
B12: Precio Vigente - Vigencia Actual | F12: 48 Meses | G12: =IF(SUMIFS(Precios!$K:$K,Precios!$E:$E,$C$8,Precios!$AP:$AP,"<="&$C$4,Precios!$AQ:$AQ,">="&$C$4)>=0,SUMIFS(Precios!$K:$K,Precios!$E:$E,$C$8,Precios!$AP:$AP,"<="&$C$4,Precios!$AQ:$AQ,">="&$C$4)) -> 11629 | H12: =IF(SUMIFS(Precios!$P:$P,Precios!$E:$E,$C$8,Precios!$AP:$AP,"<="&$C$4,Precios!$AQ:$AQ,">="&$C$4)>=0,SUMIFS(Precios!$P:$P,Precios!$E:$E,$C$8,Precios!$AP:$AP,"<="&$C$4,Precios!$AQ:$AQ,">="&$C$4)) -> 11029 | I12: =IF(SUMIFS(Precios!$U:$U,Precios!$E:$E,$C$8,Precios!$AP:$AP,"<="&$C$4,Precios!$AQ:$AQ,">="&$C$4)>=0,SUMIFS(Precios!$U:$U,Precios!$E:$E,$C$8,Precios!$AP:$AP,"<="&$C$4,Precios!$AQ:$AQ,">="&$C$4)) -> 10419 | J12: =IF(SUMIFS(Precios!$Z:$Z,Precios!$E:$E,$C$8,Precios!$AP:$AP,"<="&$C$4,Precios!$AQ:$AQ,">="&$C$4)>=0,SUMIFS(Precios!$Z:$Z,Precios!$E:$E,$C$8,Precios!$AP:$AP,"<="&$C$4,Precios!$AQ:$AQ,">="&$C$4)) -> 9819 | K12: =IF(SUMIFS(Precios!$AE:$AE,Precios!$E:$E,$C$8,Precios!$AP:$AP,"<="&$C$4,Precios!$AQ:$AQ,">="&$C$4)>=0,SUMIFS(Precios!$AE:$AE,Precios!$E:$E,$C$8,Precios!$AP:$AP,"<="&$C$4,Precios!$AQ:$AQ,">="&$C$4)) -> 8599 | L12: =IF(SUMIFS(Precios!$AJ:$AJ,Precios!$E:$E,$C$8,Precios!$AP:$AP,"<="&$C$4,Precios!$AQ:$AQ,">="&$C$4)>=0,SUMIFS(Precios!$AJ:$AJ,Precios!$E:$E,$C$8,Precios!$AP:$AP,"<="&$C$4,Precios!$AQ:$AQ,">="&$C$4)) -> 5569 | M12: =IF(SUMIFS(Precios!$AO:$AO,Precios!$E:$E,$C$8,Precios!$AP:$AP,"<="&$C$4,Precios!$AQ:$AQ,">="&$C$4)>=0,SUMIFS(Precios!$AO:$AO,Precios!$E:$E,$C$8,Precios!$AP:$AP,"<="&$C$4,Precios!$AQ:$AQ,">="&$C$4)) -> 4359
B13: INICIO VIGENCIA | C13: FIN VIGENCIA
B14: =IF(SUMIFS(Precios!$AP:$AP,Precios!$E:$E,$C$8,Precios!$AP:$AP,"<="&$C$4,Precios!$AQ:$AQ,">="&$C$4)>=0,SUMIFS(Precios!$AP:$AP,Precios!$E:$E,$C$8,Precios!$AP:$AP,"<="&$C$4,Precios!$AQ:$AQ,">="&$C$4)) -> 46279 | C14: =IF(B16=DATEVALUE("01/01/2050"), "INDEFINIDO", B16) -> 46326
B15: FIN VIGENCIA*Ocultar | F15: PRÓXIMO PRECIO
B16: =IF(SUMIFS(Precios!$AQ:$AQ,Precios!$E:$E,$C$8,Precios!$AP:$AP,"<="&$C$4,Precios!$AQ:$AQ,">="&$C$4)>=0,SUMIFS(Precios!$AQ:$AQ,Precios!$E:$E,$C$8,Precios!$AP:$AP,"<="&$C$4,Precios!$AQ:$AQ,">="&$C$4)) -> 46326 | F16: Activación & Renovación - AT&T Ármalo Negocios
B17: Próximo Precio - Vigencia Próxima Inmediata | F17: Plan | G17: 299 | H17: 399 | I17: 499 | J17: 599 | K17: 799 | L17: 1299 | M17: 1499
B18: PRÓXIMO INICIO DE VIGENCIA | C18: =IF(B16<=DATEVALUE("01/12/2026"), B16+1, "NA") -> 46327 | F18: 12 Meses | G18: =IF(B16<DATEVALUE("01/01/2050"),IF(SUMIFS(Precios!$G:$G,Precios!$E:$E,$C$8,Precios!$AP:$AP,"<="&$C$18,Precios!$AQ:$AQ,">="&$C$18)>=0,SUMIFS(Precios!$G:$G,Precios!$E:$E,$C$8,Precios!$AP:$AP,"<="&$C$18,Precios!$AQ:$AQ,">="&$C$18)),"NA") -> 14989 | H18: =IF(B16<DATEVALUE("01/01/2050"),IF(SUMIFS(Precios!$L:$L,Precios!$E:$E,$C$8,Precios!$AP:$AP,"<="&$C$18,Precios!$AQ:$AQ,">="&$C$18)>=0,SUMIFS(Precios!$L:$L,Precios!$E:$E,$C$8,Precios!$AP:$AP,"<="&$C$18,Precios!$AQ:$AQ,">="&$C$18)),"NA") -> 14839 | I18: =IF(B16<DATEVALUE("01/01/2050"),IF(SUMIFS(Precios!$Q:$Q,Precios!$E:$E,$C$8,Precios!$AP:$AP,"<="&$C$18,Precios!$AQ:$AQ,">="&$C$18)>=0,SUMIFS(Precios!$Q:$Q,Precios!$E:$E,$C$8,Precios!$AP:$AP,"<="&$C$18,Precios!$AQ:$AQ,">="&$C$18)),"NA") -> 14689 | J18: =IF(B16<DATEVALUE("01/01/2050"),IF(SUMIFS(Precios!$V:$V,Precios!$E:$E,$C$8,Precios!$AP:$AP,"<="&$C$18,Precios!$AQ:$AQ,">="&$C$18)>=0,SUMIFS(Precios!$V:$V,Precios!$E:$E,$C$8,Precios!$AP:$AP,"<="&$C$18,Precios!$AQ:$AQ,">="&$C$18)),"NA") -> 14539 | K18: =IF(B16<DATEVALUE("01/01/2050"),IF(SUMIFS(Precios!$AA:$AA,Precios!$E:$E,$C$8,Precios!$AP:$AP,"<="&$C$18,Precios!$AQ:$AQ,">="&$C$18)>=0,SUMIFS(Precios!$AA:$AA,Precios!$E:$E,$C$8,Precios!$AP:$AP,"<="&$C$18,Precios!$AQ:$AQ,">="&$C$18)),"NA") -> 14229 | L18: =IF(B16<DATEVALUE("01/01/2050"),IF(SUMIFS(Precios!$AF:$AF,Precios!$E:$E,$C$8,Precios!$AP:$AP,"<="&$C$18,Precios!$AQ:$AQ,">="&$C$18)>=0,SUMIFS(Precios!$AF:$AF,Precios!$E:$E,$C$8,Precios!$AP:$AP,"<="&$C$18,Precios!$AQ:$AQ,">="&$C$18)),"NA") -> 13479 | M18: =IF(B16<DATEVALUE("01/01/2050"),IF(SUMIFS(Precios!$AK:$AK,Precios!$E:$E,$C$8,Precios!$AP:$AP,"<="&$C$18,Precios!$AQ:$AQ,">="&$C$18)>=0,SUMIFS(Precios!$AK:$AK,Precios!$E:$E,$C$8,Precios!$AP:$AP,"<="&$C$18,Precios!$AQ:$AQ,">="&$C$18)),"NA") -> 13169
B19: SIGUIENTE FIN VIGENCIA | C19: =IF(B20=DATEVALUE("01/01/2050"), "INDEFINIDO", B20) -> INDEFINIDO | F19: 18 Meses | G19: =IF(B16<DATEVALUE("01/01/2050"),IF(SUMIFS(Precios!$H:$H,Precios!$E:$E,$C$8,Precios!$AP:$AP,"<="&$C$18,Precios!$AQ:$AQ,">="&$C$18)>=0,SUMIFS(Precios!$H:$H,Precios!$E:$E,$C$8,Precios!$AP:$AP,"<="&$C$18,Precios!$AQ:$AQ,">="&$C$18)),"NA") -> 14759 | H19: =IF(B16<DATEVALUE("01/01/2050"),IF(SUMIFS(Precios!$M:$M,Precios!$E:$E,$C$8,Precios!$AP:$AP,"<="&$C$18,Precios!$AQ:$AQ,">="&$C$18)>=0,SUMIFS(Precios!$M:$M,Precios!$E:$E,$C$8,Precios!$AP:$AP,"<="&$C$18,Precios!$AQ:$AQ,">="&$C$18)),"NA") -> 14539 | I19: =IF(B16<DATEVALUE("01/01/2050"),IF(SUMIFS(Precios!$R:$R,Precios!$E:$E,$C$8,Precios!$AP:$AP,"<="&$C$18,Precios!$AQ:$AQ,">="&$C$18)>=0,SUMIFS(Precios!$R:$R,Precios!$E:$E,$C$8,Precios!$AP:$AP,"<="&$C$18,Precios!$AQ:$AQ,">="&$C$18)),"NA") -> 14309 | J19: =IF(B16<DATEVALUE("01/01/2050"),IF(SUMIFS(Precios!$W:$W,Precios!$E:$E,$C$8,Precios!$AP:$AP,"<="&$C$18,Precios!$AQ:$AQ,">="&$C$18)>=0,SUMIFS(Precios!$W:$W,Precios!$E:$E,$C$8,Precios!$AP:$AP,"<="&$C$18,Precios!$AQ:$AQ,">="&$C$18)),"NA") -> 14079 | K19: =IF(B16<DATEVALUE("01/01/2050"),IF(SUMIFS(Precios!$AB:$AB,Precios!$E:$E,$C$8,Precios!$AP:$AP,"<="&$C$18,Precios!$AQ:$AQ,">="&$C$18)>=0,SUMIFS(Precios!$AB:$AB,Precios!$E:$E,$C$8,Precios!$AP:$AP,"<="&$C$18,Precios!$AQ:$AQ,">="&$C$18)),"NA") -> 13629 | L19: =IF(B16<DATEVALUE("01/01/2050"),IF(SUMIFS(Precios!$AG:$AG,Precios!$E:$E,$C$8,Precios!$AP:$AP,"<="&$C$18,Precios!$AQ:$AQ,">="&$C$18)>=0,SUMIFS(Precios!$AG:$AG,Precios!$E:$E,$C$8,Precios!$AP:$AP,"<="&$C$18,Precios!$AQ:$AQ,">="&$C$18)),"NA") -> 12489 | M19: =IF(B16<DATEVALUE("01/01/2050"),IF(SUMIFS(Precios!$AL:$AL,Precios!$E:$E,$C$8,Precios!$AP:$AP,"<="&$C$18,Precios!$AQ:$AQ,">="&$C$18)>=0,SUMIFS(Precios!$AL:$AL,Precios!$E:$E,$C$8,Precios!$AP:$AP,"<="&$C$18,Precios!$AQ:$AQ,">="&$C$18)),"NA") -> 12039
B20: =IF(B16<=DATEVALUE("31/12/2026"),IF(SUMIFS(Precios!$AQ:$AQ,Precios!$E:$E,$C$8,Precios!$AP:$AP,"<="&$C$18,Precios!$AQ:$AQ,">="&$C$18)>=0,SUMIFS(Precios!$AQ:$AQ,Precios!$E:$E,$C$8,Precios!$AP:$AP,"<="&$C$18,Precios!$AQ:$AQ,">="&$C$18)),"NA") -> 54789 | F20: 24 Meses | G20: =IF(B16<DATEVALUE("01/01/2050"),IF(SUMIFS(Precios!$I:$I,Precios!$E:$E,$C$8,Precios!$AP:$AP,"<="&$C$18,Precios!$AQ:$AQ,">="&$C$18)>=0,SUMIFS(Precios!$I:$I,Precios!$E:$E,$C$8,Precios!$AP:$AP,"<="&$C$18,Precios!$AQ:$AQ,">="&$C$18)),"NA") -> 14539 | H20: =IF(B16<DATEVALUE("01/01/2050"),IF(SUMIFS(Precios!$N:$N,Precios!$E:$E,$C$8,Precios!$AP:$AP,"<="&$C$18,Precios!$AQ:$AQ,">="&$C$18)>=0,SUMIFS(Precios!$N:$N,Precios!$E:$E,$C$8,Precios!$AP:$AP,"<="&$C$18,Precios!$AQ:$AQ,">="&$C$18)),"NA") -> 14239 | I20: =IF(B16<DATEVALUE("01/01/2050"),IF(SUMIFS(Precios!$S:$S,Precios!$E:$E,$C$8,Precios!$AP:$AP,"<="&$C$18,Precios!$AQ:$AQ,">="&$C$18)>=0,SUMIFS(Precios!$S:$S,Precios!$E:$E,$C$8,Precios!$AP:$AP,"<="&$C$18,Precios!$AQ:$AQ,">="&$C$18)),"NA") -> 13929 | J20: =IF(B16<DATEVALUE("01/01/2050"),IF(SUMIFS(Precios!$X:$X,Precios!$E:$E,$C$8,Precios!$AP:$AP,"<="&$C$18,Precios!$AQ:$AQ,">="&$C$18)>=0,SUMIFS(Precios!$X:$X,Precios!$E:$E,$C$8,Precios!$AP:$AP,"<="&$C$18,Precios!$AQ:$AQ,">="&$C$18)),"NA") -> 13629 | K20: =IF(B16<DATEVALUE("01/01/2050"),IF(SUMIFS(Precios!$AC:$AC,Precios!$E:$E,$C$8,Precios!$AP:$AP,"<="&$C$18,Precios!$AQ:$AQ,">="&$C$18)>=0,SUMIFS(Precios!$AC:$AC,Precios!$E:$E,$C$8,Precios!$AP:$AP,"<="&$C$18,Precios!$AQ:$AQ,">="&$C$18)),"NA") -> 13019 | L20: =IF(B16<DATEVALUE("01/01/2050"),IF(SUMIFS(Precios!$AH:$AH,Precios!$E:$E,$C$8,Precios!$AP:$AP,"<="&$C$18,Precios!$AQ:$AQ,">="&$C$18)>=0,SUMIFS(Precios!$AH:$AH,Precios!$E:$E,$C$8,Precios!$AP:$AP,"<="&$C$18,Precios!$AQ:$AQ,">="&$C$18)),"NA") -> 11509 | M20: =IF(B16<DATEVALUE("01/01/2050"),IF(SUMIFS(Precios!$AM:$AM,Precios!$E:$E,$C$8,Precios!$AP:$AP,"<="&$C$18,Precios!$AQ:$AQ,">="&$C$18)>=0,SUMIFS(Precios!$AM:$AM,Precios!$E:$E,$C$8,Precios!$AP:$AP,"<="&$C$18,Precios!$AQ:$AQ,">="&$C$18)),"NA") -> 10899
F21: 36 Meses | G21: =IF(B16<DATEVALUE("01/01/2050"),IF(SUMIFS(Precios!$J:$J,Precios!$E:$E,$C$8,Precios!$AP:$AP,"<="&$C$18,Precios!$AQ:$AQ,">="&$C$18)>=0,SUMIFS(Precios!$J:$J,Precios!$E:$E,$C$8,Precios!$AP:$AP,"<="&$C$18,Precios!$AQ:$AQ,">="&$C$18)),"NA") -> 14089 | H21: =IF(B16<DATEVALUE("01/01/2050"),IF(SUMIFS(Precios!$O:$O,Precios!$E:$E,$C$8,Precios!$AP:$AP,"<="&$C$18,Precios!$AQ:$AQ,">="&$C$18)>=0,SUMIFS(Precios!$O:$O,Precios!$E:$E,$C$8,Precios!$AP:$AP,"<="&$C$18,Precios!$AQ:$AQ,">="&$C$18)),"NA") -> 13629 | I21: =IF(B16<DATEVALUE("01/01/2050"),IF(SUMIFS(Precios!$T:$T,Precios!$E:$E,$C$8,Precios!$AP:$AP,"<="&$C$18,Precios!$AQ:$AQ,">="&$C$18)>=0,SUMIFS(Precios!$T:$T,Precios!$E:$E,$C$8,Precios!$AP:$AP,"<="&$C$18,Precios!$AQ:$AQ,">="&$C$18)),"NA") -> 13179 | J21: =IF(B16<DATEVALUE("01/01/2050"),IF(SUMIFS(Precios!$Y:$Y,Precios!$E:$E,$C$8,Precios!$AP:$AP,"<="&$C$18,Precios!$AQ:$AQ,">="&$C$18)>=0,SUMIFS(Precios!$Y:$Y,Precios!$E:$E,$C$8,Precios!$AP:$AP,"<="&$C$18,Precios!$AQ:$AQ,">="&$C$18)),"NA") -> 12719 | K21: =IF(B16<DATEVALUE("01/01/2050"),IF(SUMIFS(Precios!$AD:$AD,Precios!$E:$E,$C$8,Precios!$AP:$AP,"<="&$C$18,Precios!$AQ:$AQ,">="&$C$18)>=0,SUMIFS(Precios!$AD:$AD,Precios!$E:$E,$C$8,Precios!$AP:$AP,"<="&$C$18,Precios!$AQ:$AQ,">="&$C$18)),"NA") -> 11809 | L21: =IF(B16<DATEVALUE("01/01/2050"),IF(SUMIFS(Precios!$AI:$AI,Precios!$E:$E,$C$8,Precios!$AP:$AP,"<="&$C$18,Precios!$AQ:$AQ,">="&$C$18)>=0,SUMIFS(Precios!$AI:$AI,Precios!$E:$E,$C$8,Precios!$AP:$AP,"<="&$C$18,Precios!$AQ:$AQ,">="&$C$18)),"NA") -> 9539 | M21: =IF(B16<DATEVALUE("01/01/2050"),IF(SUMIFS(Precios!$AN:$AN,Precios!$E:$E,$C$8,Precios!$AP:$AP,"<="&$C$18,Precios!$AQ:$AQ,">="&$C$18)>=0,SUMIFS(Precios!$AN:$AN,Precios!$E:$E,$C$8,Precios!$AP:$AP,"<="&$C$18,Precios!$AQ:$AQ,">="&$C$18)),"NA") -> 8629
F22: 48 Meses | G22: =IF(B16<DATEVALUE("01/01/2050"),IF(SUMIFS(Precios!$K:$K,Precios!$E:$E,$C$8,Precios!$AP:$AP,"<="&$C$18,Precios!$AQ:$AQ,">="&$C$18)>=0,SUMIFS(Precios!$K:$K,Precios!$E:$E,$C$8,Precios!$AP:$AP,"<="&$C$18,Precios!$AQ:$AQ,">="&$C$18)),"NA") -> 13629 | H22: =IF(B16<DATEVALUE("01/01/2050"),IF(SUMIFS(Precios!$P:$P,Precios!$E:$E,$C$8,Precios!$AP:$AP,"<="&$C$18,Precios!$AQ:$AQ,">="&$C$18)>=0,SUMIFS(Precios!$P:$P,Precios!$E:$E,$C$8,Precios!$AP:$AP,"<="&$C$18,Precios!$AQ:$AQ,">="&$C$18)),"NA") -> 13029 | I22: =IF(B16<DATEVALUE("01/01/2050"),IF(SUMIFS(Precios!$U:$U,Precios!$E:$E,$C$8,Precios!$AP:$AP,"<="&$C$18,Precios!$AQ:$AQ,">="&$C$18)>=0,SUMIFS(Precios!$U:$U,Precios!$E:$E,$C$8,Precios!$AP:$AP,"<="&$C$18,Precios!$AQ:$AQ,">="&$C$18)),"NA") -> 12419 | J22: =IF(B16<DATEVALUE("01/01/2050"),IF(SUMIFS(Precios!$Z:$Z,Precios!$E:$E,$C$8,Precios!$AP:$AP,"<="&$C$18,Precios!$AQ:$AQ,">="&$C$18)>=0,SUMIFS(Precios!$Z:$Z,Precios!$E:$E,$C$8,Precios!$AP:$AP,"<="&$C$18,Precios!$AQ:$AQ,">="&$C$18)),"NA") -> 11819 | K22: =IF(B16<DATEVALUE("01/01/2050"),IF(SUMIFS(Precios!$AE:$AE,Precios!$E:$E,$C$8,Precios!$AP:$AP,"<="&$C$18,Precios!$AQ:$AQ,">="&$C$18)>=0,SUMIFS(Precios!$AE:$AE,Precios!$E:$E,$C$8,Precios!$AP:$AP,"<="&$C$18,Precios!$AQ:$AQ,">="&$C$18)),"NA") -> 10599 | L22: =IF(B16<DATEVALUE("01/01/2050"),IF(SUMIFS(Precios!$AJ:$AJ,Precios!$E:$E,$C$8,Precios!$AP:$AP,"<="&$C$18,Precios!$AQ:$AQ,">="&$C$18)>=0,SUMIFS(Precios!$AJ:$AJ,Precios!$E:$E,$C$8,Precios!$AP:$AP,"<="&$C$18,Precios!$AQ:$AQ,">="&$C$18)),"NA") -> 7569 | M22: =IF(B16<DATEVALUE("01/01/2050"),IF(SUMIFS(Precios!$AO:$AO,Precios!$E:$E,$C$8,Precios!$AP:$AP,"<="&$C$18,Precios!$AQ:$AQ,">="&$C$18)>=0,SUMIFS(Precios!$AO:$AO,Precios!$E:$E,$C$8,Precios!$AP:$AP,"<="&$C$18,Precios!$AQ:$AQ,">="&$C$18)),"NA") -> 6359
B23: * Favor de considerar que para los equipos de la marca Samsung, se deberan consultar el "Inventario Simplificado Empresarial" en Insider para conocer las vigencia de los rebates.
B24: * El objetivo del cotizador, es mostrar los precios y vigencias actuales "como referencia".
B25: * La lista de precios se actualizará semanalmente, por lo que les pedimos revisar el archivo más actual.
B26: * Esta información no sustituye a los precios oficiales indicados en AVS, Digital y Sales Force (Modelador).
B27: * Si se requiere más detalle de los precios, favor de consultar las pestañas subsecuentes.
B28: * En el caso de los planes 199, 239, 699, 899 y 999, se debera considerar el precio de lista.

Sheet AT&T Armalo Neg 2.0
AW1: =UPPER(TEXT(AU1, " dd \ mmmm \ aa")&" - "&TEXT(AV1, " dd \ mmmm \ aa")) -> 00 ENERO 00 - 00 ENERO 00
F5: AT&T Armalo Negocios | L5: Ármalo Negocios 299 | Q5: Ármalo Negocios 399 | V5: Ármalo Negocios 499 | AA5: Ármalo Negocios 599 | AF5: Ármalo Negocios 799 | AK5: Ármalo Negocios 1299 | AP5: Ármalo Negocios 1499
A6: SAP | B6: Portal | C6: SKU | D6: Marca | E6: Nombre Completo | F6: Modelo | G6: Familia Homologada | H6: Tier | I6: Operador | J6: Precio Lista Sn/IVA | K6: Precio Lista Con IVA2 | L6: 12 Meses3 | M6: 18 Meses4 | N6: 24 Meses6 | O6: 36 Meses7 | P6: 48 Meses8 | Q6: 12 Meses22 | R6: 18 Meses33 | S6: 24 Meses44 | T6: 36 Meses55 | U6: 48 Meses66 | V6: 12 Meses23 | W6: 18 Meses34 | X6: 24 Meses45 | Y6: 36 Meses56 | Z6: 48 Meses67 | AA6: 12 Meses24 | AB6: 18 Meses35 | AC6: 24 Meses46 | AD6: 36 Meses57 | AE6: 48 Meses68 | AF6: 12 Meses26 | AG6: 18 Meses37 | AH6: 24 Meses48 | AI6: 36 Meses59 | AJ6: 48 Meses610 | AK6: 12 Meses272 | AL6: 18 Meses383 | AM6: 24 Meses494 | AN6: 36 Meses5105 | AO6: 48 Meses6116 | AP6: 12 Meses287 | AQ6: 18 Meses398 | AR6: 24 Meses4109 | AS6: 36 Meses51110 | AT6: 48 Meses61211 | AU6: Fecha Inicio | AV6: Fecha Fin | AW6: VIGENCIA
A7: 93523 | B7: 00935230 | C7: N.IP1164BL | D7: APPLE | E7: APPLE IPHONE 11 64GB BLANCO ATT | F7: Apple iPhone 11 64GB | G7: APPLE IPHONE 11 64GB 4G | H7: HIGH | I7: AT&T | J7: =K7/1.16 -> 9481.8966 | K7: 10999 | L7: 3849 | M7: 3499 | N7: 3149 | O7: 2499 | P7: 1799 | Q7: 3649 | R7: 3149 | S7: 2699 | T7: 1799 | U7: 899 | V7: 3399 | W7: 2849 | X7: 2249 | Y7: 1099 | Z7: 0 | AA7: 3149 | AB7: 2499 | AC7: 1799 | AD7: 449 | AE7: 0 | AF7: 2699 | AG7: 1799 | AH7: 899 | AI7: 0 | AJ7: 0 | AK7: 1549 | AL7: 99 | AM7: 0 | AN7: 0 | AO7: 0 | AP7: 1099 | AQ7: 0 | AR7: 0 | AS7: 0 | AT7: 0 | AU7: 46059 | AV7: INDEFINIDO | AW7: =UPPER(TEXT(AU7, " dd \ mmmm \ aa")&" - "&TEXT(AV7, " dd \ mmmm \ aa")) -> 06 FEBRERO 26 - INDEFINIDO
A8: 93526 | B8: 00935260 | C8: N.IP1164RJ | D8: APPLE | E8: APPLE IPHONE 11 64GB ROJO ATT | F8: Apple iPhone 11 64GB | G8: APPLE IPHONE 11 64GB 4G | H8: HIGH | I8: AT&T | J8: =K8/1.16 -> 9481.8966 | K8: 10999 | L8: 3849 | M8: 3499 | N8: 3149 | O8: 2499 | P8: 1799 | Q8: 3649 | R8: 3149 | S8: 2699 | T8: 1799 | U8: 899 | V8: 3399 | W8: 2849 | X8: 2249 | Y8: 1099 | Z8: 0 | AA8: 3149 | AB8: 2499 | AC8: 1799 | AD8: 449 | AE8: 0 | AF8: 2699 | AG8: 1799 | AH8: 899 | AI8: 0 | AJ8: 0 | AK8: 1549 | AL8: 99 | AM8: 0 | AN8: 0 | AO8: 0 | AP8: 1099 | AQ8: 0 | AR8: 0 | AS8: 0 | AT8: 0 | AU8: 46059 | AV8: INDEFINIDO | AW8: =UPPER(TEXT(AU8, " dd \ mmmm \ aa")&" - "&TEXT(AV8, " dd \ mmmm \ aa")) -> 06 FEBRERO 26 - INDEFINIDO
A9: 93520 | B9: 00935200 | C9: N.IP1164NG | D9: APPLE | E9: APPLE IPHONE 11 64GB NEGRO ATT | F9: Apple iPhone 11 64GB | G9: APPLE IPHONE 11 64GB 4G | H9: HIGH | I9: AT&T | J9: =K9/1.16 -> 9481.8966 | K9: 10999 | L9: 3849 | M9: 3499 | N9: 3149 | O9: 2499 | P9: 1799 | Q9: 3649 | R9: 3149 | S9: 2699 | T9: 1799 | U9: 899 | V9: 3399 | W9: 2849 | X9: 2249 | Y9: 1099 | Z9: 0 | AA9: 3149 | AB9: 2499 | AC9: 1799 | AD9: 449 | AE9: 0 | AF9: 2699 | AG9: 1799 | AH9: 899 | AI9: 0 | AJ9: 0 | AK9: 1549 | AL9: 99 | AM9: 0 | AN9: 0 | AO9: 0 | AP9: 1099 | AQ9: 0 | AR9: 0 | AS9: 0 | AT9: 0 | AU9: 46059 | AV9: INDEFINIDO | AW9: =UPPER(TEXT(AU9, " dd \ mmmm \ aa")&" - "&TEXT(AV9, " dd \ mmmm \ aa")) -> 06 FEBRERO 26 - INDEFINIDO
A10: 95520 | B10: 00955200 | C10: N.I1164LB | D10: APPLE | E10: APPLE IPHONE 11 64GB BLANCO CON CABLE DE LIGHTNING A U﻿S﻿B﻿-﻿C ATT | F10: Apple iPhone 11 64GB | G10: APPLE IPHONE 11 64GB 4G | H10: HIGH | I10: AT&T | J10: =K10/1.16 -> 9481.8966 | K10: 10999 | L10: 3849 | M10: 3499 | N10: 3149 | O10: 2499 | P10: 1799 | Q10: 3649 | R10: 3149 | S10: 2699 | T10: 1799 | U10: 899 | V10: 3399 | W10: 2849 | X10: 2249 | Y10: 1099 | Z10: 0 | AA10: 3149 | AB10: 2499 | AC10: 1799 | AD10: 449 | AE10: 0 | AF10: 2699 | AG10: 1799 | AH10: 899 | AI10: 0 | AJ10: 0 | AK10: 1549 | AL10: 99 | AM10: 0 | AN10: 0 | AO10: 0 | AP10: 1099 | AQ10: 0 | AR10: 0 | AS10: 0 | AT10: 0 | AU10: 46059 | AV10: INDEFINIDO | AW10: =UPPER(TEXT(AU10, " dd \ mmmm \ aa")&" - "&TEXT(AV10, " dd \ mmmm \ aa")) -> 06 FEBRERO 26 - INDEFINIDO
A11: 95524 | B11: 00955240 | C11: N.I1164LR | D11: APPLE | E11: APPLE IPHONE 11 64GB ROJO CON CABLE DE LIGHTNING A U﻿S﻿B﻿-﻿C ATT | F11: Apple iPhone 11 64GB | G11: APPLE IPHONE 11 64GB 4G | H11: HIGH | I11: AT&T | J11: =K11/1.16 -> 9481.8966 | K11: 10999 | L11: 3849 | M11: 3499 | N11: 3149 | O11: 2499 | P11: 1799 | Q11: 3649 | R11: 3149 | S11: 2699 | T11: 1799 | U11: 899 | V11: 3399 | W11: 2849 | X11: 2249 | Y11: 1099 | Z11: 0 | AA11: 3149 | AB11: 2499 | AC11: 1799 | AD11: 449 | AE11: 0 | AF11: 2699 | AG11: 1799 | AH11: 899 | AI11: 0 | AJ11: 0 | AK11: 1549 | AL11: 99 | AM11: 0 | AN11: 0 | AO11: 0 | AP11: 1099 | AQ11: 0 | AR11: 0 | AS11: 0 | AT11: 0 | AU11: 46059 | AV11: INDEFINIDO | AW11: =UPPER(TEXT(AU11, " dd \ mmmm \ aa")&" - "&TEXT(AV11, " dd \ mmmm \ aa")) -> 06 FEBRERO 26 - INDEFINIDO
A12: 95516 | B12: 00955160 | C12: N.I1164LN | D12: APPLE | E12: APPLE IPHONE 11 64GB NEGRO CON CABLE DE LIGHTNING A U﻿S﻿B﻿-﻿C ATT | F12: Apple iPhone 11 64GB | G12: APPLE IPHONE 11 64GB 4G | H12: =IF(K12="REVISAR","REVISAR",IF(K12>=20000,"FLAGSHIP",IF(K12>=12000,"PREMIUM",IF(K12>=7000,"HIGH",IF(K12>=5000,"MID",IF(K12>=3000,"LOW","ENTRY")))))) -> HIGH | I12: AT&T | J12: =K12/1.16 -> 9481.8966 | K12: 10999 | L12: 3849 | M12: 3499 | N12: 3149 | O12: 2499 | P12: 1799 | Q12: 3649 | R12: 3149 | S12: 2699 | T12: 1799 | U12: 899 | V12: 3399 | W12: 2849 | X12: 2249 | Y12: 1099 | Z12: 0 | AA12: 3149 | AB12: 2499 | AC12: 1799 | AD12: 449 | AE12: 0 | AF12: 2699 | AG12: 1799 | AH12: 899 | AI12: 0 | AJ12: 0 | AK12: 1549 | AL12: 99 | AM12: 0 | AN12: 0 | AO12: 0 | AP12: 1099 | AQ12: 0 | AR12: 0 | AS12: 0 | AT12: 0 | AU12: 46059 | AV12: INDEFINIDO | AW12: =UPPER(TEXT(AU12, " dd \ mmmm \ aa")&" - "&TEXT(AV12, " dd \ mmmm \ aa")) -> 06 FEBRERO 26 - INDEFINIDO
A13: 95316 | B13: 95316 | C13: N.IP1264AZ | D13: APPLE | E13: APPLE IPHONE 12 64GB AZUL ATT | F13: Apple iPhone 12 64GB | G13: APPLE IPHONE 12 64GB 4G | H13: PREMIUM | I13: AT&T | J13: =K13/1.16 -> 10775 | K13: 12499 | L13: 10899 | M13: 10699 | N13: 10499 | O13: 9999 | P13: 9599 | Q13: 10799 | R13: 10499 | S13: 10199 | T13: 9599 | U13: 8999 | V13: 10599 | W13: 10199 | X13: 9899 | Y13: 9099 | Z13: 8399 | AA13: 10499 | AB13: 9999 | AC13: 9599 | AD13: 8699 | AE13: 7799 | AF13: 10199 | AG13: 9599 | AH13: 8999 | AI13: 7799 | AJ13: 6599 | AK13: 9399 | AL13: 8399 | AM13: 7499 | AN13: 5499 | AO13: 3599 | AP13: 9099 | AQ13: 7999 | AR13: 6899 | AS13: 4599 | AT13: 2399 | AU13: 45505 | AV13: INDEFINIDO | AW13: 01 Agosto 2024 - INDEFINIDO
A14: 95304 | B14: 95304 | C14: N.IP1264BL | D14: APPLE | E14: APPLE IPHONE 12 64GB BLANCO ATT | F14: Apple iPhone 12 64GB | G14: APPLE IPHONE 12 64GB 4G | H14: PREMIUM | I14: AT&T | J14: =K14/1.16 -> 10775 | K14: 12499 | L14: 10899 | M14: 10699 | N14: 10499 | O14: 9999 | P14: 9599 | Q14: 10799 | R14: 10499 | S14: 10199 | T14: 9599 | U14: 8999 | V14: 10599 | W14: 10199 | X14: 9899 | Y14: 9099 | Z14: 8399 | AA14: 10499 | AB14: 9999 | AC14: 9599 | AD14: 8699 | AE14: 7799 | AF14: 10199 | AG14: 9599 | AH14: 8999 | AI14: 7799 | AJ14: 6599 | AK14: 9399 | AL14: 8399 | AM14: 7499 | AN14: 5499 | AO14: 3599 | AP14: 9099 | AQ14: 7999 | AR14: 6899 | AS14: 4599 | AT14: 2399 | AU14: 45505 | AV14: INDEFINIDO | AW14: 01 Agosto 2024 - INDEFINIDO
A15: 96152 | B15: 96152 | C15: N.IP1264MD | D15: APPLE | E15: APPLE IPHONE 12 64GB MORADO ATT | F15: Apple iPhone 12 64GB | G15: APPLE IPHONE 12 64GB 4G | H15: PREMIUM | I15: AT&T | J15: =K15/1.16 -> 10775 | K15: 12499 | L15: 10899 | M15: 10699 | N15: 10499 | O15: 9999 | P15: 9599 | Q15: 10799 | R15: 10499 | S15: 10199 | T15: 9599 | U15: 8999 | V15: 10599 | W15: 10199 | X15: 9899 | Y15: 9099 | Z15: 8399 | AA15: 10499 | AB15: 9999 | AC15: 9599 | AD15: 8699 | AE15: 7799 | AF15: 10199 | AG15: 9599 | AH15: 8999 | AI15: 7799 | AJ15: 6599 | AK15: 9399 | AL15: 8399 | AM15: 7499 | AN15: 5499 | AO15: 3599 | AP15: 9099 | AQ15: 7999 | AR15: 6899 | AS15: 4599 | AT15: 2399 | AU15: 45505 | AV15: INDEFINIDO | AW15: 01 Agosto 2024 - INDEFINIDO
A16: 95300 | B16: 95300 | C16: N.IP1264NG | D16: APPLE | E16: APPLE IPHONE 12 64GB NEGRO ATT | F16: Apple iPhone 12 64GB | G16: APPLE IPHONE 12 64GB 4G | H16: PREMIUM | I16: AT&T | J16: =K16/1.16 -> 10775 | K16: 12499 | L16: 10899 | M16: 10699 | N16: 10499 | O16: 9999 | P16: 9599 | Q16: 10799 | R16: 10499 | S16: 10199 | T16: 9599 | U16: 8999 | V16: 10599 | W16: 10199 | X16: 9899 | Y16: 9099 | Z16: 8399 | AA16: 10499 | AB16: 9999 | AC16: 9599 | AD16: 8699 | AE16: 7799 | AF16: 10199 | AG16: 9599 | AH16: 8999 | AI16: 7799 | AJ16: 6599 | AK16: 9399 | AL16: 8399 | AM16: 7499 | AN16: 5499 | AO16: 3599 | AP16: 9099 | AQ16: 7999 | AR16: 6899 | AS16: 4599 | AT16: 2399 | AU16: 45505 | AV16: INDEFINIDO | AW16: 01 Agosto 2024 - INDEFINIDO
A17: 95308 | B17: 95308 | C17: N.IP1264RJ | D17: APPLE | E17: APPLE IPHONE 12 64GB ROJO ATT | F17: Apple iPhone 12 64GB | G17: APPLE IPHONE 12 64GB 4G | H17: PREMIUM | I17: AT&T | J17: =K17/1.16 -> 10775 | K17: 12499 | L17: 10899 | M17: 10699 | N17: 10499 | O17: 9999 | P17: 9599 | Q17: 10799 | R17: 10499 | S17: 10199 | T17: 9599 | U17: 8999 | V17: 10599 | W17: 10199 | X17: 9899 | Y17: 9099 | Z17: 8399 | AA17: 10499 | AB17: 9999 | AC17: 9599 | AD17: 8699 | AE17: 7799 | AF17: 10199 | AG17: 9599 | AH17: 8999 | AI17: 7799 | AJ17: 6599 | AK17: 9399 | AL17: 8399 | AM17: 7499 | AN17: 5499 | AO17: 3599 | AP17: 9099 | AQ17: 7999 | AR17: 6899 | AS17: 4599 | AT17: 2399 | AU17: 45505 | AV17: INDEFINIDO | AW17: 01 Agosto 2024 - INDEFINIDO
A18: 95312 | B18: 95312 | C18: N.IP1264VD | D18: APPLE | E18: APPLE IPHONE 12 64GB VERDE ATT | F18: Apple iPhone 12 64GB | G18: APPLE IPHONE 12 64GB 4G | H18: PREMIUM | I18: AT&T | J18: =K18/1.16 -> 10775 | K18: 12499 | L18: 10899 | M18: 10699 | N18: 10499 | O18: 9999 | P18: 9599 | Q18: 10799 | R18: 10499 | S18: 10199 | T18: 9599 | U18: 8999 | V18: 10599 | W18: 10199 | X18: 9899 | Y18: 9099 | Z18: 8399 | AA18: 10499 | AB18: 9999 | AC18: 9599 | AD18: 8699 | AE18: 7799 | AF18: 10199 | AG18: 9599 | AH18: 8999 | AI18: 7799 | AJ18: 6599 | AK18: 9399 | AL18: 8399 | AM18: 7499 | AN18: 5499 | AO18: 3599 | AP18: 9099 | AQ18: 7999 | AR18: 6899 | AS18: 4599 | AT18: 2399 | AU18: 45505 | AV18: INDEFINIDO | AW18: 01 Agosto 2024 - INDEFINIDO
A19: 96603 | B19: 00966030 | C19: N.I13128PA | D19: APPLE | E19: APPLE IPHONE 13 128GB AZUL ATT | F19: Apple iPhone 13 128GB | G19: APPLE IPHONE 13 128GB 4G | H19: =IF(K19="REVISAR","REVISAR",IF(K19>=20000,"FLAGSHIP",IF(K19>=12000,"PREMIUM",IF(K19>=7000,"HIGH",IF(K19>=5000,"MID",IF(K19>=3000,"LOW","ENTRY")))))) -> PREMIUM | I19: AT&T | J19: =K19/1.16 -> 11206.034 | K19: 12999 | L19: 9099 | M19: 8749 | N19: 8399 | O19: 7699 | P19: 7049 | Q19: 8849 | R19: 8399 | S19: 7949 | T19: 7049 | U19: 6149 | V19: 8649 | W19: 8049 | X19: 7499 | Y19: 6349 | Z19: 5199 | AA19: 8399 | AB19: 7699 | AC19: 7049 | AD19: 5649 | AE19: 4299 | AF19: 7949 | AG19: 7049 | AH19: 6099 | AI19: 4299 | AJ19: 2499 | AK19: 6799 | AL19: 5299 | AM19: 3849 | AN19: 899 | AO19: 0 | AP19: 6349 | AQ19: 4649 | AR19: 2949 | AS19: 0 | AT19: 0 | AU19: 46110 | AV19: INDEFINIDO | AW19: =UPPER(TEXT(AU19, " dd \ mmmm \ aa")&" - "&TEXT(AV19, " dd \ mmmm \ aa")) -> 29 MARZO 26 - INDEFINIDO
A20: 96599 | B20: 00965990 | C20: N.I13128PR | D20: APPLE | E20: APPLE IPHONE 13 128GB ROJO ATT | F20: Apple iPhone 13 128GB | G20: APPLE IPHONE 13 128GB 4G | H20: =IF(K20="REVISAR","REVISAR",IF(K20>=20000,"FLAGSHIP",IF(K20>=12000,"PREMIUM",IF(K20>=7000,"HIGH",IF(K20>=5000,"MID",IF(K20>=3000,"LOW","ENTRY")))))) -> PREMIUM | I20: AT&T | J20: =K20/1.16 -> 11206.034 | K20: 12999 | L20: 9099 | M20: 8749 | N20: 8399 | O20: 7699 | P20: 7049 | Q20: 8849 | R20: 8399 | S20: 7949 | T20: 7049 | U20: 6149 | V20: 8649 | W20: 8049 | X20: 7499 | Y20: 6349 | Z20: 5199 | AA20: 8399 | AB20: 7699 | AC20: 7049 | AD20: 5649 | AE20: 4299 | AF20: 7949 | AG20: 7049 | AH20: 6099 | AI20: 4299 | AJ20: 2499 | AK20: 6799 | AL20: 5299 | AM20: 3849 | AN20: 899 | AO20: 0 | AP20: 6349 | AQ20: 4649 | AR20: 2949 | AS20: 0 | AT20: 0 | AU20: 46110 | AV20: INDEFINIDO | AW20: =UPPER(TEXT(AU20, " dd \ mmmm \ aa")&" - "&TEXT(AV20, " dd \ mmmm \ aa")) -> 29 MARZO 26 - INDEFINIDO
A21: 96595 | B21: 00965950 | C21: N.I13128PS | D21: APPLE | E21: APPLE IPHONE 13 128GB ROSA ATT | F21: Apple iPhone 13 128GB | G21: APPLE IPHONE 13 128GB 4G | H21: =IF(K21="REVISAR","REVISAR",IF(K21>=20000,"FLAGSHIP",IF(K21>=12000,"PREMIUM",IF(K21>=7000,"HIGH",IF(K21>=5000,"MID",IF(K21>=3000,"LOW","ENTRY")))))) -> PREMIUM | I21: AT&T | J21: =K21/1.16 -> 11206.034 | K21: 12999 | L21: 9099 | M21: 8749 | N21: 8399 | O21: 7699 | P21: 7049 | Q21: 8849 | R21: 8399 | S21: 7949 | T21: 7049 | U21: 6149 | V21: 8649 | W21: 8049 | X21: 7499 | Y21: 6349 | Z21: 5199 | AA21: 8399 | AB21: 7699 | AC21: 7049 | AD21: 5649 | AE21: 4299 | AF21: 7949 | AG21: 7049 | AH21: 6099 | AI21: 4299 | AJ21: 2499 | AK21: 6799 | AL21: 5299 | AM21: 3849 | AN21: 899 | AO21: 0 | AP21: 6349 | AQ21: 4649 | AR21: 2949 | AS21: 0 | AT21: 0 | AU21: 46110 | AV21: INDEFINIDO | AW21: =UPPER(TEXT(AU21, " dd \ mmmm \ aa")&" - "&TEXT(AV21, " dd \ mmmm \ aa")) -> 29 MARZO 26 - INDEFINIDO
A22: 97658 | B22: 00976580 | C22: N.I13128PV | D22: APPLE | E22: APPLE IPHONE 13 128GB VERDE ATT | F22: Apple iPhone 13 128GB | G22: APPLE IPHONE 13 128GB 4G | H22: =IF(K22="REVISAR","REVISAR",IF(K22>=20000,"FLAGSHIP",IF(K22>=12000,"PREMIUM",IF(K22>=7000,"HIGH",IF(K22>=5000,"MID",IF(K22>=3000,"LOW","ENTRY")))))) -> PREMIUM | I22: AT&T | J22: =K22/1.16 -> 11206.034 | K22: 12999 | L22: 9099 | M22: 8749 | N22: 8399 | O22: 7699 | P22: 7049 | Q22: 8849 | R22: 8399 | S22: 7949 | T22: 7049 | U22: 6149 | V22: 8649 | W22: 8049 | X22: 7499 | Y22: 6349 | Z22: 5199 | AA22: 8399 | AB22: 7699 | AC22: 7049 | AD22: 5649 | AE22: 4299 | AF22: 7949 | AG22: 7049 | AH22: 6099 | AI22: 4299 | AJ22: 2499 | AK22: 6799 | AL22: 5299 | AM22: 3849 | AN22: 899 | AO22: 0 | AP22: 6349 | AQ22: 4649 | AR22: 2949 | AS22: 0 | AT22: 0 | AU22: 46110 | AV22: INDEFINIDO | AW22: =UPPER(TEXT(AU22, " dd \ mmmm \ aa")&" - "&TEXT(AV22, " dd \ mmmm \ aa")) -> 29 MARZO 26 - INDEFINIDO
A23: 96591 | B23: 00965910 | C23: N.I13128PB | D23: APPLE | E23: APPLE IPHONE 13 128GB BLANCO ESTRELLA ATT | F23: Apple iPhone 13 128GB | G23: APPLE IPHONE 13 128GB 4G | H23: =IF(K23="REVISAR","REVISAR",IF(K23>=20000,"FLAGSHIP",IF(K23>=12000,"PREMIUM",IF(K23>=7000,"HIGH",IF(K23>=5000,"MID",IF(K23>=3000,"LOW","ENTRY")))))) -> PREMIUM | I23: AT&T | J23: =K23/1.16 -> 11206.034 | K23: 12999 | L23: 9099 | M23: 8749 | N23: 8399 | O23: 7699 | P23: 7049 | Q23: 8849 | R23: 8399 | S23: 7949 | T23: 7049 | U23: 6149 | V23: 8649 | W23: 8049 | X23: 7499 | Y23: 6349 | Z23: 5199 | AA23: 8399 | AB23: 7699 | AC23: 7049 | AD23: 5649 | AE23: 4299 | AF23: 7949 | AG23: 7049 | AH23: 6099 | AI23: 4299 | AJ23: 2499 | AK23: 6799 | AL23: 5299 | AM23: 3849 | AN23: 899 | AO23: 0 | AP23: 6349 | AQ23: 4649 | AR23: 2949 | AS23: 0 | AT23: 0 | AU23: 46110 | AV23: INDEFINIDO | AW23: =UPPER(TEXT(AU23, " dd \ mmmm \ aa")&" - "&TEXT(AV23, " dd \ mmmm \ aa")) -> 29 MARZO 26 - INDEFINIDO
A24: 96587 | B24: 00965870 | C24: N.I13128PN | D24: APPLE | E24: APPLE IPHONE 13 128GB MEDIA NOCHE ATT | F24: Apple iPhone 13 128GB | G24: APPLE IPHONE 13 128GB 4G | H24: =IF(K24="REVISAR","REVISAR",IF(K24>=20000,"FLAGSHIP",IF(K24>=12000,"PREMIUM",IF(K24>=7000,"HIGH",IF(K24>=5000,"MID",IF(K24>=3000,"LOW","ENTRY")))))) -> PREMIUM | I24: AT&T | J24: =K24/1.16 -> 11206.034 | K24: 12999 | L24: 9099 | M24: 8749 | N24: 8399 | O24: 7699 | P24: 7049 | Q24: 8849 | R24: 8399 | S24: 7949 | T24: 7049 | U24: 6149 | V24: 8649 | W24: 8049 | X24: 7499 | Y24: 6349 | Z24: 5199 | AA24: 8399 | AB24: 7699 | AC24: 7049 | AD24: 5649 | AE24: 4299 | AF24: 7949 | AG24: 7049 | AH24: 6099 | AI24: 4299 | AJ24: 2499 | AK24: 6799 | AL24: 5299 | AM24: 3849 | AN24: 899 | AO24: 0 | AP24: 6349 | AQ24: 4649 | AR24: 2949 | AS24: 0 | AT24: 0 | AU24: 46110 | AV24: INDEFINIDO | AW24: =UPPER(TEXT(AU24, " dd \ mmmm \ aa")&" - "&TEXT(AV24, " dd \ mmmm \ aa")) -> 29 MARZO 26 - INDEFINIDO
A25: 99420 | B25: 00994200 | C25: N.I14128AM | D25: APPLE | E25: IPHONE 14 128GB AMARILLO ATT | F25: Apple iPhone 14 128GB | G25: APPLE IPHONE 14 128GB 4G | H25: =IF(K25="REVISAR","REVISAR",IF(K25>=20000,"FLAGSHIP",IF(K25>=12000,"PREMIUM",IF(K25>=7000,"HIGH",IF(K25>=5000,"MID",IF(K25>=3000,"LOW","ENTRY")))))) -> PREMIUM | I25: AT&T | J25: =K25/1.16 -> 12930.172 | K25: 14999 | L25: 10849 | M25: 10599 | N25: 10399 | O25: 9949 | P25: 9499 | Q25: 10699 | R25: 10399 | S25: 10099 | T25: 9499 | U25: 8949 | V25: 10549 | W25: 10149 | X25: 9799 | Y25: 9099 | Z25: 8349 | AA25: 10399 | AB25: 9949 | AC25: 9499 | AD25: 8649 | AE25: 7749 | AF25: 10099 | AG25: 9499 | AH25: 8949 | AI25: 7749 | AJ25: 6599 | AK25: 9349 | AL25: 8449 | AM25: 7499 | AN25: 5599 | AO25: 3699 | AP25: 9099 | AQ25: 7999 | AR25: 6899 | AS25: 4699 | AT25: 2549 | AU25: 45954 | AV25: INDEFINIDO | AW25: =UPPER(TEXT(AU25, " dd \ mmmm \ aa")&" - "&TEXT(AV25, " dd \ mmmm \ aa")) -> 24 OCTUBRE 25 - INDEFINIDO
A26: 98679 | B26: 00986790 | C26: N.I14128A | D26: APPLE | E26: IPHONE 14 128GB AZUL ATT | F26: Apple iPhone 14 128GB | G26: APPLE IPHONE 14 128GB 4G | H26: =IF(K26="REVISAR","REVISAR",IF(K26>=20000,"FLAGSHIP",IF(K26>=12000,"PREMIUM",IF(K26>=7000,"HIGH",IF(K26>=5000,"MID",IF(K26>=3000,"LOW","ENTRY")))))) -> PREMIUM | I26: AT&T | J26: =K26/1.16 -> 12930.172 | K26: 14999 | L26: 10849 | M26: 10599 | N26: 10399 | O26: 9949 | P26: 9499 | Q26: 10699 | R26: 10399 | S26: 10099 | T26: 9499 | U26: 8949 | V26: 10549 | W26: 10149 | X26: 9799 | Y26: 9099 | Z26: 8349 | AA26: 10399 | AB26: 9949 | AC26: 9499 | AD26: 8649 | AE26: 7749 | AF26: 10099 | AG26: 9499 | AH26: 8949 | AI26: 7749 | AJ26: 6599 | AK26: 9349 | AL26: 8449 | AM26: 7499 | AN26: 5599 | AO26: 3699 | AP26: 9099 | AQ26: 7999 | AR26: 6899 | AS26: 4699 | AT26: 2549 | AU26: 45954 | AV26: INDEFINIDO | AW26: =UPPER(TEXT(AU26, " dd \ mmmm \ aa")&" - "&TEXT(AV26, " dd \ mmmm \ aa")) -> 24 OCTUBRE 25 - INDEFINIDO
A27: 98670 | B27: 00986700 | C27: N.I14128B | D27: APPLE | E27: IPHONE 14 128GB BLANCO ESTELAR ATT | F27: Apple iPhone 14 128GB | G27: APPLE IPHONE 14 128GB 4G | H27: =IF(K27="REVISAR","REVISAR",IF(K27>=20000,"FLAGSHIP",IF(K27>=12000,"PREMIUM",IF(K27>=7000,"HIGH",IF(K27>=5000,"MID",IF(K27>=3000,"LOW","ENTRY")))))) -> PREMIUM | I27: AT&T | J27: =K27/1.16 -> 12930.172 | K27: 14999 | L27: 10849 | M27: 10599 | N27: 10399 | O27: 9949 | P27: 9499 | Q27: 10699 | R27: 10399 | S27: 10099 | T27: 9499 | U27: 8949 | V27: 10549 | W27: 10149 | X27: 9799 | Y27: 9099 | Z27: 8349 | AA27: 10399 | AB27: 9949 | AC27: 9499 | AD27: 8649 | AE27: 7749 | AF27: 10099 | AG27: 9499 | AH27: 8949 | AI27: 7749 | AJ27: 6599 | AK27: 9349 | AL27: 8449 | AM27: 7499 | AN27: 5599 | AO27: 3699 | AP27: 9099 | AQ27: 7999 | AR27: 6899 | AS27: 4699 | AT27: 2549 | AU27: 45954 | AV27: INDEFINIDO | AW27: =UPPER(TEXT(AU27, " dd \ mmmm \ aa")&" - "&TEXT(AV27, " dd \ mmmm \ aa")) -> 24 OCTUBRE 25 - INDEFINIDO
A28: 98673 | B28: 00986730 | C28: N.I14128M | D28: APPLE | E28: IPHONE 14 128GB MORADO ATT | F28: Apple iPhone 14 128GB | G28: APPLE IPHONE 14 128GB 4G | H28: =IF(K28="REVISAR","REVISAR",IF(K28>=20000,"FLAGSHIP",IF(K28>=12000,"PREMIUM",IF(K28>=7000,"HIGH",IF(K28>=5000,"MID",IF(K28>=3000,"LOW","ENTRY")))))) -> PREMIUM | I28: AT&T | J28: =K28/1.16 -> 12930.172 | K28: 14999 | L28: 10849 | M28: 10599 | N28: 10399 | O28: 9949 | P28: 9499 | Q28: 10699 | R28: 10399 | S28: 10099 | T28: 9499 | U28: 8949 | V28: 10549 | W28: 10149 | X28: 9799 | Y28: 9099 | Z28: 8349 | AA28: 10399 | AB28: 9949 | AC28: 9499 | AD28: 8649 | AE28: 7749 | AF28: 10099 | AG28: 9499 | AH28: 8949 | AI28: 7749 | AJ28: 6599 | AK28: 9349 | AL28: 8449 | AM28: 7499 | AN28: 5599 | AO28: 3699 | AP28: 9099 | AQ28: 7999 | AR28: 6899 | AS28: 4699 | AT28: 2549 | AU28: 45954 | AV28: INDEFINIDO | AW28: =UPPER(TEXT(AU28, " dd \ mmmm \ aa")&" - "&TEXT(AV28, " dd \ mmmm \ aa")) -> 24 OCTUBRE 25 - INDEFINIDO
A29: 98676 | B29: 00986760 | C29: N.I14128R | D29: APPLE | E29: IPHONE 14 128GB ROJO ATT | F29: Apple iPhone 14 128GB | G29: APPLE IPHONE 14 128GB 4G | H29: =IF(K29="REVISAR","REVISAR",IF(K29>=20000,"FLAGSHIP",IF(K29>=12000,"PREMIUM",IF(K29>=7000,"HIGH",IF(K29>=5000,"MID",IF(K29>=3000,"LOW","ENTRY")))))) -> PREMIUM | I29: AT&T | J29: =K29/1.16 -> 12930.172 | K29: 14999 | L29: 10849 | M29: 10599 | N29: 10399 | O29: 9949 | P29: 9499 | Q29: 10699 | R29: 10399 | S29: 10099 | T29: 9499 | U29: 8949 | V29: 10549 | W29: 10149 | X29: 9799 | Y29: 9099 | Z29: 8349 | AA29: 10399 | AB29: 9949 | AC29: 9499 | AD29: 8649 | AE29: 7749 | AF29: 10099 | AG29: 9499 | AH29: 8949 | AI29: 7749 | AJ29: 6599 | AK29: 9349 | AL29: 8449 | AM29: 7499 | AN29: 5599 | AO29: 3699 | AP29: 9099 | AQ29: 7999 | AR29: 6899 | AS29: 4699 | AT29: 2549 | AU29: 45954 | AV29: INDEFINIDO | AW29: =UPPER(TEXT(AU29, " dd \ mmmm \ aa")&" - "&TEXT(AV29, " dd \ mmmm \ aa")) -> 24 OCTUBRE 25 - INDEFINIDO
A30: 98667 | B30: 00986670 | C30: N.I14128N | D30: APPLE | E30: IPHONE 14 128GB MEDIANOCHE ATT | F30: Apple iPhone 14 128GB | G30: APPLE IPHONE 14 128GB 4G | H30: =IF(K30="REVISAR","REVISAR",IF(K30>=20000,"FLAGSHIP",IF(K30>=12000,"PREMIUM",IF(K30>=7000,"HIGH",IF(K30>=5000,"MID",IF(K30>=3000,"LOW","ENTRY")))))) -> PREMIUM | I30: AT&T | J30: =K30/1.16 -> 12930.172 | K30: 14999 | L30: 10849 | M30: 10599 | N30: 10399 | O30: 9949 | P30: 9499 | Q30: 10699 | R30: 10399 | S30: 10099 | T30: 9499 | U30: 8949 | V30: 10549 | W30: 10149 | X30: 9799 | Y30: 9099 | Z30: 8349 | AA30: 10399 | AB30: 9949 | AC30: 9499 | AD30: 8649 | AE30: 7749 | AF30: 10099 | AG30: 9499 | AH30: 8949 | AI30: 7749 | AJ30: 6599 | AK30: 9349 | AL30: 8449 | AM30: 7499 | AN30: 5599 | AO30: 3699 | AP30: 9099 | AQ30: 7999 | AR30: 6899 | AS30: 4699 | AT30: 2549 | AU30: 45954 | AV30: INDEFINIDO | AW30: =UPPER(TEXT(AU30, " dd \ mmmm \ aa")&" - "&TEXT(AV30, " dd \ mmmm \ aa")) -> 24 OCTUBRE 25 - INDEFINIDO
A31: 99423 | B31: 00994230 | C31: N.I14256AM | D31: APPLE | E31: IPHONE 14 256GB AMARILLO ATT | F31: Apple iPhone 14 256GB | G31: APPLE IPHONE 14 256GB 4G | H31: PREMIUM | I31: AT&T | J31: =K31/1.16 -> 15085.345 | K31: 17499 | L31: 10759 | M31: 10559 | N31: 10299 | O31: 9859 | P31: 9459 | Q31: 10599 | R31: 10299 | S31: 9999 | T31: 9459 | U31: 8859 | V31: 10459 | W31: 10099 | X31: 9759 | Y31: 8999 | Z31: 8259 | AA31: 10299 | AB31: 9859 | AC31: 9459 | AD31: 8559 | AE31: 7699 | AF31: 9999 | AG31: 9459 | AH31: 8859 | AI31: 7699 | AJ31: 6499 | AK31: 9299 | AL31: 8359 | AM31: 7399 | AN31: 5499 | AO31: 3599 | AP31: 8999 | AQ31: 7899 | AR31: 6799 | AS31: 4659 | AT31: 2459 | AU31: 45572 | AV31: INDEFINIDO | AW31: 07 Octubre 2024 - INDEFINIDO
A32: 98697 | B32: 00986970 | C32: N.I14256A | D32: APPLE | E32: IPHONE 14 256GB AZUL ATT | F32: Apple iPhone 14 256GB | G32: APPLE IPHONE 14 256GB 4G | H32: PREMIUM | I32: AT&T | J32: =K32/1.16 -> 15085.345 | K32: 17499 | L32: 10759 | M32: 10559 | N32: 10299 | O32: 9859 | P32: 9459 | Q32: 10599 | R32: 10299 | S32: 9999 | T32: 9459 | U32: 8859 | V32: 10459 | W32: 10099 | X32: 9759 | Y32: 8999 | Z32: 8259 | AA32: 10299 | AB32: 9859 | AC32: 9459 | AD32: 8559 | AE32: 7699 | AF32: 9999 | AG32: 9459 | AH32: 8859 | AI32: 7699 | AJ32: 6499 | AK32: 9299 | AL32: 8359 | AM32: 7399 | AN32: 5499 | AO32: 3599 | AP32: 8999 | AQ32: 7899 | AR32: 6799 | AS32: 4659 | AT32: 2459 | AU32: 45572 | AV32: INDEFINIDO | AW32: 07 Octubre 2024 - INDEFINIDO
A33: 98688 | B33: 00986880 | C33: N.I14256B | D33: APPLE | E33: IPHONE 14 256GB BLANCO ESTELAR ATT | F33: Apple iPhone 14 256GB | G33: APPLE IPHONE 14 256GB 4G | H33: PREMIUM | I33: AT&T | J33: =K33/1.16 -> 15085.345 | K33: 17499 | L33: 10759 | M33: 10559 | N33: 10299 | O33: 9859 | P33: 9459 | Q33: 10599 | R33: 10299 | S33: 9999 | T33: 9459 | U33: 8859 | V33: 10459 | W33: 10099 | X33: 9759 | Y33: 8999 | Z33: 8259 | AA33: 10299 | AB33: 9859 | AC33: 9459 | AD33: 8559 | AE33: 7699 | AF33: 9999 | AG33: 9459 | AH33: 8859 | AI33: 7699 | AJ33: 6499 | AK33: 9299 | AL33: 8359 | AM33: 7399 | AN33: 5499 | AO33: 3599 | AP33: 8999 | AQ33: 7899 | AR33: 6799 | AS33: 4659 | AT33: 2459 | AU33: 45572 | AV33: INDEFINIDO | AW33: 07 Octubre 2024 - INDEFINIDO
A34: 98685 | B34: 00986850 | C34: N.I14256N | D34: APPLE | E34: IPHONE 14 256GB MEDIANOCHE ATT | F34: Apple iPhone 14 256GB | G34: APPLE IPHONE 14 256GB 4G | H34: PREMIUM | I34: AT&T | J34: =K34/1.16 -> 15085.345 | K34: 17499 | L34: 10759 | M34: 10559 | N34: 10299 | O34: 9859 | P34: 9459 | Q34: 10599 | R34: 10299 | S34: 9999 | T34: 9459 | U34: 8859 | V34: 10459 | W34: 10099 | X34: 9759 | Y34: 8999 | Z34: 8259 | AA34: 10299 | AB34: 9859 | AC34: 9459 | AD34: 8559 | AE34: 7699 | AF34: 9999 | AG34: 9459 | AH34: 8859 | AI34: 7699 | AJ34: 6499 | AK34: 9299 | AL34: 8359 | AM34: 7399 | AN34: 5499 | AO34: 3599 | AP34: 8999 | AQ34: 7899 | AR34: 6799 | AS34: 4659 | AT34: 2459 | AU34: 45572 | AV34: INDEFINIDO | AW34: 07 Octubre 2024 - INDEFINIDO
A35: 98691 | B35: 00986910 | C35: N.I14256M | D35: APPLE | E35: IPHONE 14 256GB MORADO ATT | F35: Apple iPhone 14 256GB | G35: APPLE IPHONE 14 256GB 4G | H35: PREMIUM | I35: AT&T | J35: =K35/1.16 -> 15085.345 | K35: 17499 | L35: 10759 | M35: 10559 | N35: 10299 | O35: 9859 | P35: 9459 | Q35: 10599 | R35: 10299 | S35: 9999 | T35: 9459 | U35: 8859 | V35: 10459 | W35: 10099 | X35: 9759 | Y35: 8999 | Z35: 8259 | AA35: 10299 | AB35: 9859 | AC35: 9459 | AD35: 8559 | AE35: 7699 | AF35: 9999 | AG35: 9459 | AH35: 8859 | AI35: 7699 | AJ35: 6499 | AK35: 9299 | AL35: 8359 | AM35: 7399 | AN35: 5499 | AO35: 3599 | AP35: 8999 | AQ35: 7899 | AR35: 6799 | AS35: 4659 | AT35: 2459 | AU35: 45572 | AV35: INDEFINIDO | AW35: 07 Octubre 2024 - INDEFINIDO
A36: 98694 | B36: 00986940 | C36: N.I14256R | D36: APPLE | E36: IPHONE 14 256GB ROJO ATT | F36: Apple iPhone 14 256GB | G36: APPLE IPHONE 14 256GB 4G | H36: PREMIUM | I36: AT&T | J36: =K36/1.16 -> 15085.345 | K36: 17499 | L36: 10759 | M36: 10559 | N36: 10299 | O36: 9859 | P36: 9459 | Q36: 10599 | R36: 10299 | S36: 9999 | T36: 9459 | U36: 8859 | V36: 10459 | W36: 10099 | X36: 9759 | Y36: 8999 | Z36: 8259 | AA36: 10299 | AB36: 9859 | AC36: 9459 | AD36: 8559 | AE36: 7699 | AF36: 9999 | AG36: 9459 | AH36: 8859 | AI36: 7699 | AJ36: 6499 | AK36: 9299 | AL36: 8359 | AM36: 7399 | AN36: 5499 | AO36: 3599 | AP36: 8999 | AQ36: 7899 | AR36: 6799 | AS36: 4659 | AT36: 2459 | AU36: 45572 | AV36: INDEFINIDO | AW36: 07 Octubre 2024 - INDEFINIDO
A37: 98727 | B37: 00987270 | C37: N.I14128PLM | D37: APPLE | E37: IPHONE 14 PLUS 128GB MORADO ATT | F37: Apple iPhone 14 Plus 128GB | G37: APPLE IPHONE 14 PLUS 128GB 4G | H37: PREMIUM | I37: AT&T | J37: =K37/1.16 -> 15085.345 | K37: 17499 | L37: 11359 | M37: 11159 | N37: 10899 | O37: 10499 | P37: 10059 | Q37: 11199 | R37: 10899 | S37: 10659 | T37: 10059 | U37: 9459 | V37: 11059 | W37: 10699 | X37: 10359 | Y37: 9599 | Z37: 8899 | AA37: 10899 | AB37: 10499 | AC37: 10059 | AD37: 9199 | AE37: 8299 | AF37: 10659 | AG37: 10059 | AH37: 9459 | AI37: 8299 | AJ37: 7159 | AK37: 9899 | AL37: 8959 | AM37: 7999 | AN37: 6099 | AO37: 4259 | AP37: 9599 | AQ37: 8499 | AR37: 7459 | AS37: 5259 | AT37: 3059 | AU37: 45572 | AV37: INDEFINIDO | AW37: 07 Octubre 2024 - INDEFINIDO
A38: 98724 | B38: 00987240 | C38: N.I14128PLB | D38: APPLE | E38: IPHONE 14 PLUS 128GB BLANCO ESTELAR ATT | F38: Apple iPhone 14 Plus 128GB | G38: APPLE IPHONE 14 PLUS 128GB 4G | H38: PREMIUM | I38: AT&T | J38: =K38/1.16 -> 15085.345 | K38: 17499 | L38: 11359 | M38: 11159 | N38: 10899 | O38: 10499 | P38: 10059 | Q38: 11199 | R38: 10899 | S38: 10659 | T38: 10059 | U38: 9459 | V38: 11059 | W38: 10699 | X38: 10359 | Y38: 9599 | Z38: 8899 | AA38: 10899 | AB38: 10499 | AC38: 10059 | AD38: 9199 | AE38: 8299 | AF38: 10659 | AG38: 10059 | AH38: 9459 | AI38: 8299 | AJ38: 7159 | AK38: 9899 | AL38: 8959 | AM38: 7999 | AN38: 6099 | AO38: 4259 | AP38: 9599 | AQ38: 8499 | AR38: 7459 | AS38: 5259 | AT38: 3059 | AU38: 45572 | AV38: INDEFINIDO | AW38: 07 Octubre 2024 - INDEFINIDO
A39: 98730 | B39: 00987300 | C39: N.I14128PLR | D39: APPLE | E39: IPHONE 14 PLUS 128GB ROJO ATT | F39: Apple iPhone 14 Plus 128GB | G39: APPLE IPHONE 14 PLUS 128GB 4G | H39: PREMIUM | I39: AT&T | J39: =K39/1.16 -> 15085.345 | K39: 17499 | L39: 11359 | M39: 11159 | N39: 10899 | O39: 10499 | P39: 10059 | Q39: 11199 | R39: 10899 | S39: 10659 | T39: 10059 | U39: 9459 | V39: 11059 | W39: 10699 | X39: 10359 | Y39: 9599 | Z39: 8899 | AA39: 10899 | AB39: 10499 | AC39: 10059 | AD39: 9199 | AE39: 8299 | AF39: 10659 | AG39: 10059 | AH39: 9459 | AI39: 8299 | AJ39: 7159 | AK39: 9899 | AL39: 8959 | AM39: 7999 | AN39: 6099 | AO39: 4259 | AP39: 9599 | AQ39: 8499 | AR39: 7459 | AS39: 5259 | AT39: 3059 | AU39: 45572 | AV39: INDEFINIDO | AW39: 07 Octubre 2024 - INDEFINIDO
A40: 98721 | B40: 00987210 | C40: N.I14128PLN | D40: APPLE | E40: IPHONE 14 PLUS 128GB MEDIANOCHE ATT | F40: Apple iPhone 14 Plus 128GB | G40: APPLE IPHONE 14 PLUS 128GB 4G | H40: PREMIUM | I40: AT&T | J40: =K40/1.16 -> 15085.345 | K40: 17499 | L40: 11359 | M40: 11159 | N40: 10899 | O40: 10499 | P40: 10059 | Q40: 11199 | R40: 10899 | S40: 10659 | T40: 10059 | U40: 9459 | V40: 11059 | W40: 10699 | X40: 10359 | Y40: 9599 | Z40: 8899 | AA40: 10899 | AB40: 10499 | AC40: 10059 | AD40: 9199 | AE40: 8299 | AF40: 10659 | AG40: 10059 | AH40: 9459 | AI40: 8299 | AJ40: 7159 | AK40: 9899 | AL40: 8959 | AM40: 7999 | AN40: 6099 | AO40: 4259 | AP40: 9599 | AQ40: 8499 | AR40: 7459 | AS40: 5259 | AT40: 3059 | AU40: 45572 | AV40: INDEFINIDO | AW40: 07 Octubre 2024 - INDEFINIDO
A41: 98733 | B41: 00987330 | C41: N.I14128PLA | D41: APPLE | E41: IPHONE 14 PLUS 128GB AZUL AT&T | F41: Apple iPhone 14 Plus 128GB | G41: APPLE IPHONE 14 PLUS 128GB 4G | H41: PREMIUM | I41: AT&T | J41: =K41/1.16 -> 15085.345 | K41: 17499 | L41: 11359 | M41: 11159 | N41: 10899 | O41: 10499 | P41: 10059 | Q41: 11199 | R41: 10899 | S41: 10659 | T41: 10059 | U41: 9459 | V41: 11059 | W41: 10699 | X41: 10359 | Y41: 9599 | Z41: 8899 | AA41: 10899 | AB41: 10499 | AC41: 10059 | AD41: 9199 | AE41: 8299 | AF41: 10659 | AG41: 10059 | AH41: 9459 | AI41: 8299 | AJ41: 7159 | AK41: 9899 | AL41: 8959 | AM41: 7999 | AN41: 6099 | AO41: 4259 | AP41: 9599 | AQ41: 8499 | AR41: 7459 | AS41: 5259 | AT41: 3059 | AU41: 45572 | AV41: INDEFINIDO | AW41: 07 Octubre 2024 - INDEFINIDO
A42: 98739 | B42: 00987390 | C42: N.I14256PLN | D42: APPLE | E42: IPHONE 14 PLUS 256GB MEDNOC ATT | F42: Apple iPhone 14 Plus 256GB | G42: APPLE IPHONE 14 PLUS 256GB 4G | H42: PREMIUM | I42: AT&T | J42: =K42/1.16 -> 17240.517 | K42: 19999 | L42: 13159 | M42: 12959 | N42: 12699 | O42: 12299 | P42: 11859 | Q42: 12999 | R42: 12699 | S42: 12399 | T42: 11859 | U42: 11259 | V42: 12859 | W42: 12499 | X42: 12159 | Y42: 11399 | Z42: 10699 | AA42: 12699 | AB42: 12259 | AC42: 11859 | AD42: 10959 | AE42: 10099 | AF42: 12399 | AG42: 11859 | AH42: 11259 | AI42: 10099 | AJ42: 8959 | AK42: 11699 | AL42: 10759 | AM42: 9799 | AN42: 7899 | AO42: 5999 | AP42: 11399 | AQ42: 10299 | AR42: 9199 | AS42: 7059 | AT42: 4859 | AU42: 45572 | AV42: INDEFINIDO | AW42: 07 Octubre 2024 - INDEFINIDO
... A58: 98829 | B58: 00988290 | C58: N.I14256PMP | D58: APPLE | E58: IPHONE 14 PROMAX 256GB PLATA ATT | F58: Apple iPhone 14 Pro Max 256GB | G58: APPLE IPHONE 14 PRO MAX 256GB 4G | H58: FLAGSHIP | I58: AT&T | J58: =K58/1.16 -> 27585.345 | K58: 31999 | L58: 23599 | M58: 23399 | N58: 23199 | O58: 22699 | P58: 22299 | Q58: 23499 | R58: 23199 | S58: 22899 | T58: 22299 | U58: 21699 | V58: 23299 | W58: 22899 | X58: 22599 | Y58: 21799 | Z58: 21099 | AA58: 23199 | AB58: 22699 | AC58: 22299 | AD58: 21399 | AE58: 20499 | AF58: 22899 | AG58: 22299 | AH58: 21699 | AI58: 20499 | AJ58: 19299 | AK58: 22099 | AL58: 21099 | AM58: 20199 | AN58: 18199 | AO58: 16299 | AP58: 21799 | AQ58: 20699 | AR58: 19599 | AS58: 17299 | AT58: 15099 | AU58: 45505 | AV58: INDEFINIDO | AW58: 01 Agosto 2024 - INDEFINIDO
A59: 99825 | B59: 00998250 | C59: N.I15128AM | D59: APPLE | E59: IPHONE 15 128GB AMARILLO ATT | F59: Apple iPhone 15 128GB | G59: APPLE IPHONE 15 128GB 4G | H59: PREMIUM | I59: AT&T | J59: =K59/1.16 -> 15085.345 | K59: 17499 | L59: 12999 | M59: 12649 | N59: 12349 | O59: 11649 | P59: 10949 | Q59: 12799 | R59: 12349 | S59: 11899 | T59: 10949 | U59: 10049 | V59: 12549 | W59: 11999 | X59: 11399 | Y59: 10299 | Z59: 9149 | AA59: 12349 | AB59: 11649 | AC59: 10949 | AD59: 9599 | AE59: 8249 | AF59: 11849 | AG59: 10949 | AH59: 10049 | AI59: 8249 | AJ59: 6399 | AK59: 10749 | AL59: 9249 | AM59: 7749 | AN59: 4799 | AO59: 1849 | AP59: 10299 | AQ59: 8549 | AR59: 6849 | AS59: 3449 | AT59: 0 | AU59: 46110 | AV59: INDEFINIDO | AW59: =UPPER(TEXT(AU59, " dd \ mmmm \ aa")&" - "&TEXT(AV59, " dd \ mmmm \ aa")) -> 29 MARZO 26 - INDEFINIDO
A60: 99819 | B60: 00998190 | C60: N.I15128V | D60: APPLE | E60: IPHONE 15 128GB VERDE ATT | F60: Apple iPhone 15 128GB | G60: APPLE IPHONE 15 128GB 4G | H60: PREMIUM | I60: AT&T | J60: =K60/1.16 -> 15085.345 | K60: 17499 | L60: 12999 | M60: 12649 | N60: 12349 | O60: 11649 | P60: 10949 | Q60: 12799 | R60: 12349 | S60: 11899 | T60: 10949 | U60: 10049 | V60: 12549 | W60: 11999 | X60: 11399 | Y60: 10299 | Z60: 9149 | AA60: 12349 | AB60: 11649 | AC60: 10949 | AD60: 9599 | AE60: 8249 | AF60: 11849 | AG60: 10949 | AH60: 10049 | AI60: 8249 | AJ60: 6399 | AK60: 10749 | AL60: 9249 | AM60: 7749 | AN60: 4799 | AO60: 1849 | AP60: 10299 | AQ60: 8549 | AR60: 6849 | AS60: 3449 | AT60: 0 | AU60: 46110 | AV60: INDEFINIDO | AW60: =UPPER(TEXT(AU60, " dd \ mmmm \ aa")&" - "&TEXT(AV60, " dd \ mmmm \ aa")) -> 29 MARZO 26 - INDEFINIDO
A61: 99828 | B61: 00998280 | C61: N.I15128AZ | D61: APPLE | E61: IPHONE 15 128GB AZUL ATT | F61: Apple iPhone 15 128GB | G61: APPLE IPHONE 15 128GB 4G | H61: =IF(K61="REVISAR","REVISAR",IF(K61>=20000,"FLAGSHIP",IF(K61>=12000,"PREMIUM",IF(K61>=7000,"HIGH",IF(K61>=5000,"MID",IF(K61>=3000,"LOW","ENTRY")))))) -> PREMIUM | I61: AT&T | J61: =K61/1.16 -> 15085.345 | K61: 17499 | L61: 12999 | M61: 12649 | N61: 12349 | O61: 11649 | P61: 10949 | Q61: 12799 | R61: 12349 | S61: 11899 | T61: 10949 | U61: 10049 | V61: 12549 | W61: 11999 | X61: 11399 | Y61: 10299 | Z61: 9149 | AA61: 12349 | AB61: 11649 | AC61: 10949 | AD61: 9599 | AE61: 8249 | AF61: 11849 | AG61: 10949 | AH61: 10049 | AI61: 8249 | AJ61: 6399 | AK61: 10749 | AL61: 9249 | AM61: 7749 | AN61: 4799 | AO61: 1849 | AP61: 10299 | AQ61: 8549 | AR61: 6849 | AS61: 3449 | AT61: 0 | AU61: 46110 | AV61: INDEFINIDO | AW61: =UPPER(TEXT(AU61, " dd \ mmmm \ aa")&" - "&TEXT(AV61, " dd \ mmmm \ aa")) -> 29 MARZO 26 - INDEFINIDO
A62: 99816 | B62: 00998160 | C62: N.I15128N | D62: APPLE | E62: IPHONE 15 128GB NEGRO ATT | F62: Apple iPhone 15 128GB | G62: APPLE IPHONE 15 128GB 4G | H62: =IF(K62="REVISAR","REVISAR",IF(K62>=20000,"FLAGSHIP",IF(K62>=12000,"PREMIUM",IF(K62>=7000,"HIGH",IF(K62>=5000,"MID",IF(K62>=3000,"LOW","ENTRY")))))) -> PREMIUM | I62: AT&T | J62: =K62/1.16 -> 15085.345 | K62: 17499 | L62: 12999 | M62: 12649 | N62: 12349 | O62: 11649 | P62: 10949 | Q62: 12799 | R62: 12349 | S62: 11899 | T62: 10949 | U62: 10049 | V62: 12549 | W62: 11999 | X62: 11399 | Y62: 10299 | Z62: 9149 | AA62: 12349 | AB62: 11649 | AC62: 10949 | AD62: 9599 | AE62: 8249 | AF62: 11849 | AG62: 10949 | AH62: 10049 | AI62: 8249 | AJ62: 6399 | AK62: 10749 | AL62: 9249 | AM62: 7749 | AN62: 4799 | AO62: 1849 | AP62: 10299 | AQ62: 8549 | AR62: 6849 | AS62: 3449 | AT62: 0 | AU62: 46110 | AV62: INDEFINIDO | AW62: =UPPER(TEXT(AU62, " dd \ mmmm \ aa")&" - "&TEXT(AV62, " dd \ mmmm \ aa")) -> 29 MARZO 26 - INDEFINIDO
A63: 99822 | B63: 00998220 | C63: N.I15128RS | D63: APPLE | E63: IPHONE 15 128GB ROSA ATT | F63: Apple iPhone 15 128GB | G63: APPLE IPHONE 15 128GB 4G | H63: =IF(K63="REVISAR","REVISAR",IF(K63>=20000,"FLAGSHIP",IF(K63>=12000,"PREMIUM",IF(K63>=7000,"HIGH",IF(K63>=5000,"MID",IF(K63>=3000,"LOW","ENTRY")))))) -> PREMIUM | I63: AT&T | J63: =K63/1.16 -> 15085.345 | K63: 17499 | L63: 12999 | M63: 12649 | N63: 12349 | O63: 11649 | P63: 10949 | Q63: 12799 | R63: 12349 | S63: 11899 | T63: 10949 | U63: 10049 | V63: 12549 | W63: 11999 | X63: 11399 | Y63: 10299 | Z63: 9149 | AA63: 12349 | AB63: 11649 | AC63: 10949 | AD63: 9599 | AE63: 8249 | AF63: 11849 | AG63: 10949 | AH63: 10049 | AI63: 8249 | AJ63: 6399 | AK63: 10749 | AL63: 9249 | AM63: 7749 | AN63: 4799 | AO63: 1849 | AP63: 10299 | AQ63: 8549 | AR63: 6849 | AS63: 3449 | AT63: 0 | AU63: 46110 | AV63: INDEFINIDO | AW63: =UPPER(TEXT(AU63, " dd \ mmmm \ aa")&" - "&TEXT(AV63, " dd \ mmmm \ aa")) -> 29 MARZO 26 - INDEFINIDO
A64: 99840 | B64: 00998400 | C64: N.I15256AM | D64: APPLE | E64: IPHONE 15 256GB AMARILLO ATT | F64: Apple iPhone 15 256GB | G64: APPLE IPHONE 15 256GB 4G | H64: PREMIUM | I64: AT&T | J64: =K64/1.16 -> 17240.517 | K64: 19999 | L64: 17759 | M64: 17559 | N64: 17359 | O64: 16899 | P64: 16459 | Q64: 17659 | R64: 17359 | S64: 17059 | T64: 16459 | U64: 15899 | V64: 17499 | W64: 17099 | X64: 16759 | Y64: 16059 | Z64: 15299 | AA64: 17359 | AB64: 16899 | AC64: 16459 | AD64: 15599 | AE64: 14699 | AF64: 17059 | AG64: 16459 | AH64: 15899 | AI64: 14699 | AJ64: 13559 | AK64: 16299 | AL64: 15359 | AM64: 14399 | AN64: 12559 | AO64: 10659 | AP64: 15999 | AQ64: 14959 | AR64: 13859 | AS64: 11659 | AT64: 9459 | AU64: 45572 | AV64: INDEFINIDO | AW64: 07 Octubre 2024 - INDEFINIDO
A65: 99843 | B65: 00998430 | C65: N.I15256AZ | D65: APPLE | E65: IPHONE 15 256GB AZUL ATT | F65: Apple iPhone 15 256GB | G65: APPLE IPHONE 15 256GB 4G | H65: PREMIUM | I65: AT&T | J65: =K65/1.16 -> 17240.517 | K65: 19999 | L65: 17759 | M65: 17559 | N65: 17359 | O65: 16899 | P65: 16459 | Q65: 17659 | R65: 17359 | S65: 17059 | T65: 16459 | U65: 15899 | V65: 17499 | W65: 17099 | X65: 16759 | Y65: 16059 | Z65: 15299 | AA65: 17359 | AB65: 16899 | AC65: 16459 | AD65: 15599 | AE65: 14699 | AF65: 17059 | AG65: 16459 | AH65: 15899 | AI65: 14699 | AJ65: 13559 | AK65: 16299 | AL65: 15359 | AM65: 14399 | AN65: 12559 | AO65: 10659 | AP65: 15999 | AQ65: 14959 | AR65: 13859 | AS65: 11659 | AT65: 9459 | AU65: 45572 | AV65: INDEFINIDO | AW65: 07 Octubre 2024 - INDEFINIDO
A66: 99831 | B66: 00998310 | C66: N.I15256N | D66: APPLE | E66: IPHONE 15 256GB NEGRO ATT | F66: Apple iPhone 15 256GB | G66: APPLE IPHONE 15 256GB 4G | H66: PREMIUM | I66: AT&T | J66: =K66/1.16 -> 17240.517 | K66: 19999 | L66: 17759 | M66: 17559 | N66: 17359 | O66: 16899 | P66: 16459 | Q66: 17659 | R66: 17359 | S66: 17059 | T66: 16459 | U66: 15899 | V66: 17499 | W66: 17099 | X66: 16759 | Y66: 16059 | Z66: 15299 | AA66: 17359 | AB66: 16899 | AC66: 16459 | AD66: 15599 | AE66: 14699 | AF66: 17059 | AG66: 16459 | AH66: 15899 | AI66: 14699 | AJ66: 13559 | AK66: 16299 | AL66: 15359 | AM66: 14399 | AN66: 12559 | AO66: 10659 | AP66: 15999 | AQ66: 14959 | AR66: 13859 | AS66: 11659 | AT66: 9459 | AU66: 45572 | AV66: INDEFINIDO | AW66: 07 Octubre 2024 - INDEFINIDO
A67: 99837 | B67: 00998370 | C67: N.I15256RS | D67: APPLE | E67: IPHONE 15 256GB ROSA ATT | F67: Apple iPhone 15 256GB | G67: APPLE IPHONE 15 256GB 4G | H67: PREMIUM | I67: AT&T | J67: =K67/1.16 -> 17240.517 | K67: 19999 | L67: 17759 | M67: 17559 | N67: 17359 | O67: 16899 | P67: 16459 | Q67: 17659 | R67: 17359 | S67: 17059 | T67: 16459 | U67: 15899 | V67: 17499 | W67: 17099 | X67: 16759 | Y67: 16059 | Z67: 15299 | AA67: 17359 | AB67: 16899 | AC67: 16459 | AD67: 15599 | AE67: 14699 | AF67: 17059 | AG67: 16459 | AH67: 15899 | AI67: 14699 | AJ67: 13559 | AK67: 16299 | AL67: 15359 | AM67: 14399 | AN67: 12559 | AO67: 10659 | AP67: 15999 | AQ67: 14959 | AR67: 13859 | AS67: 11659 | AT67: 9459 | AU67: 45572 | AV67: INDEFINIDO | AW67: 07 Octubre 2024 - INDEFINIDO
A68: 99834 | B68: 00998340 | C68: N.I15256V | D68: APPLE | E68: IPHONE 15 256GB VERDE ATT | F68: Apple iPhone 15 256GB | G68: APPLE IPHONE 15 256GB 4G | H68: PREMIUM | I68: AT&T | J68: =K68/1.16 -> 17240.517 | K68: 19999 | L68: 17759 | M68: 17559 | N68: 17359 | O68: 16899 | P68: 16459 | Q68: 17659 | R68: 17359 | S68: 17059 | T68: 16459 | U68: 15899 | V68: 17499 | W68: 17099 | X68: 16759 | Y68: 16059 | Z68: 15299 | AA68: 17359 | AB68: 16899 | AC68: 16459 | AD68: 15599 | AE68: 14699 | AF68: 17059 | AG68: 16459 | AH68: 15899 | AI68: 14699 | AJ68: 13559 | AK68: 16299 | AL68: 15359 | AM68: 14399 | AN68: 12559 | AO68: 10659 | AP68: 15999 | AQ68: 14959 | AR68: 13859 | AS68: 11659 | AT68: 9459 | AU68: 45572 | AV68: INDEFINIDO | AW68: 07 Octubre 2024 - INDEFINIDO
A69: 99855 | B69: 00998550 | C69: N.I15512AM | D69: APPLE | E69: IPHONE 15 512GB AMARILLO ATT | F69: Apple iPhone 15 512GB | G69: APPLE IPHONE 15 512GB 4G | H69: FLAGSHIP | I69: AT&T | J69: =K69/1.16 -> 21550.862 | K69: 24999 | L69: 22299 | M69: 22099 | N69: 21899 | O69: 21459 | P69: 20999 | Q69: 22159 | R69: 21899 | S69: 21599 | T69: 20999 | U69: 20459 | V69: 22059 | W69: 21659 | X69: 21299 | Y69: 20559 | Z69: 19859 | AA69: 21899 | AB69: 21459 | AC69: 20999 | AD69: 20159 | AE69: 19259 | AF69: 21599 | AG69: 20999 | AH69: 20459 | AI69: 19259 | AJ69: 18099 | AK69: 20859 | AL69: 19899 | AM69: 18959 | AN69: 17099 | AO69: 15199 | AP69: 20559 | AQ69: 19499 | AR69: 18399 | AS69: 16199 | AT69: 13999 | AU69: 45572 | AV69: INDEFINIDO | AW69: 07 Octubre 2024 - INDEFINIDO
A70: 99858 | B70: 00998580 | C70: N.I15512AZ | D70: APPLE | E70: IPHONE 15 512GB AZUL ATT | F70: Apple iPhone 15 512GB | G70: APPLE IPHONE 15 512GB 4G | H70: FLAGSHIP | I70: AT&T | J70: =K70/1.16 -> 21550.862 | K70: 24999 | L70: 22299 | M70: 22099 | N70: 21899 | O70: 21459 | P70: 20999 | Q70: 22159 | R70: 21899 | S70: 21599 | T70: 20999 | U70: 20459 | V70: 22059 | W70: 21659 | X70: 21299 | Y70: 20559 | Z70: 19859 | AA70: 21899 | AB70: 21459 | AC70: 20999 | AD70: 20159 | AE70: 19259 | AF70: 21599 | AG70: 20999 | AH70: 20459 | AI70: 19259 | AJ70: 18099 | AK70: 20859 | AL70: 19899 | AM70: 18959 | AN70: 17099 | AO70: 15199 | AP70: 20559 | AQ70: 19499 | AR70: 18399 | AS70: 16199 | AT70: 13999 | AU70: 45572 | AV70: INDEFINIDO | AW70: 07 Octubre 2024 - INDEFINIDO
A71: 99846 | B71: 00998460 | C71: N.I15512N | D71: APPLE | E71: IPHONE 15 512GB NEGRO ATT | F71: Apple iPhone 15 512GB | G71: APPLE IPHONE 15 512GB 4G | H71: FLAGSHIP | I71: AT&T | J71: =K71/1.16 -> 21550.862 | K71: 24999 | L71: 22299 | M71: 22099 | N71: 21899 | O71: 21459 | P71: 20999 | Q71: 22159 | R71: 21899 | S71: 21599 | T71: 20999 | U71: 20459 | V71: 22059 | W71: 21659 | X71: 21299 | Y71: 20559 | Z71: 19859 | AA71: 21899 | AB71: 21459 | AC71: 20999 | AD71: 20159 | AE71: 19259 | AF71: 21599 | AG71: 20999 | AH71: 20459 | AI71: 19259 | AJ71: 18099 | AK71: 20859 | AL71: 19899 | AM71: 18959 | AN71: 17099 | AO71: 15199 | AP71: 20559 | AQ71: 19499 | AR71: 18399 | AS71: 16199 | AT71: 13999 | AU71: 45572 | AV71: INDEFINIDO | AW71: 07 Octubre 2024 - INDEFINIDO
A72: 99852 | B72: 00998520 | C72: N.I15512RS | D72: APPLE | E72: IPHONE 15 512GB ROSA ATT | F72: Apple iPhone 15 512GB | G72: APPLE IPHONE 15 512GB 4G | H72: FLAGSHIP | I72: AT&T | J72: =K72/1.16 -> 21550.862 | K72: 24999 | L72: 22299 | M72: 22099 | N72: 21899 | O72: 21459 | P72: 20999 | Q72: 22159 | R72: 21899 | S72: 21599 | T72: 20999 | U72: 20459 | V72: 22059 | W72: 21659 | X72: 21299 | Y72: 20559 | Z72: 19859 | AA72: 21899 | AB72: 21459 | AC72: 20999 | AD72: 20159 | AE72: 19259 | AF72: 21599 | AG72: 20999 | AH72: 20459 | AI72: 19259 | AJ72: 18099 | AK72: 20859 | AL72: 19899 | AM72: 18959 | AN72: 17099 | AO72: 15199 | AP72: 20559 | AQ72: 19499 | AR72: 18399 | AS72: 16199 | AT72: 13999 | AU72: 45572 | AV72: INDEFINIDO | AW72: 07 Octubre 2024 - INDEFINIDO
A73: 99849 | B73: 00998490 | C73: N.I15512V | D73: APPLE | E73: IPHONE 15 512GB VERDE ATT | F73: Apple iPhone 15 512GB | G73: APPLE IPHONE 15 512GB 4G | H73: FLAGSHIP | I73: AT&T | J73: =K73/1.16 -> 21550.862 | K73: 24999 | L73: 22299 | M73: 22099 | N73: 21899 | O73: 21459 | P73: 20999 | Q73: 22159 | R73: 21899 | S73: 21599 | T73: 20999 | U73: 20459 | V73: 22059 | W73: 21659 | X73: 21299 | Y73: 20559 | Z73: 19859 | AA73: 21899 | AB73: 21459 | AC73: 20999 | AD73: 20159 | AE73: 19259 | AF73: 21599 | AG73: 20999 | AH73: 20459 | AI73: 19259 | AJ73: 18099 | AK73: 20859 | AL73: 19899 | AM73: 18959 | AN73: 17099 | AO73: 15199 | AP73: 20559 | AQ73: 19499 | AR73: 18399 | AS73: 16199 | AT73: 13999 | AU73: 45572 | AV73: INDEFINIDO | AW73: 07 Octubre 2024 - INDEFINIDO
A74: 99873 | B74: 00998730 | C74: N.I15128PLAZ | D74: APPLE | E74: IPHONE 15 PLUS 128GB AZUL ATT | F74: Apple iPhone 15 Plus 128GB | G74: APPLE IPHONE 15 PLUS 128GB 4G | H74: PREMIUM | I74: AT&T | J74: =K74/1.16 -> 17240.517 | K74: 19999 | L74: 8699 | M74: 8499 | N74: 8249 | O74: 7849 | P74: 7399 | Q74: 8549 | R74: 8249 | S74: 7999 | T74: 7399 | U74: 6799 | V74: 8399 | W74: 8049 | X74: 7699 | Y74: 6949 | Z74: 6249 | AA74: 8249 | AB74: 7849 | AC74: 7399 | AD74: 6549 | AE74: 5649 | AF74: 7999 | AG74: 7399 | AH74: 6799 | AI74: 5649 | AJ74: 4499 | AK74: 7249 | AL74: 6299 | AM74: 5349 | AN74: 3449 | AO74: 1599 | AP74: 6949 | AQ74: 5849 | AR74: 4799 | AS74: 2599 | AT74: 399 | AU74: 46059 | AV74: INDEFINIDO | AW74: =UPPER(TEXT(AU74, " dd \ mmmm \ aa")&" - "&TEXT(AV74, " dd \ mmmm \ aa")) -> 06 FEBRERO 26 - INDEFINIDO
A75: 99867 | B75: 00998670 | C75: N.I15128PLRS | D75: APPLE | E75: IPHONE 15 PLUS 128GB ROSA ATT | F75: Apple iPhone 15 Plus 128GB | G75: APPLE IPHONE 15 PLUS 128GB 4G | H75: PREMIUM | I75: AT&T | J75: =K75/1.16 -> 17240.517 | K75: 19999 | L75: 8699 | M75: 8499 | N75: 8249 | O75: 7849 | P75: 7399 | Q75: 8549 | R75: 8249 | S75: 7999 | T75: 7399 | U75: 6799 | V75: 8399 | W75: 8049 | X75: 7699 | Y75: 6949 | Z75: 6249 | AA75: 8249 | AB75: 7849 | AC75: 7399 | AD75: 6549 | AE75: 5649 | AF75: 7999 | AG75: 7399 | AH75: 6799 | AI75: 5649 | AJ75: 4499 | AK75: 7249 | AL75: 6299 | AM75: 5349 | AN75: 3449 | AO75: 1599 | AP75: 6949 | AQ75: 5849 | AR75: 4799 | AS75: 2599 | AT75: 399 | AU75: 46059 | AV75: INDEFINIDO | AW75: =UPPER(TEXT(AU75, " dd \ mmmm \ aa")&" - "&TEXT(AV75, " dd \ mmmm \ aa")) -> 06 FEBRERO 26 - INDEFINIDO
A76: 99861 | B76: 00998610 | C76: N.I15128PLN | D76: APPLE | E76: IPHONE 15 PLUS 128GB NEGRO ATT | F76: Apple iPhone 15 Plus 128GB | G76: APPLE IPHONE 15 PLUS 128GB 4G | H76: =IF(K76="REVISAR","REVISAR",IF(K76>=20000,"FLAGSHIP",IF(K76>=12000,"PREMIUM",IF(K76>=7000,"HIGH",IF(K76>=5000,"MID",IF(K76>=3000,"LOW","ENTRY")))))) -> PREMIUM | I76: AT&T | J76: =K76/1.16 -> 17240.517 | K76: 19999 | L76: 8699 | M76: 8499 | N76: 8249 | O76: 7849 | P76: 7399 | Q76: 8549 | R76: 8249 | S76: 7999 | T76: 7399 | U76: 6799 | V76: 8399 | W76: 8049 | X76: 7699 | Y76: 6949 | Z76: 6249 | AA76: 8249 | AB76: 7849 | AC76: 7399 | AD76: 6549 | AE76: 5649 | AF76: 7999 | AG76: 7399 | AH76: 6799 | AI76: 5649 | AJ76: 4499 | AK76: 7249 | AL76: 6299 | AM76: 5349 | AN76: 3449 | AO76: 1599 | AP76: 6949 | AQ76: 5849 | AR76: 4799 | AS76: 2599 | AT76: 399 | AU76: 46059 | AV76: INDEFINIDO | AW76: =UPPER(TEXT(AU76, " dd \ mmmm \ aa")&" - "&TEXT(AV76, " dd \ mmmm \ aa")) -> 06 FEBRERO 26 - INDEFINIDO
A77: 99864 | B77: 00998640 | C77: N.I15128PLV | D77: APPLE | E77: IPHONE 15 PLUS 128GB VERDE ATT | F77: Apple iPhone 15 Plus 128GB | G77: APPLE IPHONE 15 PLUS 128GB 4G | H77: PREMIUM | I77: AT&T | J77: =K77/1.16 -> 17240.517 | K77: 19999 | L77: 8699 | M77: 8499 | N77: 8249 | O77: 7849 | P77: 7399 | Q77: 8549 | R77: 8249 | S77: 7999 | T77: 7399 | U77: 6799 | V77: 8399 | W77: 8049 | X77: 7699 | Y77: 6949 | Z77: 6249 | AA77: 8249 | AB77: 7849 | AC77: 7399 | AD77: 6549 | AE77: 5649 | AF77: 7999 | AG77: 7399 | AH77: 6799 | AI77: 5649 | AJ77: 4499 | AK77: 7249 | AL77: 6299 | AM77: 5349 | AN77: 3449 | AO77: 1599 | AP77: 6949 | AQ77: 5849 | AR77: 4799 | AS77: 2599 | AT77: 399 | AU77: 46059 | AV77: INDEFINIDO | AW77: =UPPER(TEXT(AU77, " dd \ mmmm \ aa")&" - "&TEXT(AV77, " dd \ mmmm \ aa")) -> 06 FEBRERO 26 - INDEFINIDO
A78: 99885 | B78: 00998850 | C78: N.I15256PLAM | D78: APPLE | E78: IPHONE 15 PLUS 256GB AMARILLO ATT | F78: Apple iPhone 15 Plus 256GB | G78: APPLE IPHONE 15 PLUS 256GB 4G | H78: FLAGSHIP | I78: AT&T | J78: =K78/1.16 -> 19395.69 | K78: 22499 | L78: 20059 | M78: 19859 | N78: 19599 | O78: 19159 | P78: 18759 | Q78: 19899 | R78: 19599 | S78: 19299 | T78: 18759 | U78: 18159 | V78: 19759 | W78: 19399 | X78: 19059 | Y78: 18299 | Z78: 17559 | AA78: 19599 | AB78: 19159 | AC78: 18759 | AD78: 17859 | AE78: 16999 | AF78: 19299 | AG78: 18759 | AH78: 18159 | AI78: 16999 | AJ78: 15799 | AK78: 18599 | AL78: 17659 | AM78: 16699 | AN78: 14799 | AO78: 12899 | AP78: 18299 | AQ78: 17199 | AR78: 16099 | AS78: 13959 | AT78: 11759 | AU78: 45572 | AV78: INDEFINIDO | AW78: 07 Octubre 2024 - INDEFINIDO
A79: 99888 | B79: 00998880 | C79: N.I15256PLAZ | D79: APPLE | E79: IPHONE 15 PLUS 256GB AZUL ATT | F79: Apple iPhone 15 Plus 256GB | G79: APPLE IPHONE 15 PLUS 256GB 4G | H79: FLAGSHIP | I79: AT&T | J79: =K79/1.16 -> 19395.69 | K79: 22499 | L79: 20059 | M79: 19859 | N79: 19599 | O79: 19159 | P79: 18759 | Q79: 19899 | R79: 19599 | S79: 19299 | T79: 18759 | U79: 18159 | V79: 19759 | W79: 19399 | X79: 19059 | Y79: 18299 | Z79: 17559 | AA79: 19599 | AB79: 19159 | AC79: 18759 | AD79: 17859 | AE79: 16999 | AF79: 19299 | AG79: 18759 | AH79: 18159 | AI79: 16999 | AJ79: 15799 | AK79: 18599 | AL79: 17659 | AM79: 16699 | AN79: 14799 | AO79: 12899 | AP79: 18299 | AQ79: 17199 | AR79: 16099 | AS79: 13959 | AT79: 11759 | AU79: 45572 | AV79: INDEFINIDO | AW79: 07 Octubre 2024 - INDEFINIDO
A80: 99876 | B80: 00998760 | C80: N.I15256PLN | D80: APPLE | E80: IPHONE 15 PLUS 256GB NEGRO ATT | F80: Apple iPhone 15 Plus 256GB | G80: APPLE IPHONE 15 PLUS 256GB 4G | H80: FLAGSHIP | I80: AT&T | J80: =K80/1.16 -> 19395.69 | K80: 22499 | L80: 20059 | M80: 19859 | N80: 19599 | O80: 19159 | P80: 18759 | Q80: 19899 | R80: 19599 | S80: 19299 | T80: 18759 | U80: 18159 | V80: 19759 | W80: 19399 | X80: 19059 | Y80: 18299 | Z80: 17559 | AA80: 19599 | AB80: 19159 | AC80: 18759 | AD80: 17859 | AE80: 16999 | AF80: 19299 | AG80: 18759 | AH80: 18159 | AI80: 16999 | AJ80: 15799 | AK80: 18599 | AL80: 17659 | AM80: 16699 | AN80: 14799 | AO80: 12899 | AP80: 18299 | AQ80: 17199 | AR80: 16099 | AS80: 13959 | AT80: 11759 | AU80: 45572 | AV80: INDEFINIDO | AW80: 07 Octubre 2024 - INDEFINIDO
A81: 99882 | B81: 00998820 | C81: N.I15256PLRS | D81: APPLE | E81: IPHONE 15 PLUS 256GB ROSA ATT | F81: Apple iPhone 15 Plus 256GB | G81: APPLE IPHONE 15 PLUS 256GB 4G | H81: FLAGSHIP | I81: AT&T | J81: =K81/1.16 -> 19395.69 | K81: 22499 | L81: 20059 | M81: 19859 | N81: 19599 | O81: 19159 | P81: 18759 | Q81: 19899 | R81: 19599 | S81: 19299 | T81: 18759 | U81: 18159 | V81: 19759 | W81: 19399 | X81: 19059 | Y81: 18299 | Z81: 17559 | AA81: 19599 | AB81: 19159 | AC81: 18759 | AD81: 17859 | AE81: 16999 | AF81: 19299 | AG81: 18759 | AH81: 18159 | AI81: 16999 | AJ81: 15799 | AK81: 18599 | AL81: 17659 | AM81: 16699 | AN81: 14799 | AO81: 12899 | AP81: 18299 | AQ81: 17199 | AR81: 16099 | AS81: 13959 | AT81: 11759 | AU81: 45572 | AV81: INDEFINIDO | AW81: 07 Octubre 2024 - INDEFINIDO
A82: 99879 | B82: 00998790 | C82: N.I15256PLV | D82: APPLE | E82: IPHONE 15 PLUS 256GB VERDE ATT | F82: Apple iPhone 15 Plus 256GB | G82: APPLE IPHONE 15 PLUS 256GB 4G | H82: FLAGSHIP | I82: AT&T | J82: =K82/1.16 -> 19395.69 | K82: 22499 | L82: 20059 | M82: 19859 | N82: 19599 | O82: 19159 | P82: 18759 | Q82: 19899 | R82: 19599 | S82: 19299 | T82: 18759 | U82: 18159 | V82: 19759 | W82: 19399 | X82: 19059 | Y82: 18299 | Z82: 17559 | AA82: 19599 | AB82: 19159 | AC82: 18759 | AD82: 17859 | AE82: 16999 | AF82: 19299 | AG82: 18759 | AH82: 18159 | AI82: 16999 | AJ82: 15799 | AK82: 18599 | AL82: 17659 | AM82: 16699 | AN82: 14799 | AO82: 12899 | AP82: 18299 | AQ82: 17199 | AR82: 16099 | AS82: 13959 | AT82: 11759 | AU82: 45572 | AV82: INDEFINIDO | AW82: 07 Octubre 2024 - INDEFINIDO
A83: 99900 | B83: 00999000 | C83: N.I15512PLAM | D83: APPLE | E83: IPHONE 15 PLUS 512GB AMARILLO ATT | F83: Apple iPhone 15 Plus 512GB | G83: APPLE IPHONE 15 PLUS 512GB 4G | H83: FLAGSHIP | I83: AT&T | J83: =K83/1.16 -> 23706.034 | K83: 27499 | L83: 23059 | M83: 22799 | N83: 22599 | O83: 22159 | P83: 21759 | Q83: 22899 | R83: 22599 | S83: 22299 | T83: 21759 | U83: 21159 | V83: 22759 | W83: 22399 | X83: 21999 | Y83: 21299 | Z83: 20559 | AA83: 22599 | AB83: 22159 | AC83: 21759 | AD83: 20859 | AE83: 19999 | AF83: 22299 | AG83: 21759 | AH83: 21159 | AI83: 19999 | AJ83: 18799 | AK83: 21599 | AL83: 20659 | AM83: 19699 | AN83: 17799 | AO83: 15899 | AP83: 21299 | AQ83: 20199 | AR83: 19099 | AS83: 16899 | AT83: 14759 | AU83: 45572 | AV83: INDEFINIDO | AW83: 07 Octubre 2024 - INDEFINIDO
A84: 99903 | B84: 00999030 | C84: N.I15512PLAZ | D84: APPLE | E84: IPHONE 15 PLUS 512GB AZUL ATT | F84: Apple iPhone 15 Plus 512GB | G84: APPLE IPHONE 15 PLUS 512GB 4G | H84: FLAGSHIP | I84: AT&T | J84: =K84/1.16 -> 23706.034 | K84: 27499 | L84: 23059 | M84: 22799 | N84: 22599 | O84: 22159 | P84: 21759 | Q84: 22899 | R84: 22599 | S84: 22299 | T84: 21759 | U84: 21159 | V84: 22759 | W84: 22399 | X84: 21999 | Y84: 21299 | Z84: 20559 | AA84: 22599 | AB84: 22159 | AC84: 21759 | AD84: 20859 | AE84: 19999 | AF84: 22299 | AG84: 21759 | AH84: 21159 | AI84: 19999 | AJ84: 18799 | AK84: 21599 | AL84: 20659 | AM84: 19699 | AN84: 17799 | AO84: 15899 | AP84: 21299 | AQ84: 20199 | AR84: 19099 | AS84: 16899 | AT84: 14759 | AU84: 45572 | AV84: INDEFINIDO | AW84: 07 Octubre 2024 - INDEFINIDO
A85: 99891 | B85: 00998910 | C85: N.I15512PLN | D85: APPLE | E85: IPHONE 15 PLUS 512GB NEGRO ATT | F85: Apple iPhone 15 Plus 512GB | G85: APPLE IPHONE 15 PLUS 512GB 4G | H85: FLAGSHIP | I85: AT&T | J85: =K85/1.16 -> 23706.034 | K85: 27499 | L85: 23059 | M85: 22799 | N85: 22599 | O85: 22159 | P85: 21759 | Q85: 22899 | R85: 22599 | S85: 22299 | T85: 21759 | U85: 21159 | V85: 22759 | W85: 22399 | X85: 21999 | Y85: 21299 | Z85: 20559 | AA85: 22599 | AB85: 22159 | AC85: 21759 | AD85: 20859 | AE85: 19999 | AF85: 22299 | AG85: 21759 | AH85: 21159 | AI85: 19999 | AJ85: 18799 | AK85: 21599 | AL85: 20659 | AM85: 19699 | AN85: 17799 | AO85: 15899 | AP85: 21299 | AQ85: 20199 | AR85: 19099 | AS85: 16899 | AT85: 14759 | AU85: 45572 | AV85: INDEFINIDO | AW85: 07 Octubre 2024 - INDEFINIDO
A86: 99897 | B86: 00998970 | C86: N.I15512PLRS | D86: APPLE | E86: IPHONE 15 PLUS 512GB ROSA ATT | F86: Apple iPhone 15 Plus 512GB | G86: APPLE IPHONE 15 PLUS 512GB 4G | H86: FLAGSHIP | I86: AT&T | J86: =K86/1.16 -> 23706.034 | K86: 27499 | L86: 23059 | M86: 22799 | N86: 22599 | O86: 22159 | P86: 21759 | Q86: 22899 | R86: 22599 | S86: 22299 | T86: 21759 | U86: 21159 | V86: 22759 | W86: 22399 | X86: 21999 | Y86: 21299 | Z86: 20559 | AA86: 22599 | AB86: 22159 | AC86: 21759 | AD86: 20859 | AE86: 19999 | AF86: 22299 | AG86: 21759 | AH86: 21159 | AI86: 19999 | AJ86: 18799 | AK86: 21599 | AL86: 20659 | AM86: 19699 | AN86: 17799 | AO86: 15899 | AP86: 21299 | AQ86: 20199 | AR86: 19099 | AS86: 16899 | AT86: 14759 | AU86: 45572 | AV86: INDEFINIDO | AW86: 07 Octubre 2024 - INDEFINIDO
A87: 99894 | B87: 00998940 | C87: N.I15512PLV | D87: APPLE | E87: IPHONE 15 PLUS 512GB VERDE ATT | F87: Apple iPhone 15 Plus 512GB | G87: APPLE IPHONE 15 PLUS 512GB 4G | H87: FLAGSHIP | I87: AT&T | J87: =K87/1.16 -> 23706.034 | K87: 27499 | L87: 23059 | M87: 22799 | N87: 22599 | O87: 22159 | P87: 21759 | Q87: 22899 | R87: 22599 | S87: 22299 | T87: 21759 | U87: 21159 | V87: 22759 | W87: 22399 | X87: 21999 | Y87: 21299 | Z87: 20559 | AA87: 22599 | AB87: 22159 | AC87: 21759 | AD87: 20859 | AE87: 19999 | AF87: 22299 | AG87: 21759 | AH87: 21159 | AI87: 19999 | AJ87: 18799 | AK87: 21599 | AL87: 20659 | AM87: 19699 | AN87: 17799 | AO87: 15899 | AP87: 21299 | AQ87: 20199 | AR87: 19099 | AS87: 16899 | AT87: 14759 | AU87: 45572 | AV87: INDEFINIDO | AW87: 07 Octubre 2024 - INDEFINIDO
A88: 99915 | B88: 00999150 | C88: N.I15128PTAZ | D88: APPLE | E88: IPHONE 15 PRO 128GB TITANIO AZUL ATT | F88: Apple iPhone 15 Pro 128GB | G88: APPLE IPHONE 15 PRO 128GB 4G | H88: =IF(K88="REVISAR","REVISAR",IF(K88>=20000,"FLAGSHIP",IF(K88>=12000,"PREMIUM",IF(K88>=7000,"HIGH",IF(K88>=5000,"MID",IF(K88>=3000,"LOW","ENTRY")))))) -> FLAGSHIP | I88: AT&T | J88: =K88/1.16 -> 20688.793 | K88: 23999 | L88: 14399 | M88: 14199 | N88: 13999 | O88: 13549 | P88: 13099 | Q88: 14249 | R88: 13999 | S88: 13699 | T88: 13099 | U88: 12549 | V88: 14149 | W88: 13749 | X88: 13399 | Y88: 12699 | Z88: 11949 | AA88: 13999 | AB88: 13549 | AC88: 13099 | AD88: 12249 | AE88: 11349 | AF88: 13699 | AG88: 13099 | AH88: 12549 | AI88: 11349 | AJ88: 10199 | AK88: 12949 | AL88: 11999 | AM88: 11049 | AN88: 9199 | AO88: 7299 | AP88: 12649 | AQ88: 11599 | AR88: 10499 | AS88: 8299 | AT88: 6099 | AU88: 46059 | AV88: INDEFINIDO | AW88: =UPPER(TEXT(AU88, " dd \ mmmm \ aa")&" - "&TEXT(AV88, " dd \ mmmm \ aa")) -> 06 FEBRERO 26 - INDEFINIDO
A89: 99909 | B89: 00999090 | C89: N.I15128PTBL | D89: APPLE | E89: IPHONE 15 PRO 128GB TITANIO BLANCO ATT | F89: Apple iPhone 15 Pro 128GB | G89: APPLE IPHONE 15 PRO 128GB 4G | H89: =IF(K89="REVISAR","REVISAR",IF(K89>=20000,"FLAGSHIP",IF(K89>=12000,"PREMIUM",IF(K89>=7000,"HIGH",IF(K89>=5000,"MID",IF(K89>=3000,"LOW","ENTRY")))))) -> FLAGSHIP | I89: AT&T | J89: =K89/1.16 -> 20688.793 | K89: 23999 | L89: 14399 | M89: 14199 | N89: 13999 | O89: 13549 | P89: 13099 | Q89: 14249 | R89: 13999 | S89: 13699 | T89: 13099 | U89: 12549 | V89: 14149 | W89: 13749 | X89: 13399 | Y89: 12699 | Z89: 11949 | AA89: 13999 | AB89: 13549 | AC89: 13099 | AD89: 12249 | AE89: 11349 | AF89: 13699 | AG89: 13099 | AH89: 12549 | AI89: 11349 | AJ89: 10199 | AK89: 12949 | AL89: 11999 | AM89: 11049 | AN89: 9199 | AO89: 7299 | AP89: 12649 | AQ89: 11599 | AR89: 10499 | AS89: 8299 | AT89: 6099 | AU89: 46059 | AV89: INDEFINIDO | AW89: =UPPER(TEXT(AU89, " dd \ mmmm \ aa")&" - "&TEXT(AV89, " dd \ mmmm \ aa")) -> 06 FEBRERO 26 - INDEFINIDO
A90: 99912 | B90: 00999120 | C90: N.I15128PTNA | D90: APPLE | E90: IPHONE 15 PRO 128GB TITANIO NATURAL ATT | F90: Apple iPhone 15 Pro 128GB | G90: APPLE IPHONE 15 PRO 128GB 4G | H90: =IF(K90="REVISAR","REVISAR",IF(K90>=20000,"FLAGSHIP",IF(K90>=12000,"PREMIUM",IF(K90>=7000,"HIGH",IF(K90>=5000,"MID",IF(K90>=3000,"LOW","ENTRY")))))) -> FLAGSHIP | I90: AT&T | J90: =K90/1.16 -> 20688.793 | K90: 23999 | L90: 14399 | M90: 14199 | N90: 13999 | O90: 13549 | P90: 13099 | Q90: 14249 | R90: 13999 | S90: 13699 | T90: 13099 | U90: 12549 | V90: 14149 | W90: 13749 | X90: 13399 | Y90: 12699 | Z90: 11949 | AA90: 13999 | AB90: 13549 | AC90: 13099 | AD90: 12249 | AE90: 11349 | AF90: 13699 | AG90: 13099 | AH90: 12549 | AI90: 11349 | AJ90: 10199 | AK90: 12949 | AL90: 11999 | AM90: 11049 | AN90: 9199 | AO90: 7299 | AP90: 12649 | AQ90: 11599 | AR90: 10499 | AS90: 8299 | AT90: 6099 | AU90: 46059 | AV90: INDEFINIDO | AW90: =UPPER(TEXT(AU90, " dd \ mmmm \ aa")&" - "&TEXT(AV90, " dd \ mmmm \ aa")) -> 06 FEBRERO 26 - INDEFINIDO
A91: 99906 | B91: 00999060 | C91: N.I15128PTNG | D91: APPLE | E91: IPHONE 15 PRO 128GB TITANIO NEGRO ATT | F91: Apple iPhone 15 Pro 128GB | G91: APPLE IPHONE 15 PRO 128GB 4G | H91: =IF(K91="REVISAR","REVISAR",IF(K91>=20000,"FLAGSHIP",IF(K91>=12000,"PREMIUM",IF(K91>=7000,"HIGH",IF(K91>=5000,"MID",IF(K91>=3000,"LOW","ENTRY")))))) -> FLAGSHIP | I91: AT&T | J91: =K91/1.16 -> 20688.793 | K91: 23999 | L91: 14399 | M91: 14199 | N91: 13999 | O91: 13549 | P91: 13099 | Q91: 14249 | R91: 13999 | S91: 13699 | T91: 13099 | U91: 12549 | V91: 14149 | W91: 13749 | X91: 13399 | Y91: 12699 | Z91: 11949 | AA91: 13999 | AB91: 13549 | AC91: 13099 | AD91: 12249 | AE91: 11349 | AF91: 13699 | AG91: 13099 | AH91: 12549 | AI91: 11349 | AJ91: 10199 | AK91: 12949 | AL91: 11999 | AM91: 11049 | AN91: 9199 | AO91: 7299 | AP91: 12649 | AQ91: 11599 | AR91: 10499 | AS91: 8299 | AT91: 6099 | AU91: 46059 | AV91: INDEFINIDO | AW91: =UPPER(TEXT(AU91, " dd \ mmmm \ aa")&" - "&TEXT(AV91, " dd \ mmmm \ aa")) -> 06 FEBRERO 26 - INDEFINIDO
A92: 99942 | B92: 999420 | C92: N.I151TBPTNG | D92: APPLE | E92: IPHONE 15 PRO 1TB TITANIO NEGRO ATT | F92: Apple Iphone 15 Pro 1TB 5G | G92: APPLE IPHONE 15 PRO 1TB 4G | H92: FLAGSHIP | I92: AT&T | J92: =K92/1.16 -> 30171.552 | K92: 34999 | L92: 21399 | M92: 21199 | N92: 20959 | O92: 20559 | P92: 20099 | Q92: 21259 | R92: 20959 | S92: 20699 | T92: 20099 | U92: 19499 | V92: 21099 | W92: 20759 | X92: 20399 | Y92: 19659 | Z92: 18959 | AA92: 20959 | AB92: 20559 | AC92: 20099 | AD92: 19259 | AE92: 18359 | AF92: 20699 | AG92: 20099 | AH92: 19499 | AI92: 18359 | AJ92: 17199 | AK92: 19959 | AL92: 18999 | AM92: 18059 | AN92: 16159 | AO92: 14299 | AP92: 19659 | AQ92: 18559 | AR92: 17499 | AS92: 15299 | AT92: 13099 | AU92: 45597 | AV92: INDEFINIDO | AW92: 01 Noviembre 2024 - INDEFINIDO
A93: 99945 | B93: 999450 | C93: N.I151TBPTBL | D93: APPLE | E93: IPHONE 15 PRO 1TB TITANIO BLANCO ATT | F93: Apple Iphone 15 Pro 1TB 5G | G93: APPLE IPHONE 15 PRO 1TB 4G | H93: FLAGSHIP | I93: AT&T | J93: =K93/1.16 -> 30171.552 | K93: 34999 | L93: 21399 | M93: 21199 | N93: 20959 | O93: 20559 | P93: 20099 | Q93: 21259 | R93: 20959 | S93: 20699 | T93: 20099 | U93: 19499 | V93: 21099 | W93: 20759 | X93: 20399 | Y93: 19659 | Z93: 18959 | AA93: 20959 | AB93: 20559 | AC93: 20099 | AD93: 19259 | AE93: 18359 | AF93: 20699 | AG93: 20099 | AH93: 19499 | AI93: 18359 | AJ93: 17199 | AK93: 19959 | AL93: 18999 | AM93: 18059 | AN93: 16159 | AO93: 14299 | AP93: 19659 | AQ93: 18559 | AR93: 17499 | AS93: 15299 | AT93: 13099 | AU93: 45597 | AV93: INDEFINIDO | AW93: 01 Noviembre 2024 - INDEFINIDO
A94: 99948 | B94: 999480 | C94: N.I151TBPTNA | D94: APPLE | E94: IPHONE 15 PRO 1TB TITANIO NATURAL ATT | F94: Apple Iphone 15 Pro 1TB 5G | G94: APPLE IPHONE 15 PRO 1TB 4G | H94: FLAGSHIP | I94: AT&T | J94: =K94/1.16 -> 30171.552 | K94: 34999 | L94: 21399 | M94: 21199 | N94: 20959 | O94: 20559 | P94: 20099 | Q94: 21259 | R94: 20959 | S94: 20699 | T94: 20099 | U94: 19499 | V94: 21099 | W94: 20759 | X94: 20399 | Y94: 19659 | Z94: 18959 | AA94: 20959 | AB94: 20559 | AC94: 20099 | AD94: 19259 | AE94: 18359 | AF94: 20699 | AG94: 20099 | AH94: 19499 | AI94: 18359 | AJ94: 17199 | AK94: 19959 | AL94: 18999 | AM94: 18059 | AN94: 16159 | AO94: 14299 | AP94: 19659 | AQ94: 18559 | AR94: 17499 | AS94: 15299 | AT94: 13099 | AU94: 45597 | AV94: INDEFINIDO | AW94: 01 Noviembre 2024 - INDEFINIDO
A95: 99951 | B95: 999510 | C95: N.I151TBPTAZ | D95: APPLE | E95: IPHONE 15 PRO 1TB TITANIO AZUL ATT | F95: Apple Iphone 15 Pro 1TB 5G | G95: APPLE IPHONE 15 PRO 1TB 4G | H95: FLAGSHIP | I95: AT&T | J95: =K95/1.16 -> 30171.552 | K95: 34999 | L95: 21399 | M95: 21199 | N95: 20959 | O95: 20559 | P95: 20099 | Q95: 21259 | R95: 20959 | S95: 20699 | T95: 20099 | U95: 19499 | V95: 21099 | W95: 20759 | X95: 20399 | Y95: 19659 | Z95: 18959 | AA95: 20959 | AB95: 20559 | AC95: 20099 | AD95: 19259 | AE95: 18359 | AF95: 20699 | AG95: 20099 | AH95: 19499 | AI95: 18359 | AJ95: 17199 | AK95: 19959 | AL95: 18999 | AM95: 18059 | AN95: 16159 | AO95: 14299 | AP95: 19659 | AQ95: 18559 | AR95: 17499 | AS95: 15299 | AT95: 13099 | AU95: 45597 | AV95: INDEFINIDO | AW95: 01 Noviembre 2024 - INDEFINIDO
A96: 99927 | B96: 00999270 | C96: N.I15256PTAZ | D96: APPLE | E96: IPHONE 15 PRO 256GB TITANIO AZUL ATT | F96: Apple iPhone 15 Pro 256GB | G96: APPLE IPHONE 15 PRO 256GB 4G | H96: =IF(K96="REVISAR","REVISAR",IF(K96>=20000,"FLAGSHIP",IF(K96>=12000,"PREMIUM",IF(K96>=7000,"HIGH",IF(K96>=5000,"MID",IF(K96>=3000,"LOW","ENTRY")))))) -> FLAGSHIP | I96: AT&T | J96: =K96/1.16 -> 22412.931 | K96: 25999 | L96: 18249 | M96: 17999 | N96: 17799 | O96: 17349 | P96: 16949 | Q96: 18099 | R96: 17799 | S96: 17499 | T96: 16949 | U96: 16349 | V96: 17949 | W96: 17599 | X96: 17199 | Y96: 16499 | Z96: 15749 | AA96: 17799 | AB96: 17349 | AC96: 16899 | AD96: 16049 | AE96: 15199 | AF96: 17499 | AG96: 16899 | AH96: 16349 | AI96: 15199 | AJ96: 13999 | AK96: 16799 | AL96: 15849 | AM96: 14899 | AN96: 12999 | AO96: 11099 | AP96: 16499 | AQ96: 15399 | AR96: 14299 | AS96: 12099 | AT96: 9949 | AU96: 46059 | AV96: INDEFINIDO | AW96: =UPPER(TEXT(AU96, " dd \ mmmm \ aa")&" - "&TEXT(AV96, " dd \ mmmm \ aa")) -> 06 FEBRERO 26 - INDEFINIDO
A97: 99924 | B97: 00999240 | C97: N.I15256PTNA | D97: APPLE | E97: IPHONE 15 PRO 256GB TITANIO NATURAL ATT | F97: Apple iPhone 15 Pro 256GB | G97: APPLE IPHONE 15 PRO 256GB 4G | H97: =IF(K97="REVISAR","REVISAR",IF(K97>=20000,"FLAGSHIP",IF(K97>=12000,"PREMIUM",IF(K97>=7000,"HIGH",IF(K97>=5000,"MID",IF(K97>=3000,"LOW","ENTRY")))))) -> FLAGSHIP | I97: AT&T | J97: =K97/1.16 -> 22412.931 | K97: 25999 | L97: 18249 | M97: 17999 | N97: 17799 | O97: 17349 | P97: 16949 | Q97: 18099 | R97: 17799 | S97: 17499 | T97: 16949 | U97: 16349 | V97: 17949 | W97: 17599 | X97: 17199 | Y97: 16499 | Z97: 15749 | AA97: 17799 | AB97: 17349 | AC97: 16899 | AD97: 16049 | AE97: 15199 | AF97: 17499 | AG97: 16899 | AH97: 16349 | AI97: 15199 | AJ97: 13999 | AK97: 16799 | AL97: 15849 | AM97: 14899 | AN97: 12999 | AO97: 11099 | AP97: 16499 | AQ97: 15399 | AR97: 14299 | AS97: 12099 | AT97: 9949 | AU97: 46059 | AV97: INDEFINIDO | AW97: =UPPER(TEXT(AU97, " dd \ mmmm \ aa")&" - "&TEXT(AV97, " dd \ mmmm \ aa")) -> 06 FEBRERO 26 - INDEFINIDO
A98: 99918 | B98: 00999180 | C98: N.I15256PTNG | D98: APPLE | E98: IPHONE 15 PRO 256GB TITANIO NEGRO ATT | F98: Apple iPhone 15 Pro 256GB | G98: APPLE IPHONE 15 PRO 256GB 4G | H98: =IF(K98="REVISAR","REVISAR",IF(K98>=20000,"FLAGSHIP",IF(K98>=12000,"PREMIUM",IF(K98>=7000,"HIGH",IF(K98>=5000,"MID",IF(K98>=3000,"LOW","ENTRY")))))) -> FLAGSHIP | I98: AT&T | J98: =K98/1.16 -> 22412.931 | K98: 25999 | L98: 18249 | M98: 17999 | N98: 17799 | O98: 17349 | P98: 16949 | Q98: 18099 | R98: 17799 | S98: 17499 | T98: 16949 | U98: 16349 | V98: 17949 | W98: 17599 | X98: 17199 | Y98: 16499 | Z98: 15749 | AA98: 17799 | AB98: 17349 | AC98: 16899 | AD98: 16049 | AE98: 15199 | AF98: 17499 | AG98: 16899 | AH98: 16349 | AI98: 15199 | AJ98: 13999 | AK98: 16799 | AL98: 15849 | AM98: 14899 | AN98: 12999 | AO98: 11099 | AP98: 16499 | AQ98: 15399 | AR98: 14299 | AS98: 12099 | AT98: 9949 | AU98: 46059 | AV98: INDEFINIDO | AW98: =UPPER(TEXT(AU98, " dd \ mmmm \ aa")&" - "&TEXT(AV98, " dd \ mmmm \ aa")) -> 06 FEBRERO 26 - INDEFINIDO
A99: 99921 | B99: 00999210 | C99: N.I15256PTBL | D99: APPLE | E99: IPHONE 15 PRO 256GB TITANIO BLANCO ATT | F99: Apple iPhone 15 Pro 256GB | G99: APPLE IPHONE 15 PRO 256GB 4G | H99: FLAGSHIP | I99: AT&T | J99: =K99/1.16 -> 22412.931 | K99: 25999 | L99: 18249 | M99: 17999 | N99: 17799 | O99: 17349 | P99: 16949 | Q99: 18099 | R99: 17799 | S99: 17499 | T99: 16949 | U99: 16349 | V99: 17949 | W99: 17599 | X99: 17199 | Y99: 16499 | Z99: 15749 | AA99: 17799 | AB99: 17349 | AC99: 16899 | AD99: 16049 | AE99: 15199 | AF99: 17499 | AG99: 16899 | AH99: 16349 | AI99: 15199 | AJ99: 13999 | AK99: 16799 | AL99: 15849 | AM99: 14899 | AN99: 12999 | AO99: 11099 | AP99: 16499 | AQ99: 15399 | AR99: 14299 | AS99: 12099 | AT99: 9949 | AU99: 46059 | AV99: INDEFINIDO | AW99: 06 FEBRERO 26 - INDEFINIDO
A100: 99930 | B100: 00999300 | C100: N.I15512PTNG | D100: APPLE | E100: IPHONE 15 PRO 512GB TITANIO NEGRO ATT | F100: Apple iPhone 15 Pro 512GB | G100: APPLE IPHONE 15 PRO 512GB 4G | H100: =IF(K100="REVISAR","REVISAR",IF(K100>=20000,"FLAGSHIP",IF(K100>=12000,"PREMIUM",IF(K100>=7000,"HIGH",IF(K100>=5000,"MID",IF(K100>=3000,"LOW","ENTRY")))))) -> FLAGSHIP | I100: AT&T | J100: =K100/1.16 -> 26292.241 | K100: 30499 | L100: 21149 | M100: 20949 | N100: 20749 | O100: 20299 | P100: 19849 | Q100: 20999 | R100: 20749 | S100: 20449 | T100: 19849 | U100: 19299 | V100: 20899 | W100: 20499 | X100: 20149 | Y100: 19449 | Z100: 18699 | AA100: 20749 | AB100: 20299 | AC100: 19849 | AD100: 18999 | AE100: 18099 | AF100: 20449 | AG100: 19849 | AH100: 19299 | AI100: 18099 | AJ100: 16949 | AK100: 19699 | AL100: 18749 | AM100: 17799 | AN100: 15949 | AO100: 14049 | AP100: 19399 | AQ100: 18349 | AR100: 17249 | AS100: 15049 | AT100: 12849 | AU100: 46059 | AV100: INDEFINIDO | AW100: =UPPER(TEXT(AU100, " dd \ mmmm \ aa")&" - "&TEXT(AV100, " dd \ mmmm \ aa")) -> 06 FEBRERO 26 - INDEFINIDO
A101: 99939 | B101: 00999390 | C101: N.I15512PTAZ | D101: APPLE | E101: IPHONE 15 PRO 512GB TITANIO AZUL ATT | F101: Apple iPhone 15 Pro 512GB | G101: APPLE IPHONE 15 PRO 512GB 4G | H101: FLAGSHIP | I101: AT&T | J101: =K101/1.16 -> 26292.241 | K101: 30499 | L101: 21149 | M101: 20949 | N101: 20749 | O101: 20299 | P101: 19849 | Q101: 20999 | R101: 20749 | S101: 20449 | T101: 19849 | U101: 19299 | V101: 20899 | W101: 20499 | X101: 20149 | Y101: 19449 | Z101: 18699 | AA101: 20749 | AB101: 20299 | AC101: 19849 | AD101: 18999 | AE101: 18099 | AF101: 20449 | AG101: 19849 | AH101: 19299 | AI101: 18099 | AJ101: 16949 | AK101: 19699 | AL101: 18749 | AM101: 17799 | AN101: 15949 | AO101: 14049 | AP101: 19399 | AQ101: 18349 | AR101: 17249 | AS101: 15049 | AT101: 12849 | AU101: 46059 | AV101: INDEFINIDO | AW101: =UPPER(TEXT(AU101, " dd \ mmmm \ aa")&" - "&TEXT(AV101, " dd \ mmmm \ aa")) -> 06 FEBRERO 26 - INDEFINIDO
A102: 99933 | B102: 00999330 | C102: N.I15512PTBL | D102: APPLE | E102: IPHONE 15 PRO 512GB TITANIO BLANCO ATT | F102: Apple iPhone 15 Pro 512GB | G102: APPLE IPHONE 15 PRO 512GB 4G | H102: FLAGSHIP | I102: AT&T | J102: =K102/1.16 -> 26292.241 | K102: 30499 | L102: 21149 | M102: 20949 | N102: 20749 | O102: 20299 | P102: 19849 | Q102: 20999 | R102: 20749 | S102: 20449 | T102: 19849 | U102: 19299 | V102: 20899 | W102: 20499 | X102: 20149 | Y102: 19449 | Z102: 18699 | AA102: 20749 | AB102: 20299 | AC102: 19849 | AD102: 18999 | AE102: 18099 | AF102: 20449 | AG102: 19849 | AH102: 19299 | AI102: 18099 | AJ102: 16949 | AK102: 19699 | AL102: 18749 | AM102: 17799 | AN102: 15949 | AO102: 14049 | AP102: 19399 | AQ102: 18349 | AR102: 17249 | AS102: 15049 | AT102: 12849 | AU102: 46059 | AV102: INDEFINIDO | AW102: =UPPER(TEXT(AU102, " dd \ mmmm \ aa")&" - "&TEXT(AV102, " dd \ mmmm \ aa")) -> 06 FEBRERO 26 - INDEFINIDO
A103: 99936 | B103: 00999360 | C103: N.I15512PTNA | D103: APPLE | E103: IPHONE 15 PRO 512GB TITANIO NATURAL ATT | F103: Apple iPhone 15 Pro 512GB | G103: APPLE IPHONE 15 PRO 512GB 4G | H103: FLAGSHIP | I103: AT&T | J103: =K103/1.16 -> 26292.241 | K103: 30499 | L103: 21149 | M103: 20949 | N103: 20749 | O103: 20299 | P103: 19849 | Q103: 20999 | R103: 20749 | S103: 20449 | T103: 19849 | U103: 19299 | V103: 20899 | W103: 20499 | X103: 20149 | Y103: 19449 | Z103: 18699 | AA103: 20749 | AB103: 20299 | AC103: 19849 | AD103: 18999 | AE103: 18099 | AF103: 20449 | AG103: 19849 | AH103: 19299 | AI103: 18099 | AJ103: 16949 | AK103: 19699 | AL103: 18749 | AM103: 17799 | AN103: 15949 | AO103: 14049 | AP103: 19399 | AQ103: 18349 | AR103: 17249 | AS103: 15049 | AT103: 12849 | AU103: 46059 | AV103: INDEFINIDO | AW103: =UPPER(TEXT(AU103, " dd \ mmmm \ aa")&" - "&TEXT(AV103, " dd \ mmmm \ aa")) -> 06 FEBRERO 26 - INDEFINIDO
A104: 99987 | B104: 00999870 | C104: N.I151TPMTAZ | D104: APPLE | E104: IPHONE 15 PRO MAX 1TB TITANIO AZUL ATT | F104: Apple iPhone 15 Pro Max 1TB | G104: APPLE IPHONE 15 PRO MAX 1TB 4G | H104: FLAGSHIP | I104: AT&T | J104: =K104/1.16 -> 32757.759 | K104: 37999 | L104: 34099 | M104: 33899 | N104: 33599 | O104: 33199 | P104: 32799 | Q104: 33899 | R104: 33599 | S104: 33299 | T104: 32699 | U104: 32199 | V104: 33799 | W104: 33399 | X104: 32999 | Y104: 32299 | Z104: 31599 | AA104: 33599 | AB104: 33199 | AC104: 32699 | AD104: 31799 | AE104: 30999 | AF104: 33299 | AG104: 32699 | AH104: 32099 | AI104: 30899 | AJ104: 29799 | AK104: 32599 | AL104: 31599 | AM104: 30599 | AN104: 28699 | AO104: 26799 | AP104: 32299 | AQ104: 31199 | AR104: 29999 | AS104: 27799 | AT104: 25599 | AU104: 45564 | AV104: INDEFINIDO | AW104: 29 Septiembre 2024 - INDEFINIDO
A105: 99981 | B105: 00999810 | C105: N.I151TPMTBL | D105: APPLE | E105: IPHONE 15 PRO MAX 1TB TITANIO BLANCO ATT | F105: Apple iPhone 15 Pro Max 1TB | G105: APPLE IPHONE 15 PRO MAX 1TB 4G | H105: FLAGSHIP | I105: AT&T | J105: =K105/1.16 -> 32757.759 | K105: 37999 | L105: 34099 | M105: 33899 | N105: 33599 | O105: 33199 | P105: 32799 | Q105: 33899 | R105: 33599 | S105: 33299 | T105: 32699 | U105: 32199 | V105: 33799 | W105: 33399 | X105: 32999 | Y105: 32299 | Z105: 31599 | AA105: 33599 | AB105: 33199 | AC105: 32699 | AD105: 31799 | AE105: 30999 | AF105: 33299 | AG105: 32699 | AH105: 32099 | AI105: 30899 | AJ105: 29799 | AK105: 32599 | AL105: 31599 | AM105: 30599 | AN105: 28699 | AO105: 26799 | AP105: 32299 | AQ105: 31199 | AR105: 29999 | AS105: 27799 | AT105: 25599 | AU105: 45564 | AV105: INDEFINIDO | AW105: 29 Septiembre 2024 - INDEFINIDO
A106: 99984 | B106: 00999840 | C106: N.I151TPMTNA | D106: APPLE | E106: IPHONE 15 PRO MAX 1TB TITANIO NATURAL ATT | F106: Apple iPhone 15 Pro Max 1TB | G106: APPLE IPHONE 15 PRO MAX 1TB 4G | H106: FLAGSHIP | I106: AT&T | J106: =K106/1.16 -> 32757.759 | K106: 37999 | L106: 34099 | M106: 33899 | N106: 33599 | O106: 33199 | P106: 32799 | Q106: 33899 | R106: 33599 | S106: 33299 | T106: 32699 | U106: 32199 | V106: 33799 | W106: 33399 | X106: 32999 | Y106: 32299 | Z106: 31599 | AA106: 33599 | AB106: 33199 | AC106: 32699 | AD106: 31799 | AE106: 30999 | AF106: 33299 | AG106: 32699 | AH106: 32099 | AI106: 30899 | AJ106: 29799 | AK106: 32599 | AL106: 31599 | AM106: 30599 | AN106: 28699 | AO106: 26799 | AP106: 32299 | AQ106: 31199 | AR106: 29999 | AS106: 27799 | AT106: 25599 | AU106: 45564 | AV106: INDEFINIDO | AW106: 29 Septiembre 2024 - INDEFINIDO
A107: 99978 | B107: 00999780 | C107: N.I151TPMTNG | D107: APPLE | E107: IPHONE 15 PRO MAX 1TB TITANIO NEGRO ATT | F107: Apple iPhone 15 Pro Max 1TB | G107: APPLE IPHONE 15 PRO MAX 1TB 4G | H107: FLAGSHIP | I107: AT&T | J107: =K107/1.16 -> 32757.759 | K107: 37999 | L107: 34099 | M107: 33899 | N107: 33599 | O107: 33199 | P107: 32799 | Q107: 33899 | R107: 33599 | S107: 33299 | T107: 32699 | U107: 32199 | V107: 33799 | W107: 33399 | X107: 32999 | Y107: 32299 | Z107: 31599 | AA107: 33599 | AB107: 33199 | AC107: 32699 | AD107: 31799 | AE107: 30999 | AF107: 33299 | AG107: 32699 | AH107: 32099 | AI107: 30899 | AJ107: 29799 | AK107: 32599 | AL107: 31599 | AM107: 30599 | AN107: 28699 | AO107: 26799 | AP107: 32299 | AQ107: 31199 | AR107: 29999 | AS107: 27799 | AT107: 25599 | AU107: 45564 | AV107: INDEFINIDO | AW107: 29 Septiembre 2024 - INDEFINIDO
A108: 99963 | B108: 00999630 | C108: N.I15256PMTA | D108: APPLE | E108: IPHONE 15 PRO MAX 256GB TITANIO AZUL ATT | F108: Apple iPhone 15 Pro Max 256GB | G108: APPLE IPHONE 15 PRO MAX 256GB 4G | H108: FLAGSHIP | I108: AT&T | J108: =K108/1.16 -> 24999.138 | K108: 28999 | L108: 25699 | M108: 25399 | N108: 24999 | O108: 24299 | P108: 23599 | Q108: 25499 | R108: 24999 | S108: 24499 | T108: 23499 | U108: 22599 | V108: 25199 | W108: 24599 | X108: 24099 | Y108: 22799 | Z108: 21699 | AA108: 24999 | AB108: 24299 | AC108: 23599 | AD108: 22099 | AE108: 20699 | AF108: 24499 | AG108: 23499 | AH108: 22699 | AI108: 20699 | AJ108: 18899 | AK108: 23299 | AL108: 21799 | AM108: 20299 | AN108: 17199 | AO108: 14199 | AP108: 22799 | AQ108: 21099 | AR108: 19399 | AS108: 15799 | AT108: 12299 | AU108: 45564 | AV108: INDEFINIDO | AW108: 29 Septiembre 2024 - INDEFINIDO
A109: 99957 | B109: 00999570 | C109: N.I15256PMTB | D109: APPLE | E109: IPHONE 15 PRO MAX 256GB TITANIO BLANCO ATT | F109: Apple iPhone 15 Pro Max 256GB | G109: APPLE IPHONE 15 PRO MAX 256GB 4G | H109: FLAGSHIP | I109: AT&T | J109: =K109/1.16 -> 24999.138 | K109: 28999 | L109: 25699 | M109: 25399 | N109: 24999 | O109: 24299 | P109: 23599 | Q109: 25499 | R109: 24999 | S109: 24499 | T109: 23499 | U109: 22599 | V109: 25199 | W109: 24599 | X109: 24099 | Y109: 22799 | Z109: 21699 | AA109: 24999 | AB109: 24299 | AC109: 23599 | AD109: 22099 | AE109: 20699 | AF109: 24499 | AG109: 23499 | AH109: 22699 | AI109: 20699 | AJ109: 18899 | AK109: 23299 | AL109: 21799 | AM109: 20299 | AN109: 17199 | AO109: 14199 | AP109: 22799 | AQ109: 21099 | AR109: 19399 | AS109: 15799 | AT109: 12299 | AU109: 45564 | AV109: INDEFINIDO | AW109: 29 Septiembre 2024 - INDEFINIDO
A110: 99960 | B110: 00999600 | C110: N.I15256PMNA | D110: APPLE | E110: IPHONE 15 PRO MAX 256GB TITANIO NATURAL ATT | F110: Apple iPhone 15 Pro Max 256GB | G110: APPLE IPHONE 15 PRO MAX 256GB 4G | H110: FLAGSHIP | I110: AT&T | J110: =K110/1.16 -> 24999.138 | K110: 28999 | L110: 25699 | M110: 25399 | N110: 24999 | O110: 24299 | P110: 23599 | Q110: 25499 | R110: 24999 | S110: 24499 | T110: 23499 | U110: 22599 | V110: 25199 | W110: 24599 | X110: 24099 | Y110: 22799 | Z110: 21699 | AA110: 24999 | AB110: 24299 | AC110: 23599 | AD110: 22099 | AE110: 20699 | AF110: 24499 | AG110: 23499 | AH110: 22699 | AI110: 20699 | AJ110: 18899 | AK110: 23299 | AL110: 21799 | AM110: 20299 | AN110: 17199 | AO110: 14199 | AP110: 22799 | AQ110: 21099 | AR110: 19399 | AS110: 15799 | AT110: 12299 | AU110: 45564 | AV110: INDEFINIDO | AW110: 29 Septiembre 2024 - INDEFINIDO
A111: 99954 | B111: 00999540 | C111: N.I15256PMTN | D111: APPLE | E111: IPHONE 15 PRO MAX 256GB TITANIO NEGRO ATT | F111: Apple iPhone 15 Pro Max 256GB | G111: APPLE IPHONE 15 PRO MAX 256GB 4G | H111: FLAGSHIP | I111: AT&T | J111: =K111/1.16 -> 24999.138 | K111: 28999 | L111: 25699 | M111: 25399 | N111: 24999 | O111: 24299 | P111: 23599 | Q111: 25499 | R111: 24999 | S111: 24499 | T111: 23499 | U111: 22599 | V111: 25199 | W111: 24599 | X111: 24099 | Y111: 22799 | Z111: 21699 | AA111: 24999 | AB111: 24299 | AC111: 23599 | AD111: 22099 | AE111: 20699 | AF111: 24499 | AG111: 23499 | AH111: 22699 | AI111: 20699 | AJ111: 18899 | AK111: 23299 | AL111: 21799 | AM111: 20299 | AN111: 17199 | AO111: 14199 | AP111: 22799 | AQ111: 21099 | AR111: 19399 | AS111: 15799 | AT111: 12299 | AU111: 45564 | AV111: INDEFINIDO | AW111: 29 Septiembre 2024 - INDEFINIDO
A112: 99975 | B112: 00999750 | C112: N.I15512PMTA | D112: APPLE | E112: IPHONE 15 PRO MAX 512GB TITANIO AZUL ATT | F112: Apple iPhone 15 Pro Max 512GB | G112: APPLE IPHONE 15 PRO MAX 512GB 4G | H112: =IF(K112="REVISAR","REVISAR",IF(K112>=20000,"FLAGSHIP",IF(K112>=12000,"PREMIUM",IF(K112>=7000,"HIGH",IF(K112>=5000,"MID",IF(K112>=3000,"LOW","ENTRY")))))) -> FLAGSHIP | I112: AT&T | J112: =K112/1.16 -> 28878.448 | K112: 33499 | L112: 20999 | M112: 20799 | N112: 20599 | O112: 20149 | P112: 19699 | Q112: 20849 | R112: 20549 | S112: 20299 | T112: 19699 | U112: 19099 | V112: 20699 | W112: 20349 | X112: 19999 | Y112: 19249 | Z112: 18549 | AA112: 20549 | AB112: 20149 | AC112: 19699 | AD112: 18849 | AE112: 17949 | AF112: 20299 | AG112: 19699 | AH112: 19099 | AI112: 17949 | AJ112: 16799 | AK112: 19549 | AL112: 18599 | AM112: 17649 | AN112: 15749 | AO112: 13899 | AP112: 19249 | AQ112: 18149 | AR112: 17099 | AS112: 14899 | AT112: 12699 | AU112: 46059 | AV112: INDEFINIDO | AW112: =UPPER(TEXT(AU112, " dd \ mmmm \ aa")&" - "&TEXT(AV112, " dd \ mmmm \ aa")) -> 06 FEBRERO 26 - INDEFINIDO
A113: 99972 | B113: 00999720 | C113: N.I15512PMNA | D113: APPLE | E113: IPHONE 15 PRO MAX 512GB TITANIO NATURAL ATT | F113: Apple iPhone 15 Pro Max 512GB | G113: APPLE IPHONE 15 PRO MAX 512GB 4G | H113: =IF(K113="REVISAR","REVISAR",IF(K113>=20000,"FLAGSHIP",IF(K113>=12000,"PREMIUM",IF(K113>=7000,"HIGH",IF(K113>=5000,"MID",IF(K113>=3000,"LOW","ENTRY")))))) -> FLAGSHIP | I113: AT&T | J113: =K113/1.16 -> 28878.448 | K113: 33499 | L113: 20999 | M113: 20799 | N113: 20599 | O113: 20149 | P113: 19699 | Q113: 20849 | R113: 20549 | S113: 20299 | T113: 19699 | U113: 19099 | V113: 20699 | W113: 20349 | X113: 19999 | Y113: 19249 | Z113: 18549 | AA113: 20549 | AB113: 20149 | AC113: 19699 | AD113: 18849 | AE113: 17949 | AF113: 20299 | AG113: 19699 | AH113: 19099 | AI113: 17949 | AJ113: 16799 | AK113: 19549 | AL113: 18599 | AM113: 17649 | AN113: 15749 | AO113: 13899 | AP113: 19249 | AQ113: 18149 | AR113: 17099 | AS113: 14899 | AT113: 12699 | AU113: 46059 | AV113: INDEFINIDO | AW113: =UPPER(TEXT(AU113, " dd \ mmmm \ aa")&" - "&TEXT(AV113, " dd \ mmmm \ aa")) -> 06 FEBRERO 26 - INDEFINIDO
A114: 99966 | B114: 00999660 | C114: N.I15512PMTN | D114: APPLE | E114: IPHONE 15 PRO MAX 512GB TITANIO NEGRO ATT | F114: Apple iPhone 15 Pro Max 512GB | G114: APPLE IPHONE 15 PRO MAX 512GB 4G | H114: =IF(K114="REVISAR","REVISAR",IF(K114>=20000,"FLAGSHIP",IF(K114>=12000,"PREMIUM",IF(K114>=7000,"HIGH",IF(K114>=5000,"MID",IF(K114>=3000,"LOW","ENTRY")))))) -> FLAGSHIP | I114: AT&T | J114: =K114/1.16 -> 28878.448 | K114: 33499 | L114: 20999 | M114: 20799 | N114: 20599 | O114: 20149 | P114: 19699 | Q114: 20849 | R114: 20549 | S114: 20299 | T114: 19699 | U114: 19099 | V114: 20699 | W114: 20349 | X114: 19999 | Y114: 19249 | Z114: 18549 | AA114: 20549 | AB114: 20149 | AC114: 19699 | AD114: 18849 | AE114: 17949 | AF114: 20299 | AG114: 19699 | AH114: 19099 | AI114: 17949 | AJ114: 16799 | AK114: 19549 | AL114: 18599 | AM114: 17649 | AN114: 15749 | AO114: 13899 | AP114: 19249 | AQ114: 18149 | AR114: 17099 | AS114: 14899 | AT114: 12699 | AU114: 46059 | AV114: INDEFINIDO | AW114: =UPPER(TEXT(AU114, " dd \ mmmm \ aa")&" - "&TEXT(AV114, " dd \ mmmm \ aa")) -> 06 FEBRERO 26 - INDEFINIDO
A115: 99969 | B115: 00999690 | C115: N.I15512PMTB | D115: APPLE | E115: IPHONE 15 PRO MAX 512GB TITANIO BLANCO ATT | F115: Apple iPhone 15 Pro Max 512GB | G115: APPLE IPHONE 15 PRO MAX 512GB 4G | H115: FLAGSHIP | I115: AT&T | J115: =K115/1.16 -> 28878.448 | K115: 33499 | L115: 20999 | M115: 20799 | N115: 20599 | O115: 20149 | P115: 19699 | Q115: 20849 | R115: 20549 | S115: 20299 | T115: 19699 | U115: 19099 | V115: 20699 | W115: 20349 | X115: 19999 | Y115: 19249 | Z115: 18549 | AA115: 20549 | AB115: 20149 | AC115: 19699 | AD115: 18849 | AE115: 17949 | AF115: 20299 | AG115: 19699 | AH115: 19099 | AI115: 17949 | AJ115: 16799 | AK115: 19549 | AL115: 18599 | AM115: 17649 | AN115: 15749 | AO115: 13899 | AP115: 19249 | AQ115: 18149 | AR115: 17099 | AS115: 14899 | AT115: 12699 | AU115: 46059 | AV115: INDEFINIDO | AW115: =UPPER(TEXT(AU115, " dd \ mmmm \ aa")&" - "&TEXT(AV115, " dd \ mmmm \ aa")) -> 06 FEBRERO 26 - INDEFINIDO
A116: 100894 | B116: 01008940 | C116: N.IP16128BL | D116: APPLE | E116: IPHONE 16 128GB BLANCO ATT | F116: Iphone 16 128 GB | G116: APPLE IPHONE 16 128GB 5G | H116: =IF(K116="REVISAR","REVISAR",IF(K116>=20000,"FLAGSHIP",IF(K116>=12000,"PREMIUM",IF(K116>=7000,"HIGH",IF(K116>=5000,"MID",IF(K116>=3000,"LOW","ENTRY")))))) -> PREMIUM | I116: AT&T | J116: =K116/1.16 -> 17240.517 | K116: 19999 | L116: 15299 | M116: 14949 | N116: 14599 | O116: 13899 | P116: 13249 | Q116: 15049 | R116: 14599 | S116: 14149 | T116: 13249 | U116: 12349 | V116: 14849 | W116: 14249 | X116: 13699 | Y116: 12549 | Z116: 11399 | AA116: 14599 | AB116: 13899 | AC116: 13249 | AD116: 11849 | AE116: 10499 | AF116: 14149 | AG116: 13249 | AH116: 12299 | AI116: 10499 | AJ116: 8699 | AK116: 12999 | AL116: 11549 | AM116: 10049 | AN116: 7099 | AO116: 4099 | AP116: 12549 | AQ116: 10849 | AR116: 9149 | AS116: 5699 | AT116: 2299 | AU116: 46110 | AV116: INDEFINIDO | AW116: =UPPER(TEXT(AU116, " dd \ mmmm \ aa")&" - "&TEXT(AV116, " dd \ mmmm \ aa")) -> 29 MARZO 26 - INDEFINIDO
A117: 100891 | B117: 01008910 | C117: N.IP16128NE | D117: APPLE | E117: IPHONE 16 128GB NEGRO ATT | F117: Iphone 16 128 GB | G117: APPLE IPHONE 16 128GB 5G | H117: =IF(K117="REVISAR","REVISAR",IF(K117>=20000,"FLAGSHIP",IF(K117>=12000,"PREMIUM",IF(K117>=7000,"HIGH",IF(K117>=5000,"MID",IF(K117>=3000,"LOW","ENTRY")))))) -> PREMIUM | I117: AT&T | J117: =K117/1.16 -> 17240.517 | K117: 19999 | L117: 15299 | M117: 14949 | N117: 14599 | O117: 13899 | P117: 13249 | Q117: 15049 | R117: 14599 | S117: 14149 | T117: 13249 | U117: 12349 | V117: 14849 | W117: 14249 | X117: 13699 | Y117: 12549 | Z117: 11399 | AA117: 14599 | AB117: 13899 | AC117: 13249 | AD117: 11849 | AE117: 10499 | AF117: 14149 | AG117: 13249 | AH117: 12299 | AI117: 10499 | AJ117: 8699 | AK117: 12999 | AL117: 11549 | AM117: 10049 | AN117: 7099 | AO117: 4099 | AP117: 12549 | AQ117: 10849 | AR117: 9149 | AS117: 5699 | AT117: 2299 | AU117: 46110 | AV117: INDEFINIDO | AW117: =UPPER(TEXT(AU117, " dd \ mmmm \ aa")&" - "&TEXT(AV117, " dd \ mmmm \ aa")) -> 29 MARZO 26 - INDEFINIDO
A118: 100882 | B118: 01008820 | C118: N.IP16128UM | D118: APPLE | E118: IPHONE 16 128GB ULTRAMARINO ATT | F118: Iphone 16 128 GB | G118: APPLE IPHONE 16 128GB 5G | H118: =IF(K118="REVISAR","REVISAR",IF(K118>=20000,"FLAGSHIP",IF(K118>=12000,"PREMIUM",IF(K118>=7000,"HIGH",IF(K118>=5000,"MID",IF(K118>=3000,"LOW","ENTRY")))))) -> PREMIUM | I118: AT&T | J118: =K118/1.16 -> 17240.517 | K118: 19999 | L118: 15299 | M118: 14949 | N118: 14599 | O118: 13899 | P118: 13249 | Q118: 15049 | R118: 14599 | S118: 14149 | T118: 13249 | U118: 12349 | V118: 14849 | W118: 14249 | X118: 13699 | Y118: 12549 | Z118: 11399 | AA118: 14599 | AB118: 13899 | AC118: 13249 | AD118: 11849 | AE118: 10499 | AF118: 14149 | AG118: 13249 | AH118: 12299 | AI118: 10499 | AJ118: 8699 | AK118: 12999 | AL118: 11549 | AM118: 10049 | AN118: 7099 | AO118: 4099 | AP118: 12549 | AQ118: 10849 | AR118: 9149 | AS118: 5699 | AT118: 2299 | AU118: 46110 | AV118: INDEFINIDO | AW118: =UPPER(TEXT(AU118, " dd \ mmmm \ aa")&" - "&TEXT(AV118, " dd \ mmmm \ aa")) -> 29 MARZO 26 - INDEFINIDO
...

Sheet Catalogo
A1: Marca | B1: Alcatel | C1: Apple | D1: Hisense | E1: Huawei | F1: Motorola | G1: Samsung | H1: Honor | I1: Xiaomi | J1: OPPO | K1: ZTE | L1: REALME | M1: NUBIA | N1: Google
A2: ALCATEL | B2: ALCATEL 1 SE 32GB 4G | C2: APPLE IPHONE 11 64GB 4G | D2: HISENSE E20 16GB 4G | E2: HUAWEI MATE 50 PRO 256GB 4G | F2: MOTO EDGE 70 PRO BUNDLEMOTO WATCH | G2: SAMSUNG GALAXY A01 16GB 4G | H2: HONOR 200 256GB 5G / BUNDLE | I2: XIAOMI 11 LITE NE 128GB 5G | J2: OPPO A12 32GB 4G | K2: ZTE AXON 60 256GB 4G | L2: REALME C11 2021 64GB 4G | N2: GOOGLE PIXEL 10 128GB 5G
A3: APPLE | B3: ALCATEL 1 SE 64GB 4G | C3: APPLE IPHONE 11 PRO 256GB 4G | D3: HISENSE E20S 32GB 4G | E3: HUAWEI NOVA 8 128GB 4G / BUNDLE | F3: MOTOROLA EDGE 50 512GB 5G | G3: SAMSUNG GALAXY A01 CORE 32GB 4G | H3: HONOR 400 512GB 5G | I3: XIAOMI 11 LITE NE 128GB 5G | J3: OPPO A38 128GB 4G | K3: ZTE AXON 60 LITE 256GB 4G | L3: REALME C35 128GB 4G | N3: GOOGLE PIXEL 10 256GB 5G
A4: GOOGLE | B4: ALCATEL 1B 5002M | C4: APPLE IPHONE 11 PRO 64GB 4G | D4: HISENSE E50 64GB 4G | E4: HUAWEI NOVA 8I 128GB 4G | F4: MOTOROLA EDGE 60 FUSION 256GB 5G | G4: SAMSUNG GALAXY A03 128GB 4G | H4: HONOR 400 LITE 256GB 5G | I4: XIAOMI 11T 256GB 4G | J4: OPPO A40 256GB 4G | K4: ZTE BLADE A55 128GB 4G | N4: GOOGLE PIXEL 10 PRO 256GB 5G
A5: HISENSE | B5: ALCATEL 3 2020 | C5: APPLE IPHONE 11 PRO MAX 64GB 4G | D5: HISENSE E50I | E5: HUAWEI NOVA 9 128GB 4G | F5: MOTOROLA EDGE 60 PRO 512GB 5G | G5: SAMSUNG GALAXY A03 64GB 4G | H5: HONOR 50 6GB 4G | I5: XIAOMI 11T 256GB 4G | J5: OPPO A5 256GB 4G | K5: ZTE BLADE A7 2020 64GB 4G | N5: GOOGLE PIXEL 10 PRO 512GB 5G
A6: HONOR | C6: APPLE IPHONE 12 256GB 4G | D6: HISENSE E60 64GB 4G | E6: HUAWEI NOVA 9 SE 128GB 4G | F6: MOTOROLA EDGE 70 512GB 5G | G6: SAMSUNG GALAXY A04 64GB 4G | H6: HONOR 50 8GB 4G | I6: XIAOMI 11T PRO 128GB 4G | J6: OPPO A5 PRO 256GB 4G | K6: ZTE BLADE V50 SMART 128GB 4G | N6: GOOGLE PIXEL 10 PRO XL 256GB 5G
A7: HUAWEI | C7: APPLE IPHONE 12 MINI 128GB | D7: HISENSE E60 LITE 64GB 4G | E7: HUAWEI NOVA Y60 64GB 4G | F7: MOTOROLA EDGE 70 FUSION 256GB 5G | G7: SAMSUNG GALAXY A05 64GB 4G | H7: HONOR 50 LITE 128GB 4G | I7: XIAOMI 11T PRO 128GB 4G | J7: OPPO A5 PRO 5G / BDL | N7: GOOGLE PIXEL 10 PRO XL 512GB 5G
A8: MOTOROLA | C8: APPLE IPHONE 12 MINI 256GB 4G | D8: HISENSE H60 SMART 128GB 4G | E8: HUAWEI NOVA Y61 64GB 4G | F8: MOTOROLA G04 128GB 4G | G8: SAMSUNG GALAXY A06 64GB 4G | H8: HONOR 600 512GB 5G | I8: XIAOMI 12 256GB 4G | J8: OPPO A54 128GB 4G | N8: GOOGLE PIXEL 9A 128GB 5G
A9: NUBIA | C9: APPLE IPHONE 12 MINI 64GB 4G | E9: HUAWEI NOVA Y70 128GB 4G | F9: MOTOROLA G24 256GB 4G | G9: SAMSUNG GALAXY A07 128GB 4G | H9: HONOR 8A 128GB 4G | I9: XIAOMI 12 256GB 4G | J9: OPPO A57 64GB 4G
A10: OPPO | C10: APPLE IPHONE 12 PRO 256GB 4G | E10: HUAWEI NOVA Y90 256GB 4G | F10: MOTOROLA G54 128GB 5G | G10: SAMSUNG GALAXY A07 64GB 4G | H10: HONOR 90 256GB 5G | I10: XIAOMI 15T BUNDLE BOCINA SOUND OUTDOOR | J10: OPPO A6 BUNDLE ENCO BUDS 3
A11: REALME | C11: APPLE IPHONE 12 PRO 512GB 4G | E11: HUAWEI P40 128GB LITE 4G | F11: MOTOROLA G54 256GB 5G | G11: SAMSUNG GALAXY A13 128GB 4G | H11: HONOR 90 512GB 4G | I11: XIAOMI 15T BUNDLE BOCINA SOUND OUTDOOR | J11: OPPO A60 256GB 4G
A12: SAMSUNG | C12: APPLE IPHONE 13 128GB 4G | E12: HUAWEI P50 128GB 4G | F12: MOTOROLA G84 256GB 5G | G12: SAMSUNG GALAXY A16 128GB 4G | H12: HONOR MAGIC 5 LITE 128GB 4G / BUNDLE | I12: XIAOMI 15T PRO BUNDLE REDMI PAD | J12: OPPO A6K 256GB 5G
A13: XIAOMI | C13: APPLE IPHONE 13 256GB 4G | E13: HUAWEI P50 PRO 256GB 4G | F13: MOTOROLA MOTO E22 32GB 4G | G13: SAMSUNG GALAXY A17 128GB 4G | H13: HONOR MAGIC 5 LITE 256GB 4G | I13: XIAOMI 15T PRO BUNDLE REDMI PAD | J13: OPPO A6T 128GB 4G
A14: ZTE | C14: APPLE IPHONE 13 512GB 4G | E14: HUAWEI P50 PRO 256GB 4G BUNDLE | F14: MOTOROLA MOTO E32 64GB 4G | G14: SAMSUNG GALAXY A23 128GB 4G | H14: HONOR MAGIC 6 LITE 256GB 5G | I14: XIAOMI 17T 512GB 5G BUNDLE | J14: OPPO A6X 128GB 4G
C15: APPLE IPHONE 13 MINI 128GB 4G | E15: HUAWEI Y5P 32GB 4G | F15: MOTOROLA MOTO E5 16GB 4G | G15: SAMSUNG GALAXY A26 128GB 5G | H15: HONOR MAGIC 8 LITE BUNDLE | I15: XIAOMI 17T 512GB 5G BUNDLE | J15: OPPO A72 128GB 4G
C16: APPLE IPHONE 13 PRO 128GB 4G | E16: HUAWEI Y6S 64GB 4G | F16: MOTOROLA MOTO E6I 32GB 4G | G16: Samsung Galaxy A27 128GB 5G | H16: HONOR MAGIC VS | I16: XIAOMI 17T PRO REDMI PAD 2 512GB 5G | J16: OPPO A79 256GB 5G
C17: APPLE IPHONE 13 PRO 256GB 4G | E17: HUAWEI Y7A 64GB 4G | F17: MOTOROLA MOTO E7I POWER 32GB 4G | G17: SAMSUNG GALAXY A33 128GB 4G | H17: HONOR MAGIC7 LITE 512GB 5G / BUNDLE | I17: XIAOMI 17T PRO REDMI PAD 2 512GB 5G | J17: OPPO A80 256GB 5G
C18: APPLE IPHONE 13 PRO 512GB 4G | E18: HUAWEI Y7P 64GB 4G | F18: MOTOROLA MOTO EDGE 20 PRO 256GB 4G | G18: SAMSUNG GALAXY A34 128GB 5G | H18: HONOR MAGIC7 PRO 512GB 5G | I18: XIAOMI NOTE 13 256GB 4G | J18: OPPO FIND X8 PRO 512GB 5G
C19: APPLE IPHONE 13 PRO MAX 128GB 4G | E19: HUAWEI Y7S 64GB 4G | F19: MOTOROLA MOTO EDGE 30 128GB 4G | G19: SAMSUNG GALAXY A35 128GB 5G | H19: HONOR MAGIC8 PRO BUNDLE PAD X8B | I19: XIAOMI NOTE 13 256GB 4G | J19: OPPO FIND X9 PRO 5G
C20: APPLE IPHONE 13 PRO MAX 1TB | E20: HUAWEI Y9A 128GB 4G / BUNDLE | F20: MOTOROLA MOTO EDGE 30 PRO 256GB 4G | G20: SAMSUNG GALAXY A36 128GB 5G | H20: HONOR MAGICV3 512GB 5G | I20: XIAOMI NOTE 13 PRO 256GB 4G | J20: OPPO RENO 10 256GB 4G
C21: APPLE IPHONE 13 PRO MAX 256GB 4G | F21: MOTOROLA MOTO EDGE 30 ULTRA 256GB 4G / BUNDLE | G21: SAMSUNG GALAXY A37 256GB 5G | H21: HONOR X5B PLUS 256GB 4G | I21: XIAOMI NOTE 13 PRO 256GB 4G | J21: OPPO RENO 12 512GB 5G
C22: APPLE IPHONE 14 128GB 4G | F22: MOTOROLA MOTO G05 128GB 4G | G22: SAMSUNG GALAXY A53 128GB 4G | H22: HONOR X5C 128GB 4G | I22: XIAOMI NOTE 15 PRO 5G / BUNDLE | J22: OPPO RENO 12 F 256GB 5G
C23: APPLE IPHONE 14 512GB 4G | F23: MOTOROLA MOTO G05 64GB 4G | G23: SAMSUNG GALAXY A54 128GB 5G | H23: HONOR X5C PLUS 256GB 4G | I23: XIAOMI NOTE 15 PRO 5G / BUNDLE | J23: OPPO RENO 13 512GB 5G
C24: APPLE IPHONE 14 PLUS 512GB 4G | F24: MOTOROLA MOTO G06 128GB 4G | G24: SAMSUNG GALAXY A55 128GB 5G | H24: HONOR X5D 128GB 4G | I24: XIAOMI REDMI 10C 128GB 4G | J24: OPPO RENO 13F 256GB 5G
C25: APPLE IPHONE 14 PRO 128GB 4G | F25: MOTOROLA MOTO G06 64GB 4G | G25: SAMSUNG GALAXY A56 256GB 5G | H25: HONOR X6A 128GB 4G | I25: XIAOMI REDMI 10C 128GB 4G | J25: OPPO RENO 14 512GB 5G BDL HEADPHONES
C26: APPLE IPHONE 14 PRO 1TB 4G | F26: MOTOROLA MOTO G13 128GB 4G | G26: SAMSUNG GALAXY A57 256GB 5G | H26: HONOR X6A PLUS 256GB 4G | I26: XIAOMI REDMI 11T | J26: OPPO RENO 5 LITE 128GB 4G
C27: APPLE IPHONE 14 PRO 512GB 4G | F27: MOTOROLA MOTO G15 256GB 4G | G27: SAMSUNG GALAXY A70 128GB 4G | H27: HONOR X6B 256GB 4G | I27: XIAOMI REDMI 11T | J27: OPPO RENO 7 128GB 4G / BUNDLE
C28: APPLE IPHONE 14 PRO MAX 1TB 4G | F28: MOTOROLA MOTO G17 256GB 4G | G28: SAMSUNG GALAXY FLIP4 128GB 4G | H28: HONOR X6C 256GB 4G | I28: XIAOMI REDMI 13 256GB 4G | J28: OPPO RENO13 PRO 512GB 5G
C29: APPLE IPHONE 14 PRO MAX 512GB | F29: MOTOROLA MOTO G20 64GB 4G | G29: SAMSUNG GALAXY FLIP4 256GB 4G | H29: HONOR X7 128GB 4G | I29: XIAOMI REDMI 13 256GB 4G | J29: OPPO RENO14 512GB 5G
C30: APPLE IPHONE 15 128GB 4G | F30: MOTOROLA MOTO G200 128GB 5G | G30: SAMSUNG GALAXY FOLD 4 256GB 4G | H30: HONOR X7C 256GB 4G / BUNDLE | I30: XIAOMI REDMI 13C 128GB 4G | J30: OPPO RENO14 F 256GB 5G
C31: APPLE IPHONE 15 PLUS 128GB 4G | F31: MOTOROLA MOTO G55 256GB 5G | G31: SAMSUNG GALAXY S22 256GB 5G | H31: HONOR X7D 256GB 4G | I31: XIAOMI REDMI 13C 128GB 4G | J31: OPPO RENO16 256GB 5G BDL ENCO BUDS 3 PRO
C32: APPLE IPHONE 15 PRO 128GB 4G | F32: MOTOROLA MOTO G56 256GB 5G | G32: SAMSUNG GALAXY S22 PLUS 128GB 5G | H32: HONOR X8 128GB 4G | I32: XIAOMI REDMI 14C 128GB 4G | J32: OPPO RENO16 F 256GB 5G
C33: APPLE IPHONE 15 PRO 256GB 4G | F33: MOTOROLA MOTO G60 128GB 4G | G33: SAMSUNG GALAXY S22 PLUS 256GB 5G | H33: HONOR X8B 256GB 4G | I33: XIAOMI REDMI 14C 128GB 4G
C34: APPLE IPHONE 15 PRO 512GB 4G | F34: MOTOROLA MOTO G77 256GB 5G | G34: SAMSUNG GALAXY S22 ULTRA 128GB 4G | H34: HONOR X8C 512GB 4G | I34: XIAOMI REDMI 14T 512GB 4G / BUNDLE
C35: APPLE IPHONE 15 PRO MAX 512GB 4G | F35: MOTOROLA MOTO G82 128GB 5G | G35: SAMSUNG GALAXY S22 ULTRA 256GB 4G | H35: HONOR X8D 256GB 4G | I35: XIAOMI REDMI 14T 512GB 4G / BUNDLE
C36: APPLE IPHONE 16 128GB 5G | F36: MOTOROLA MOTO G9 PLUS 128GB 4G | G36: SAMSUNG GALAXY S23 128GB 4G | H36: HONOR X9 8GB 4G | I36: XIAOMI REDMI 15 256GB 4G
C37: APPLE IPHONE 16 256GB 5G | F37: MOTOROLA MOTO ONE HYPER 128GB 4G | G37: SAMSUNG GALAXY S23 256GB 4G | H37: HONOR 200 512GB 5G / BUNDLE | I37: XIAOMI REDMI 15 256GB 4G
C38: APPLE IPHONE 16 PLUS 128GB 5G | F38: MOTOROLA RAZR 60 ULTRA 1T 5G | G38: SAMSUNG GALAXY S23 PLUS 256GB 4G | H38: HONOR X5 32GB 4G | I38: XIAOMI REDMI 15C 128GB 4G
C39: APPLE IPHONE 16 PLUS 256GB 5G | G39: SAMSUNG GALAXY S23 ULTRA 1TB 4G | H39: HONOR X6E 128GB 4G | I39: XIAOMI REDMI 15C 128GB 4G
C40: APPLE IPHONE 16 PRO 128GB 5G | G40: SAMSUNG GALAXY S24 128GB | H40: HONOR X6E 256GB 4G | I40: XIAOMI REDMI 17 128GB 4G
C41: APPLE IPHONE 16 PRO 256GB 5G | G41: SAMSUNG GALAXY S24 256GB 5G | I41: XIAOMI REDMI 9 64GB 4G
C42: APPLE IPHONE 16 PRO MAX 256GB 5G | G42: SAMSUNG GALAXY S24 FE 256GB 5G | I42: XIAOMI REDMI 9 64GB 4G
C43: APPLE IPHONE 16 PRO MAX 512GB 5G | G43: SAMSUNG GALAXY S24 ULTRA 256GB 5G | I43: XIAOMI REDMI 9C 32GB 4G
C44: APPLE IPHONE 16E 128GB 5G | G44: SAMSUNG GALAXY S25 256GB 5G | I44: XIAOMI REDMI 9C 32GB 4G
C45: APPLE IPHONE 16E 256GB 5G | G45: SAMSUNG GALAXY S25 EDGE 256GB 5G | I45: XIAOMI REDMI A5 64GB 4G
C46: APPLE IPHONE 17 256GB 5G | G46: SAMSUNG GALAXY S25 FE 128GB 5G | I46: XIAOMI REDMI A5 64GB 4G
C47: APPLE IPHONE 17 512GB 5G | G47: SAMSUNG GALAXY S25 PLUS 512GB 5G | I47: XIAOMI REDMI A7 PRO 128GB 4G
C48: APPLE IPHONE 17 PRO 1TB 5G | G48: SAMSUNG GALAXY S25 ULTRA 256GB 5G | I48: XIAOMI REDMI A7 PRO 128GB 4G
C49: APPLE IPHONE 17 PRO 256GB 5G | G49: SAMSUNG GALAXY S25 ULTRA 512GB 5G | I49: XIAOMI REDMI NOTE 10 PRO 128GB 4G
C50: APPLE IPHONE 17 PRO 512GB 5G | G50: SAMSUNG GALAXY S26 256GB 5G | I50: XIAOMI REDMI NOTE 10 PRO 128GB 4G
C51: APPLE IPHONE 17 PRO MAX 1TB 5G | G51: SAMSUNG GALAXY S26 FE 256GB 5G | I51: XIAOMI REDMI NOTE 10S 128GB 4G
C52: APPLE IPHONE 17 PRO MAX 256GB 5G | G52: SAMSUNG GALAXY S26 PLUS 512GB 5G | I52: XIAOMI REDMI NOTE 10S 128GB 4G
... C63: APPLE IPHONE 18 PRO 512GB 5G | G63: SAMSUNG GALAXY A37 128GB | I63: XIAOMI REDMI NOTE 17 BUNDLE SOUND POCK
C64: APPLE IPHONE 18 PRO MAX 256GB 5G
C65: APPLE IPHONE 18 PRO MAX 512GB 5G
C66: APPLE IPHONE DUO 256GB 5G
C67: APPLE IPHONE DUO 512GB 5G

Sheet Promociones AT&T Armalo Neg
B4: Promociones
H7: Ármalo Negocios 299 | M7: Ármalo Negocios 399 | R7: Ármalo Negocios 499 | W7: Ármalo Negocios 599 | AB7: Ármalo Negocios 799 | AG7: Ármalo Negocios 1299 | AL7: Ármalo Negocios 1499 | AQ7: VIGENCIA
H8: 299 | M8: 399 | R8: 499 | W8: 599 | AB8: 799 | AG8: 1299 | AL8: 1499
B9: No. | C9: Estatus | D9: Marca | E9: Modelo | F9: Familia Homologada | G9: Precio de Contado | H9: 12 Meses | I9: 18 Meses | J9: 24 Meses | K9: 36 Meses | L9: 48 Meses | M9: 12 Meses | N9: 18 Meses | O9: 24 Meses | P9: 36 Meses | Q9: 48 Meses | R9: 12 Meses | S9: 18 Meses | T9: 24 Meses | U9: 36 Meses | V9: 48 Meses | W9: 12 Meses | X9: 18 Meses | Y9: 24 Meses | Z9: 36 Meses | AA9: 48 Meses | AB9: 12 Meses | AC9: 18 Meses | AD9: 24 Meses | AE9: 36 Meses | AF9: 48 Meses | AG9: 12 Meses | AH9: 18 Meses | AI9: 24 Meses | AJ9: 36 Meses | AK9: 48 Meses | AL9: 12 Meses | AM9: 18 Meses | AN9: 24 Meses | AO9: 36 Meses | AP9: 48 Meses | AQ9: Fecha Inicio | AR9: Fecha Fin | AS9: VIGENCIA
B10: =ROW()-9 -> 1 | C10: NO RESURTIBLE | D10: APPLE | E10: Apple iPhone 11 64GB | F10: APPLE IPHONE 11 64GB 4G | G10: 10999 | H10: 3849 | I10: 3499 | J10: 3149 | K10: 2499 | L10: 1799 | M10: 3649 | N10: 3149 | O10: 2699 | P10: 1799 | Q10: 899 | R10: 3399 | S10: 2849 | T10: 2249 | U10: 1099 | V10: 0 | W10: 3149 | X10: 2499 | Y10: 1799 | Z10: 449 | AA10: 0 | AB10: 2699 | AC10: 1799 | AD10: 899 | AE10: 0 | AF10: 0 | AG10: 1549 | AH10: 99 | AI10: 0 | AJ10: 0 | AK10: 0 | AL10: 1099 | AM10: 0 | AN10: 0 | AO10: 0 | AP10: 0 | AQ10: 46059 | AR10: INDEFINIDO | AS10: =UPPER(TEXT(AQ10, " dd \ mmmm \ aa")&" - "&TEXT(AR10, " dd \ mmmm \ aa")) -> 06 FEBRERO 26 - INDEFINIDO
B11: =ROW()-9 -> 2 | C11: NO RESURTIBLE | D11: APPLE | E11: Apple iPhone 15 128GB | F11: APPLE IPHONE 15 128GB 4G | G11: 17499 | H11: 11799 | I11: 11449 | J11: 11099 | K11: 10399 | L11: 9749 | M11: 11549 | N11: 11099 | O11: 10649 | P11: 9749 | Q11: 8849 | R11: 11349 | S11: 10749 | T11: 10199 | U11: 9049 | V11: 7899 | W11: 11099 | X11: 10399 | Y11: 9749 | Z11: 8349 | AA11: 6999 | AB11: 10649 | AC11: 9749 | AD11: 8849 | AE11: 6999 | AF11: 5199 | AG11: 9499 | AH11: 8049 | AI11: 6549 | AJ11: 3599 | AK11: 599 | AL11: 9049 | AM11: 7349 | AN11: 5649 | AO11: 2199 | AP11: 0 | AQ11: 46054 | AR11: 46291 | AS11: =UPPER(TEXT(AQ11, " dd \ mmmm \ aa")&" - "&TEXT(AR11, " dd \ mmmm \ aa")) -> 01 FEBRERO 26 - 26 SEPTIEMBRE 26
B12: =ROW()-9 -> 3 | C12: NO RESURTIBLE | D12: APPLE | E12: Apple iPhone 16 128GB | F12: APPLE IPHONE 16 128GB 5G | G12: 19999 | H12: 13409 | I12: 13059 | J12: 12709 | K12: 12019 | L12: 11319 | M12: 13179 | N12: 12709 | O12: 12249 | P12: 11319 | Q12: 10389 | R12: 12939 | S12: 12359 | T12: 11779 | U12: 10619 | V12: 9449 | W12: 12709 | X12: 12009 | Y12: 11309 | Z12: 9919 | AA12: 8519 | AB12: 12239 | AC12: 11309 | AD12: 10379 | AE12: 8519 | AF12: 6659 | AG12: 11079 | AH12: 9559 | AI12: 8049 | AJ12: 5019 | AK12: 1999 | AL12: 10609 | AM12: 8869 | AN12: 7119 | AO12: 3629 | AP12: 129 | AQ12: 46201 | AR12: 46291 | AS12: =UPPER(TEXT(AQ12, " dd \ mmmm \ aa")&" - "&TEXT(AR12, " dd \ mmmm \ aa")) -> 28 JUNIO 26 - 26 SEPTIEMBRE 26
B13: =ROW()-9 -> 4 | C13: NO RESURTIBLE | D13: APPLE | E13: Apple iPhone 16 Plus 128GB | F13: APPLE IPHONE 16 PLUS 128GB 5G | G13: 22999 | H13: 16929 | I13: 16699 | J13: 16479 | K13: 16019 | L13: 15569 | M13: 16779 | N13: 16479 | O13: 16169 | P13: 15569 | Q13: 14969 | R13: 16629 | S13: 16249 | T13: 15869 | U13: 15119 | V13: 14359 | W13: 16479 | X13: 16019 | Y13: 15569 | Z13: 14659 | AA13: 13749 | AB13: 16169 | AC13: 15569 | AD13: 14959 | AE13: 13749 | AF13: 12539 | AG13: 15419 | AH13: 14429 | AI13: 13449 | AJ13: 11479 | AK13: 9509 | AL13: 15109 | AM13: 13979 | AN13: 12839 | AO13: 10569 | AP13: 8299 | AQ13: 46201 | AR13: 46291 | AS13: =UPPER(TEXT(AQ13, " dd \ mmmm \ aa")&" - "&TEXT(AR13, " dd \ mmmm \ aa")) -> 28 JUNIO 26 - 26 SEPTIEMBRE 26
B14: =ROW()-9 -> 5 | C14: NO RESURTIBLE | D14: APPLE | E14: Apple iPhone 16 Plus 512GB | F14: APPLE IPHONE 16 PLUS 512GB 5G | G14: 25499 | H14: 15729 | I14: 15499 | J14: 15279 | K14: 14819 | L14: 14369 | M14: 15579 | N14: 15279 | O14: 14969 | P14: 14369 | Q14: 13769 | R14: 15429 | S14: 15049 | T14: 14669 | U14: 13919 | V14: 13159 | W14: 15279 | X14: 14819 | Y14: 14369 | Z14: 13459 | AA14: 12549 | AB14: 14969 | AC14: 14369 | AD14: 13759 | AE14: 12549 | AF14: 11339 | AG14: 14219 | AH14: 13229 | AI14: 12249 | AJ14: 10279 | AK14: 8309 | AL14: 13909 | AM14: 12779 | AN14: 11639 | AO14: 9369 | AP14: 7099 | AQ14: 46201 | AR14: 46291 | AS14: =UPPER(TEXT(AQ14, " dd \ mmmm \ aa")&" - "&TEXT(AR14, " dd \ mmmm \ aa")) -> 28 JUNIO 26 - 26 SEPTIEMBRE 26
B15: =ROW()-9 -> 6 | C15: NO RESURTIBLE | D15: APPLE | E15: Apple iPhone 16e 128GB | F15: APPLE IPHONE 16E 128GB 5G | G15: 14999 | H15: 9389 | I15: 9039 | J15: 8699 | K15: 7999 | L15: 7299 | M15: 9159 | N15: 8689 | O15: 8229 | P15: 7299 | Q15: 6369 | R15: 8929 | S15: 8349 | T15: 7759 | U15: 6599 | V15: 5439 | W15: 8689 | X15: 7999 | Y15: 7299 | Z15: 5899 | AA15: 4509 | AB15: 8229 | AC15: 7299 | AD15: 6369 | AE15: 4499 | AF15: 2639 | AG15: 7059 | AH15: 5549 | AI15: 4039 | AJ15: 1009 | AK15: 0 | AL15: 6599 | AM15: 4849 | AN15: 3099 | AO15: 0 | AP15: 0 | AQ15: 46199 | AR15: INDEFINIDO | AS15: =UPPER(TEXT(AQ15, " dd \ mmmm \ aa")&" - "&TEXT(AR15, " dd \ mmmm \ aa")) -> 26 JUNIO 26 - INDEFINIDO
B16: =ROW()-9 -> 7 | C16: NO RESURTIBLE | D16: APPLE | E16: Apple iPhone 17 256GB | F16: APPLE IPHONE 17 256GB 5G | G16: 19999 | H16: 19999 | I16: 19999 | J16: 19999 | K16: 19999 | L16: 19999 | M16: 19999 | N16: 19999 | O16: 19999 | P16: 19999 | Q16: 19999 | R16: 19999 | S16: 19999 | T16: 19999 | U16: 19999 | V16: 19999 | W16: 17499 | X16: 17099 | Y16: 16699 | Z16: 15799 | AA16: 14899 | AB16: 16499 | AC16: 15899 | AD16: 15299 | AE16: 14199 | AF16: 12999 | AG16: 16099 | AH16: 15099 | AI16: 14199 | AJ16: 12299 | AK16: 10399 | AL16: 15399 | AM16: 14299 | AN16: 13199 | AO16: 10999 | AP16: 8799 | AQ16: 46157 | AR16: 46291 | AS16: =UPPER(TEXT(AQ16, " dd \ mmmm \ aa")&" - "&TEXT(AR16, " dd \ mmmm \ aa")) -> 15 MAYO 26 - 26 SEPTIEMBRE 26
B17: =ROW()-9 -> 8 | C17: NO RESURTIBLE | D17: APPLE | E17: Apple iPhone 17 512GB | F17: APPLE IPHONE 17 512GB 5G | G17: 24999 | H17: 24999 | I17: 24999 | J17: 24999 | K17: 24999 | L17: 24999 | M17: 24999 | N17: 24999 | O17: 24999 | P17: 24999 | Q17: 24999 | R17: 24999 | S17: 24999 | T17: 24999 | U17: 24999 | V17: 24999 | W17: 21599 | X17: 21099 | Y17: 20699 | Z17: 19799 | AA17: 18999 | AB17: 20499 | AC17: 19899 | AD17: 19299 | AE17: 18199 | AF17: 16999 | AG17: 20099 | AH17: 19199 | AI17: 18199 | AJ17: 16299 | AK17: 14399 | AL17: 19399 | AM17: 18299 | AN17: 17199 | AO17: 14999 | AP17: 12799 | AQ17: 46157 | AR17: 46291 | AS17: =UPPER(TEXT(AQ17, " dd \ mmmm \ aa")&" - "&TEXT(AR17, " dd \ mmmm \ aa")) -> 15 MAYO 26 - 26 SEPTIEMBRE 26
B18: =ROW()-9 -> 9 | C18: RESURTIBLE | D18: APPLE | E18: Apple iPhone 17 Pro 256GB | F18: APPLE IPHONE 17 PRO 256GB 5G | G18: 28499 | H18: 28499 | I18: 28499 | J18: 28499 | K18: 28499 | L18: 28499 | M18: 28499 | N18: 28499 | O18: 28499 | P18: 28499 | Q18: 28499 | R18: 28499 | S18: 28499 | T18: 28499 | U18: 28499 | V18: 28499 | W18: 24399 | X18: 23899 | Y18: 23499 | Z18: 22599 | AA18: 21799 | AB18: 23299 | AC18: 22699 | AD18: 22199 | AE18: 20999 | AF18: 19799 | AG18: 22899 | AH18: 21999 | AI18: 20999 | AJ18: 19099 | AK18: 17299 | AL18: 22199 | AM18: 21099 | AN18: 19999 | AO18: 17799 | AP18: 15699 | AQ18: 46157 | AR18: 46291 | AS18: =UPPER(TEXT(AQ18, " dd \ mmmm \ aa")&" - "&TEXT(AR18, " dd \ mmmm \ aa")) -> 15 MAYO 26 - 26 SEPTIEMBRE 26
B19: =ROW()-9 -> 10 | C19: NO RESURTIBLE | D19: APPLE | E19: Apple iPhone 17 Pro 512GB | F19: APPLE IPHONE 17 PRO 512GB 5G | G19: 33499 | H19: 33499 | I19: 33499 | J19: 33499 | K19: 33499 | L19: 33499 | M19: 33499 | N19: 33499 | O19: 33499 | P19: 33499 | Q19: 33499 | R19: 33499 | S19: 33499 | T19: 33499 | U19: 33499 | V19: 33499 | W19: 28399 | X19: 27999 | Y19: 27499 | Z19: 26699 | AA19: 25799 | AB19: 27299 | AC19: 26799 | AD19: 26199 | AE19: 24999 | AF19: 23799 | AG19: 26999 | AH19: 25999 | AI19: 25099 | AJ19: 23199 | AK19: 21299 | AL19: 26199 | AM19: 25099 | AN19: 23999 | AO19: 21899 | AP19: 19699 | AQ19: 46157 | AR19: 46291 | AS19: =UPPER(TEXT(AQ19, " dd \ mmmm \ aa")&" - "&TEXT(AR19, " dd \ mmmm \ aa")) -> 15 MAYO 26 - 26 SEPTIEMBRE 26
B20: =ROW()-9 -> 11 | C20: INV. LIMITADO EN CANAL | D20: APPLE | E20: Apple iPhone 17 Pro Max 1TB | F20: APPLE IPHONE 17 PRO MAX 1TB 5G | G20: 40999 | H20: 40999 | I20: 40999 | J20: 40999 | K20: 40999 | L20: 40999 | M20: 40999 | N20: 40999 | O20: 40999 | P20: 40999 | Q20: 40999 | R20: 40999 | S20: 40999 | T20: 40999 | U20: 40999 | V20: 40999 | W20: 34399 | X20: 33999 | Y20: 33599 | Z20: 32699 | AA20: 31799 | AB20: 33399 | AC20: 32799 | AD20: 32199 | AE20: 30999 | AF20: 29899 | AG20: 32999 | AH20: 31999 | AI20: 31099 | AJ20: 29199 | AK20: 27299 | AL20: 32299 | AM20: 31199 | AN20: 30099 | AO20: 27899 | AP20: 25699 | AQ20: 46157 | AR20: 46291 | AS20: =UPPER(TEXT(AQ20, " dd \ mmmm \ aa")&" - "&TEXT(AR20, " dd \ mmmm \ aa")) -> 15 MAYO 26 - 26 SEPTIEMBRE 26
B21: =ROW()-9 -> 12 | C21: RESURTIBLE | D21: APPLE | E21: Apple iPhone 17 Pro Max 256GB | F21: APPLE IPHONE 17 PRO MAX 256GB 5G | G21: 30999 | H21: 30999 | I21: 30999 | J21: 30999 | K21: 30999 | L21: 30999 | M21: 30999 | N21: 30999 | O21: 30999 | P21: 30999 | Q21: 30999 | R21: 30999 | S21: 30999 | T21: 30999 | U21: 30999 | V21: 30999 | W21: 26399 | X21: 25999 | Y21: 25499 | Z21: 24599 | AA21: 23799 | AB21: 25299 | AC21: 24699 | AD21: 24199 | AE21: 22999 | AF21: 21799 | AG21: 24899 | AH21: 23999 | AI21: 22999 | AJ21: 21199 | AK21: 19299 | AL21: 24199 | AM21: 23099 | AN21: 21999 | AO21: 19799 | AP21: 17699 | AQ21: 46157 | AR21: 46291 | AS21: =UPPER(TEXT(AQ21, " dd \ mmmm \ aa")&" - "&TEXT(AR21, " dd \ mmmm \ aa")) -> 15 MAYO 26 - 26 SEPTIEMBRE 26
B22: =ROW()-9 -> 13 | C22: NO RESURTIBLE | D22: APPLE | E22: Apple iPhone 17 Pro Max 512GB | F22: APPLE IPHONE 17 PRO MAX 512GB 5G | G22: 35999 | H22: 35999 | I22: 35999 | J22: 35999 | K22: 35999 | L22: 35999 | M22: 35999 | N22: 35999 | O22: 35999 | P22: 35999 | Q22: 35999 | R22: 35999 | S22: 35999 | T22: 35999 | U22: 35999 | V22: 35999 | W22: 30399 | X22: 29999 | Y22: 29499 | Z22: 28699 | AA22: 27799 | AB22: 29399 | AC22: 28799 | AD22: 28199 | AE22: 26999 | AF22: 25899 | AG22: 28999 | AH22: 27999 | AI22: 27099 | AJ22: 25199 | AK22: 23299 | AL22: 28199 | AM22: 27099 | AN22: 26099 | AO22: 23899 | AP22: 21699 | AQ22: 46157 | AR22: 46291 | AS22: =UPPER(TEXT(AQ22, " dd \ mmmm \ aa")&" - "&TEXT(AR22, " dd \ mmmm \ aa")) -> 15 MAYO 26 - 26 SEPTIEMBRE 26
B23: =ROW()-9 -> 14 | C23: NO RESURTIBLE | D23: GOOGLE | E23: Google Pixel 10 128GB | F23: GOOGLE PIXEL 10 128GB 5G | G23: 19999 | H23: 12179 | I23: 11949 | J23: 11719 | K23: 11269 | L23: 10819 | M23: 12019 | N23: 11719 | O23: 11419 | P23: 10819 | Q23: 10209 | R23: 11869 | S23: 11489 | T23: 11119 | U23: 10359 | V23: 9599 | W23: 11719 | X23: 11269 | Y23: 10809 | Z23: 9909 | AA23: 8999 | AB23: 11419 | AC23: 10809 | AD23: 10209 | AE23: 8999 | AF23: 7789 | AG23: 10659 | AH23: 9679 | AI23: 8689 | AJ23: 6729 | AK23: 4759 | AL23: 10359 | AM23: 9219 | AN23: 8089 | AO23: 5819 | AP23: 3549 | AQ23: 46204 | AR23: 46329 | AS23: =UPPER(TEXT(AQ23, " dd \ mmmm \ aa")&" - "&TEXT(AR23, " dd \ mmmm \ aa")) -> 01 JULIO 26 - 03 NOVIEMBRE 26
B24: =ROW()-9 -> 15 | C24: NO RESURTIBLE | D24: GOOGLE | E24: Google Pixel 10 256GB | F24: GOOGLE PIXEL 10 256GB 5G | G24: 22499 | H24: 13289 | I24: 13069 | J24: 12839 | K24: 12389 | L24: 11939 | M24: 13139 | N24: 12839 | O24: 12539 | P24: 11929 | Q24: 11329 | R24: 12989 | S24: 12609 | T24: 12239 | U24: 11479 | V24: 10719 | W24: 12839 | X24: 12389 | Y24: 11929 | Z24: 11029 | AA24: 10119 | AB24: 12539 | AC24: 11929 | AD24: 11329 | AE24: 10119 | AF24: 8909 | AG24: 11779 | AH24: 10799 | AI24: 9809 | AJ24: 7849 | AK24: 5879 | AL24: 11479 | AM24: 10339 | AN24: 9209 | AO24: 6939 | AP24: 4669 | AQ24: 46204 | AR24: 46329 | AS24: =UPPER(TEXT(AQ24, " dd \ mmmm \ aa")&" - "&TEXT(AR24, " dd \ mmmm \ aa")) -> 01 JULIO 26 - 03 NOVIEMBRE 26
B25: =ROW()-9 -> 16 | C25: NO RESURTIBLE | D25: GOOGLE | E25: Google Pixel 10 Pro 256GB | F25: GOOGLE PIXEL 10 PRO 256GB 5G | G25: 28499 | H25: 16039 | I25: 15809 | J25: 15589 | K25: 15139 | L25: 14679 | M25: 15889 | N25: 15589 | O25: 15289 | P25: 14679 | Q25: 14079 | R25: 15739 | S25: 15359 | T25: 14979 | U25: 14229 | V25: 13469 | W25: 15589 | X25: 15129 | Y25: 14679 | Z25: 13769 | AA25: 12869 | AB25: 15279 | AC25: 14679 | AD25: 14069 | AE25: 12859 | AF25: 11649 | AG25: 14529 | AH25: 13539 | AI25: 12559 | AJ25: 10589 | AK25: 8619 | AL25: 14219 | AM25: 13089 | AN25: 11949 | AO25: 9679 | AP25: 7409 | AQ25: 46204 | AR25: 46329 | AS25: =UPPER(TEXT(AQ25, " dd \ mmmm \ aa")&" - "&TEXT(AR25, " dd \ mmmm \ aa")) -> 01 JULIO 26 - 03 NOVIEMBRE 26
B26: =ROW()-9 -> 17 | C26: NO RESURTIBLE | D26: GOOGLE | E26: Google Pixel 10 Pro 512GB | F26: GOOGLE PIXEL 10 PRO 512GB 5G | G26: 31499 | H26: 18519 | I26: 18289 | J26: 18059 | K26: 17609 | L26: 17159 | M26: 18369 | N26: 18059 | O26: 17759 | P26: 17159 | Q26: 16549 | R26: 18209 | S26: 17839 | T26: 17459 | U26: 16699 | V26: 15949 | W26: 18059 | X26: 17609 | Y26: 17159 | Z26: 16249 | AA26: 15339 | AB26: 17759 | AC26: 17149 | AD26: 16549 | AE26: 15339 | AF26: 14129 | AG26: 16999 | AH26: 16019 | AI26: 15029 | AJ26: 13069 | AK26: 11099 | AL26: 16699 | AM26: 15559 | AN26: 14429 | AO26: 12159 | AP26: 9889 | AQ26: 46204 | AR26: 46329 | AS26: =UPPER(TEXT(AQ26, " dd \ mmmm \ aa")&" - "&TEXT(AR26, " dd \ mmmm \ aa")) -> 01 JULIO 26 - 03 NOVIEMBRE 26
B27: =ROW()-9 -> 18 | C27: NO RESURTIBLE | D27: GOOGLE | E27: Google Pixel 10 Pro XL 256GB | F27: GOOGLE PIXEL 10 PRO XL 256GB 5G | G27: 30999 | H27: 19119 | I27: 18889 | J27: 18669 | K27: 18209 | L27: 17759 | M27: 18969 | N27: 18659 | O27: 18359 | P27: 17759 | Q27: 17149 | R27: 18819 | S27: 18439 | T27: 18059 | U27: 17299 | V27: 16549 | W27: 18659 | X27: 18209 | Y27: 17759 | Z27: 16849 | AA27: 15939 | AB27: 18359 | AC27: 17759 | AD27: 17149 | AE27: 15939 | AF27: 14729 | AG27: 17599 | AH27: 16619 | AI27: 15639 | AJ27: 13669 | AK27: 11699 | AL27: 17299 | AM27: 16169 | AN27: 15029 | AO27: 12759 | AP27: 10489 | AQ27: 46204 | AR27: 46329 | AS27: =UPPER(TEXT(AQ27, " dd \ mmmm \ aa")&" - "&TEXT(AR27, " dd \ mmmm \ aa")) -> 01 JULIO 26 - 03 NOVIEMBRE 26
... B31: =ROW()-9 -> 22 | C31: RESURTIBLE | D31: HONOR | E31: Honor 600 512GB | F31: HONOR 600 512GB 5G | G31: 16999 | H31: 10279 | I31: 10059 | J31: 9829 | K31: 9379 | L31: 8919 | M31: 10129 | N31: 9829 | O31: 9529 | P31: 8919 | Q31: 8319 | R31: 9979 | S31: 9599 | T31: 9219 | U31: 8469 | V31: 7709 | W31: 9829 | X31: 9379 | Y31: 8919 | Z31: 8009 | AA31: 7109 | AB31: 9529 | AC31: 8919 | AD31: 8319 | AE31: 7109 | AF31: 5899 | AG31: 8769 | AH31: 7789 | AI31: 6799 | AJ31: 4829 | AK31: 2869 | AL31: 8469 | AM31: 7329 | AN31: 6199 | AO31: 3929 | AP31: 1649 | AQ31: 46204 | AR31: 46295 | AS31: =UPPER(TEXT(AQ31, " dd \ mmmm \ aa")&" - "&TEXT(AR31, " dd \ mmmm \ aa")) -> 01 JULIO 26 - 30 SEPTIEMBRE 26
B32: =ROW()-9 -> 23 | C32: NO RESURTIBLE | D32: HONOR | E32: Honor 90 256GB & Bundle Band 7 | F32: HONOR 90 256GB 5G | G32: 10999 | H32: 5649 | I32: 5399 | J32: 5199 | K32: 4749 | L32: 4349 | M32: 5499 | N32: 5199 | O32: 4899 | P32: 4349 | Q32: 3749 | R32: 5349 | S32: 4999 | T32: 4599 | U32: 3899 | V32: 3149 | W32: 5199 | X32: 4749 | Y32: 4299 | Z32: 3449 | AA32: 2599 | AB32: 4899 | AC32: 4299 | AD32: 3749 | AE32: 2599 | AF32: 1399 | AG32: 4199 | AH32: 3249 | AI32: 2299 | AJ32: 399 | AK32: 0 | AL32: 3899 | AM32: 2799 | AN32: 1699 | AO32: 0 | AP32: 0 | AQ32: 45936 | AR32: INDEFINIDO | AS32: =UPPER(TEXT(AQ32, " dd \ mmmm \ aa")&" - "&TEXT(AR32, " dd \ mmmm \ aa")) -> 06 OCTUBRE 25 - INDEFINIDO
B33: =ROW()-9 -> 24 | C33: NO RESURTIBLE | D33: HONOR | E33: Honor 90 512GB | F33: HONOR 90 512GB 4G | G33: 15999 | H33: 8649 | I33: 8399 | J33: 8199 | K33: 7749 | L33: 7349 | M33: 8499 | N33: 8199 | O33: 7899 | P33: 7349 | Q33: 6749 | R33: 8349 | S33: 7999 | T33: 7599 | U33: 6899 | V33: 6149 | W33: 8199 | X33: 7749 | Y33: 7349 | Z33: 6449 | AA33: 5599 | AB33: 7899 | AC33: 7349 | AD33: 6749 | AE33: 5599 | AF33: 4399 | AG33: 7199 | AH33: 6249 | AI33: 5299 | AJ33: 3399 | AK33: 1499 | AL33: 6899 | AM33: 5799 | AN33: 4699 | AO33: 2549 | AP33: 349 | AQ33: 45936 | AR33: INDEFINIDO | AS33: =UPPER(TEXT(AQ33, " dd \ mmmm \ aa")&" - "&TEXT(AR33, " dd \ mmmm \ aa")) -> 06 OCTUBRE 25 - INDEFINIDO
B34: =ROW()-9 -> 25 | C34: NO RESURTIBLE | D34: HONOR | E34: Honor Magic 5 Lite 256GB & Bundle Band 7 | F34: HONOR MAGIC 5 LITE 256GB 4G | G34: 8999 | H34: 3499 | I34: 3299 | J34: 3049 | K34: 2649 | L34: 2199 | M34: 3349 | N34: 3049 | O34: 2759 | P34: 2199 | Q34: 1599 | R34: 3199 | S34: 2849 | T34: 2499 | U34: 1749 | V34: 1049 | W34: 3049 | X34: 2649 | Y34: 2199 | Z34: 1299 | AA34: 449 | AB34: 2749 | AC34: 2199 | AD34: 1599 | AE34: 449 | AF34: 0 | AG34: 2049 | AH34: 1099 | AI34: 149 | AJ34: 0 | AK34: 0 | AL34: 1749 | AM34: 649 | AN34: 0 | AO34: 0 | AP34: 0 | AQ34: 45936 | AR34: INDEFINIDO | AS34: =UPPER(TEXT(AQ34, " dd \ mmmm \ aa")&" - "&TEXT(AR34, " dd \ mmmm \ aa")) -> 06 OCTUBRE 25 - INDEFINIDO
B35: =ROW()-9 -> 26 | C35: NO RESURTIBLE | D35: HONOR | E35: Honor Magic 6 Lite & Bundle Band 7 | F35: HONOR MAGIC 6 LITE 256GB 5G | G35: 8999 | H35: 3339 | I35: 3109 | J35: 2889 | K35: 2429 | L35: 1979 | M35: 3189 | N35: 2889 | O35: 2579 | P35: 1979 | Q35: 1369 | R35: 3039 | S35: 2659 | T35: 2279 | U35: 1519 | V35: 769 | W35: 2879 | X35: 2429 | Y35: 1979 | Z35: 1069 | AA35: 159 | AB35: 2579 | AC35: 1979 | AD35: 1369 | AE35: 159 | AF35: 0 | AG35: 1819 | AH35: 839 | AI35: 0 | AJ35: 0 | AK35: 0 | AL35: 1519 | AM35: 389 | AN35: 0 | AO35: 0 | AP35: 0 | AQ35: 46199 | AR35: INDEFINIDO | AS35: =UPPER(TEXT(AQ35, " dd \ mmmm \ aa")&" - "&TEXT(AR35, " dd \ mmmm \ aa")) -> 26 JUNIO 26 - INDEFINIDO
B36: =ROW()-9 -> 27 | C36: NO RESURTIBLE | D36: HONOR | E36: Honor Magic 7 Lite & Bundle Headphones | F36: HONOR MAGIC7 LITE BDL 512GB 5G | G36: 9999 | H36: 6549 | I36: 6199 | J36: 5849 | K36: 5199 | L36: 4499 | M36: 6299 | N36: 5849 | O36: 5399 | P36: 4499 | Q36: 3599 | R36: 6099 | S36: 5499 | T36: 4949 | U36: 3799 | V36: 6549 | W36: 6549 | X36: 6549 | Y36: 4499 | Z36: 3149 | AA36: 1749 | AB36: 5399 | AC36: 4499 | AD36: 3599 | AE36: 1749 | AF36: 0 | AG36: 4249 | AH36: 2799 | AI36: 1299 | AJ36: 0 | AK36: 0 | AL36: 3799 | AM36: 2099 | AN36: 399 | AO36: 0 | AP36: 0 | AQ36: 46204 | AR36: INDEFINIDO | AS36: =UPPER(TEXT(AQ36, " dd \ mmmm \ aa")&" - "&TEXT(AR36, " dd \ mmmm \ aa")) -> 01 JULIO 26 - INDEFINIDO
B37: =ROW()-9 -> 28 | C37: RESURTIBLE | D37: HONOR | E37: Honor Magic 8 Lite 512GB 5G Bundle Headphones | F37: HONOR MAGIC8 LITE 512GB 5G | G37: 9999 | H37: 5899 | I37: 5549 | J37: 5199 | K37: 4499 | L37: 3809 | M37: 5659 | N37: 5199 | O37: 4729 | P37: 3799 | Q37: 2869 | R37: 5429 | S37: 4849 | T37: 4269 | U37: 3099 | V37: 1939 | W37: 5199 | X37: 4499 | Y37: 3799 | Z37: 2409 | AA37: 1009 | AB37: 4729 | AC37: 3799 | AD37: 2869 | AE37: 1009 | AF37: 0 | AG37: 3569 | AH37: 2049 | AI37: 539 | AJ37: 0 | AK37: 0 | AL37: 3099 | AM37: 1349 | AN37: 0 | AO37: 0 | AP37: 0 | AQ37: 46204 | AR37: 46295 | AS37: =UPPER(TEXT(AQ37, " dd \ mmmm \ aa")&" - "&TEXT(AR37, " dd \ mmmm \ aa")) -> 01 JULIO 26 - 30 SEPTIEMBRE 26
B38: =ROW()-9 -> 29 | C38: NO RESURTIBLE | D38: HONOR | E38: Honor Magic V3 5G | F38: HONOR MAGICV3 512GB 5G | G38: 45999 | H38: 26409 | I38: 26189 | J38: 25959 | K38: 25509 | L38: 25049 | M38: 26259 | N38: 25959 | O38: 25659 | P38: 25049 | Q38: 24449 | R38: 26109 | S38: 25729 | T38: 25349 | U38: 24599 | V38: 23839 | W38: 25959 | X38: 25509 | Y38: 25049 | Z38: 24139 | AA38: 23239 | AB38: 25659 | AC38: 25049 | AD38: 24449 | AE38: 23239 | AF38: 22029 | AG38: 24899 | AH38: 23919 | AI38: 22929 | AJ38: 20959 | AK38: 18999 | AL38: 24599 | AM38: 23459 | AN38: 22329 | AO38: 20059 | AP38: 17779 | AQ38: 46235 | AR38: 46295 | AS38: =UPPER(TEXT(AQ38, " dd \ mmmm \ aa")&" - "&TEXT(AR38, " dd \ mmmm \ aa")) -> 01 AGOSTO 26 - 30 SEPTIEMBRE 26
B39: =ROW()-9 -> 30 | C39: NO RESURTIBLE | D39: HONOR | E39: Honor X5C Plus | F39: HONOR X5C PLUS 256GB 4G | G39: 2999 | H39: 1629 | I39: 1399 | J39: 1169 | K39: 719 | L39: 269 | M39: 1469 | N39: 1169 | O39: 869 | P39: 269 | Q39: 0 | R39: 1319 | S39: 939 | T39: 569 | U39: 0 | V39: 0 | W39: 1169 | X39: 719 | Y39: 259 | Z39: 0 | AA39: 0 | AB39: 869 | AC39: 259 | AD39: 0 | AE39: 0 | AF39: 0 | AG39: 109 | AH39: 0 | AI39: 0 | AJ39: 0 | AK39: 0 | AL39: 0 | AM39: 0 | AN39: 0 | AO39: 0 | AP39: 0 | AQ39: 46235 | AR39: 46295 | AS39: =UPPER(TEXT(AQ39, " dd \ mmmm \ aa")&" - "&TEXT(AR39, " dd \ mmmm \ aa")) -> 01 AGOSTO 26 - 30 SEPTIEMBRE 26
B40: =ROW()-9 -> 31 | C40: NPI | D40: HONOR | E40: Honor X5d 128GB 4G | F40: HONOR X5D 128GB 4G | G40: 3999 | H40: 1959 | I40: 1609 | J40: 1259 | K40: 559 | L40: 0 | M40: 1719 | N40: 1259 | O40: 789 | P40: 0 | Q40: 0 | R40: 1489 | S40: 909 | T40: 329 | U40: 0 | V40: 0 | W40: 1259 | X40: 559 | Y40: 0 | Z40: 0 | AA40: 0 | AB40: 789 | AC40: 0 | AD40: 0 | AE40: 0 | AF40: 0 | AG40: 0 | AH40: 0 | AI40: 0 | AJ40: 0 | AK40: 0 | AL40: 0 | AM40: 0 | AN40: 0 | AO40: 0 | AP40: 0 | AQ40: 46254 | AR40: 46295 | AS40: =UPPER(TEXT(AQ40, " dd \ mmmm \ aa")&" - "&TEXT(AR40, " dd \ mmmm \ aa")) -> 20 AGOSTO 26 - 30 SEPTIEMBRE 26
B41: =ROW()-9 -> 32 | C41: NO RESURTIBLE | D41: HONOR | E41: Honor X6A | F41: HONOR X6A 128GB 4G | G41: 2999 | H41: 1149 | I41: 799 | J41: 449 | K41: 0 | L41: 0 | M41: 899 | N41: 449 | O41: 0 | P41: 0 | Q41: 0 | R41: 699 | S41: 99 | T41: 0 | U41: 0 | V41: 0 | W41: 449 | X41: 0 | Y41: 0 | Z41: 0 | AA41: 0 | AB41: 0 | AC41: 0 | AD41: 0 | AE41: 0 | AF41: 0 | AG41: 0 | AH41: 0 | AI41: 0 | AJ41: 0 | AK41: 0 | AL41: 0 | AM41: 0 | AN41: 0 | AO41: 0 | AP41: 0 | AQ41: 45936 | AR41: INDEFINIDO | AS41: =UPPER(TEXT(AQ41, " dd \ mmmm \ aa")&" - "&TEXT(AR41, " dd \ mmmm \ aa")) -> 06 OCTUBRE 25 - INDEFINIDO
B42: =ROW()-9 -> 33 | C42: NO RESURTIBLE | D42: HONOR | E42: Honor X6C | F42: HONOR X6C 256GB 4G | G42: 3999 | H42: 2129 | I42: 1779 | J42: 1429 | K42: 739 | L42: 39 | M42: 1899 | N42: 1429 | O42: 969 | P42: 39 | Q42: 0 | R42: 1659 | S42: 1079 | T42: 499 | U42: 0 | V42: 0 | W42: 1429 | X42: 729 | Y42: 29 | Z42: 0 | AA42: 0 | AB42: 959 | AC42: 29 | AD42: 0 | AE42: 0 | AF42: 0 | AG42: 0 | AH42: 0 | AI42: 0 | AJ42: 0 | AK42: 0 | AL42: 0 | AM42: 0 | AN42: 0 | AO42: 0 | AP42: 0 | AQ42: 46204 | AR42: 46295 | AS42: =UPPER(TEXT(AQ42, " dd \ mmmm \ aa")&" - "&TEXT(AR42, " dd \ mmmm \ aa")) -> 01 JULIO 26 - 30 SEPTIEMBRE 26
B43: =ROW()-9 -> 34 | C43: NPI | D43: HONOR | E43: Honor X6E 128GB 4G | F43: HONOR X6E 128GB 4G | G43: 5499 | H43: 2749 | I43: 2399 | J43: 2049 | K43: 1349 | L43: 659 | M43: 2509 | N43: 2049 | O43: 1579 | P43: 649 | Q43: 0 | R43: 2279 | S43: 1699 | T43: 1119 | U43: 0 | V43: 0 | W43: 2049 | X43: 1349 | Y43: 649 | Z43: 0 | AA43: 0 | AB43: 1579 | AC43: 649 | AD43: 0 | AE43: 0 | AF43: 0 | AG43: 419 | AH43: 0 | AI43: 0 | AJ43: 0 | AK43: 0 | AL43: 0 | AM43: 0 | AN43: 0 | AO43: 0 | AP43: 0 | AQ43: 46276 | AR43: 46326 | AS43: =UPPER(TEXT(AQ43, " dd \ mmmm \ aa")&" - "&TEXT(AR43, " dd \ mmmm \ aa")) -> 11 SEPTIEMBRE 26 - 31 OCTUBRE 26
B44: =ROW()-9 -> 35 | C44: NPI | D44: HONOR | E44: Honor X6E 256GB 4G | F44: HONOR X6E 256GB 4G | G44: 6499 | H44: 3469 | I44: 3119 | J44: 2769 | K44: 2069 | L44: 1379 | M44: 3229 | N44: 2769 | O44: 2299 | P44: 1369 | Q44: 439 | R44: 2999 | S44: 2419 | T44: 1839 | U44: 669 | V44: 0 | W44: 2769 | X44: 2069 | Y44: 1369 | Z44: 0 | AA44: 0 | AB44: 2299 | AC44: 1369 | AD44: 439 | AE44: 0 | AF44: 0 | AG44: 1139 | AH44: 0 | AI44: 0 | AJ44: 0 | AK44: 0 | AL44: 669 | AM44: 0 | AN44: 0 | AO44: 0 | AP44: 0 | AQ44: 46276 | AR44: 46326 | AS44: =UPPER(TEXT(AQ44, " dd \ mmmm \ aa")&" - "&TEXT(AR44, " dd \ mmmm \ aa")) -> 11 SEPTIEMBRE 26 - 31 OCTUBRE 26
B45: =ROW()-9 -> 36 | C45: NO RESURTIBLE | D45: HONOR | E45: Honor X7D | F45: HONOR X7D 256GB 4G | G45: 5999 | H45: 2819 | I45: 2469 | J45: 2119 | K45: 1419 | L45: 729 | M45: 2579 | N45: 2119 | O45: 1649 | P45: 719 | Q45: 0 | R45: 2349 | S45: 1769 | T45: 1189 | U45: 19 | V45: 0 | W45: 2119 | X45: 1419 | Y45: 719 | Z45: 0 | AA45: 0 | AB45: 1649 | AC45: 719 | AD45: 0 | AE45: 0 | AF45: 0 | AG45: 489 | AH45: 0 | AI45: 0 | AJ45: 0 | AK45: 0 | AL45: 19 | AM45: 0 | AN45: 0 | AO45: 0 | AP45: 0 | AQ45: 46204 | AR45: 46295 | AS45: =UPPER(TEXT(AQ45, " dd \ mmmm \ aa")&" - "&TEXT(AR45, " dd \ mmmm \ aa")) -> 01 JULIO 26 - 30 SEPTIEMBRE 26
B46: =ROW()-9 -> 37 | C46: RESURTIBLE | D46: HONOR | E46: Honor X8D | F46: HONOR X8D 256GB 4G | G46: 6999 | H46: 4239 | I46: 4019 | J46: 3789 | K46: 3339 | L46: 2879 | M46: 4089 | N46: 3789 | O46: 3489 | P46: 2879 | Q46: 2279 | R46: 3939 | S46: 3559 | T46: 3179 | U46: 2429 | V46: 1669 | W46: 3789 | X46: 3339 | Y46: 2879 | Z46: 1969 | AA46: 1069 | AB46: 3489 | AC46: 2879 | AD46: 2279 | AE46: 1069 | AF46: 0 | AG46: 2729 | AH46: 1749 | AI46: 759 | AJ46: 0 | AK46: 0 | AL46: 2429 | AM46: 1289 | AN46: 159 | AO46: 0 | AP46: 0 | AQ46: 46204 | AR46: 46295 | AS46: =UPPER(TEXT(AQ46, " dd \ mmmm \ aa")&" - "&TEXT(AR46, " dd \ mmmm \ aa")) -> 01 JULIO 26 - 30 SEPTIEMBRE 26
B47: =ROW()-9 -> 38 | C47: NO RESURTIBLE | D47: MOTOROLA | E47: Motorola Moto Edge 50 | F47: MOTOROLA EDGE 50 512GB 5G | G47: 9999 | H47: 3709 | I47: 3479 | J47: 3249 | K47: 2799 | L47: 2349 | M47: 3549 | N47: 3249 | O47: 2949 | P47: 2349 | Q47: 1739 | R47: 3399 | S47: 3019 | T47: 2649 | U47: 1889 | V47: 1139 | W47: 3249 | X47: 2799 | Y47: 2339 | Z47: 1439 | AA47: 529 | AB47: 2949 | AC47: 2339 | AD47: 1739 | AE47: 529 | AF47: 0 | AG47: 2189 | AH47: 1209 | AI47: 219 | AJ47: 0 | AK47: 0 | AL47: 1889 | AM47: 749 | AN47: 0 | AO47: 0 | AP47: 0 | AQ47: 46235 | AR47: INDEFINIDO | AS47: =UPPER(TEXT(AQ47, " dd \ mmmm \ aa")&" - "&TEXT(AR47, " dd \ mmmm \ aa")) -> 01 AGOSTO 26 - INDEFINIDO
B48: =ROW()-9 -> 39 | C48: NO RESURTIBLE | D48: MOTOROLA | E48: Motorola Moto Edge 60 Pro | F48: MOTOROLA EDGE 60 PRO 512GB 5G | G48: 14999 | H48: 10349 | I48: 10119 | J48: 9899 | K48: 9449 | L48: 8989 | M48: 10199 | N48: 9899 | O48: 9599 | P48: 8989 | Q48: 8389 | R48: 10049 | S48: 9669 | T48: 9289 | U48: 8539 | V48: 7779 | W48: 9899 | X48: 9439 | Y48: 8989 | Z48: 8079 | AA48: 7179 | AB48: 9589 | AC48: 8989 | AD48: 8379 | AE48: 7169 | AF48: 5959 | AG48: 8839 | AH48: 7849 | AI48: 6869 | AJ48: 4899 | AK48: 2929 | AL48: 8529 | AM48: 7399 | AN48: 6259 | AO48: 3989 | AP48: 1719 | AQ48: 46204 | AR48: INDEFINIDO | AS48: =UPPER(TEXT(AQ48, " dd \ mmmm \ aa")&" - "&TEXT(AR48, " dd \ mmmm \ aa")) -> 01 JULIO 26 - INDEFINIDO
B49: =ROW()-9 -> 40 | C49: NO RESURTIBLE | D49: MOTOROLA | E49: Motorola Moto Edge 70 | F49: MOTOROLA EDGE 70 512GB 5G | G49: 12999 | H49: 7929 | I49: 7699 | J49: 7469 | K49: 7019 | L49: 6569 | M49: 7769 | N49: 7469 | O49: 7169 | P49: 6569 | Q49: 5959 | R49: 7619 | S49: 7239 | T49: 6869 | U49: 6109 | V49: 5359 | W49: 7469 | X49: 7019 | Y49: 6559 | Z49: 5659 | AA49: 4749 | AB49: 7169 | AC49: 6559 | AD49: 5959 | AE49: 4749 | AF49: 3539 | AG49: 6409 | AH49: 5429 | AI49: 4439 | AJ49: 2479 | AK49: 509 | AL49: 6109 | AM49: 4969 | AN49: 3839 | AO49: 1569 | AP49: 0 | AQ49: 46266 | AR49: 46295 | AS49: =UPPER(TEXT(AQ49, " dd \ mmmm \ aa")&" - "&TEXT(AR49, " dd \ mmmm \ aa")) -> 01 SEPTIEMBRE 26 - 30 SEPTIEMBRE 26
B50: =ROW()-9 -> 41 | C50: NO RESURTIBLE | D50: MOTOROLA | E50: Motorola Edge 70 Fusion Bundle Buds | F50: MOTOROLA EDGE 70 FUSION 256GB 5G | G50: 10999 | H50: 6299 | I50: 5949 | J50: 5599 | K50: 4909 | L50: 4209 | M50: 6069 | N50: 5599 | O50: 5139 | P50: 4209 | Q50: 3279 | R50: 5829 | S50: 5249 | T50: 4669 | U50: 3509 | V50: 2349 | W50: 5599 | X50: 4899 | Y50: 4199 | Z50: 2809 | AA50: 1409 | AB50: 5129 | AC50: 4199 | AD50: 3269 | AE50: 1409 | AF50: 0 | AG50: 3969 | AH50: 2459 | AI50: 939 | AJ50: 0 | AK50: 0 | AL50: 3499 | AM50: 1759 | AN50: 9 | AO50: 0 | AP50: 0 | AQ50: 46266 | AR50: 46295 | AS50: =UPPER(TEXT(AQ50, " dd \ mmmm \ aa")&" - "&TEXT(AR50, " dd \ mmmm \ aa")) -> 01 SEPTIEMBRE 26 - 30 SEPTIEMBRE 26
B51: =ROW()-9 -> 42 | C51: RESURTIBLE | D51: MOTOROLA | E51: Motorola Moto Edge 70 Pro + Watch | F51: MOTOROLA EDGE 70 PRO 512GB 5G | G51: 19999 | H51: 13999 | I51: 13749 | J51: 13549 | K51: 13099 | L51: 12699 | M51: 13849 | N51: 13549 | O51: 13249 | P51: 12699 | Q51: 12099 | R51: 13699 | S51: 13349 | T51: 12949 | U51: 12249 | V51: 11499 | W51: 13549 | X51: 13099 | Y51: 12699 | Z51: 11799 | AA51: 10949 | AB51: 13249 | AC51: 12699 | AD51: 12099 | AE51: 10949 | AF51: 9749 | AG51: 12549 | AH51: 11599 | AI51: 10649 | AJ51: 8749 | AK51: 6849 | AL51: 12249 | AM51: 11149 | AN51: 10049 | AO51: 7899 | AP51: 5699 | AQ51: 46178 | AR51: INDEFINIDO | AS51: =UPPER(TEXT(AQ51, " dd \ mmmm \ aa")&" - "&TEXT(AR51, " dd \ mmmm \ aa")) -> 05 JUNIO 26 - INDEFINIDO
B52: =ROW()-9 -> 43 | C52: NO RESURTIBLE | D52: MOTOROLA | E52: Motorola Moto G54 | F52: MOTOROLA G54 128GB 5G | G52: 4999 | H52: 1599 | I52: 1249 | J52: 899 | K52: 199 | L52: 0 | M52: 1349 | N52: 899 | O52: 449 | P52: 0 | Q52: 0 | R52: 1099 | S52: 549 | T52: 0 | U52: 0 | V52: 0 | W52: 899 | X52: 199 | Y52: 0 | Z52: 0 | AA52: 0 | AB52: 449 | AC52: 0 | AD52: 0 | AE52: 0 | AF52: 0 | AG52: 0 | AH52: 0 | AI52: 0 | AJ52: 0 | AK52: 0 | AL52: 0 | AM52: 0 | AN52: 0 | AO52: 0 | AP52: 0 | AQ52: 45908 | AR52: INDEFINIDO | AS52: =UPPER(TEXT(AQ52, " dd \ mmmm \ aa")&" - "&TEXT(AR52, " dd \ mmmm \ aa")) -> 08 SEPTIEMBRE 25 - INDEFINIDO
B53: =ROW()-9 -> 44 | C53: NO RESURTIBLE | D53: MOTOROLA | E53: Motorola Moto G54 256GB | F53: MOTOROLA G54 256GB 5G | G53: 4999 | H53: 899 | I53: 549 | J53: 199 | K53: 0 | L53: 0 | M53: 649 | N53: 199 | O53: 0 | P53: 0 | Q53: 0 | R53: 449 | S53: 0 | T53: 0 | U53: 0 | V53: 0 | W53: 199 | X53: 0 | Y53: 0 | Z53: 0 | AA53: 0 | AB53: 0 | AC53: 0 | AD53: 0 | AE53: 0 | AF53: 0 | AG53: 0 | AH53: 0 | AI53: 0 | AJ53: 0 | AK53: 0 | AL53: 0 | AM53: 0 | AN53: 0 | AO53: 0 | AP53: 0 | AQ53: 45962 | AR53: INDEFINIDO | AS53: =UPPER(TEXT(AQ53, " dd \ mmmm \ aa")&" - "&TEXT(AR53, " dd \ mmmm \ aa")) -> 01 NOVIEMBRE 25 - INDEFINIDO
B54: =ROW()-9 -> 45 | C54: NO RESURTIBLE | D54: MOTOROLA | E54: Motorola Moto G06 | F54: MOTOROLA MOTO G06 128GB 4G | G54: 2999 | H54: 1429 | I54: 1079 | J54: 739 | K54: 39 | L54: 0 | M54: 1199 | N54: 729 | O54: 269 | P54: 0 | Q54: 0 | R54: 969 | S54: 389 | T54: 0 | U54: 0 | V54: 0 | W54: 729 | X54: 39 | Y54: 0 | Z54: 0 | AA54: 0 | AB54: 269 | AC54: 0 | AD54: 0 | AE54: 0 | AF54: 0 | AG54: 0 | AH54: 0 | AI54: 0 | AJ54: 0 | AK54: 0 | AL54: 0 | AM54: 0 | AN54: 0 | AO54: 0 | AP54: 0 | AQ54: 46266 | AR54: INDEFINIDO | AS54: =UPPER(TEXT(AQ54, " dd \ mmmm \ aa")&" - "&TEXT(AR54, " dd \ mmmm \ aa")) -> 01 SEPTIEMBRE 26 - INDEFINIDO
B55: =ROW()-9 -> 46 | C55: NO RESURTIBLE | D55: MOTOROLA | E55: Motorola Moto G17 | F55: MOTOROLA MOTO G17 256GB 4G | G55: 5499 | H55: 3269 | I55: 2919 | J55: 2569 | K55: 1869 | L55: 1179 | M55: 3029 | N55: 2569 | O55: 2099 | P55: 1179 | Q55: 249 | R55: 2799 | S55: 2219 | T55: 1639 | U55: 479 | V55: 0 | W55: 2569 | X55: 1869 | Y55: 1169 | Z55: 0 | AA55: 0 | AB55: 2099 | AC55: 1169 | AD55: 239 | AE55: 0 | AF55: 0 | AG55: 939 | AH55: 0 | AI55: 0 | AJ55: 0 | AK55: 0 | AL55: 469 | AM55: 0 | AN55: 0 | AO55: 0 | AP55: 0 | AQ55: 46266 | AR55: INDEFINIDO | AS55: =UPPER(TEXT(AQ55, " dd \ mmmm \ aa")&" - "&TEXT(AR55, " dd \ mmmm \ aa")) -> 01 SEPTIEMBRE 26 - INDEFINIDO
B56: =ROW()-9 -> 47 | C56: NO RESURTIBLE | D56: MOTOROLA | E56: Motorola Moto G56 | F56: MOTOROLA MOTO G56 256GB 5G | G56: 5999 | H56: 3629 | I56: 3279 | J56: 2929 | K56: 2229 | L56: 1539 | M56: 3389 | N56: 2929 | O56: 2459 | P56: 1539 | Q56: 609 | R56: 3159 | S56: 2579 | T56: 1999 | U56: 839 | V56: 0 | W56: 2929 | X56: 2229 | Y56: 1529 | Z56: 139 | AA56: 0 | AB56: 2459 | AC56: 1529 | AD56: 599 | AE56: 0 | AF56: 0 | AG56: 1299 | AH56: 0 | AI56: 0 | AJ56: 0 | AK56: 0 | AL56: 829 | AM56: 0 | AN56: 0 | AO56: 0 | AP56: 0 | AQ56: 46185 | AR56: INDEFINIDO | AS56: =UPPER(TEXT(AQ56, " dd \ mmmm \ aa")&" - "&TEXT(AR56, " dd \ mmmm \ aa")) -> 12 JUNIO 26 - INDEFINIDO
B57: =ROW()-9 -> 48 | C57: NO RESURTIBLE | D57: MOTOROLA | E57: Motorola Moto G60 | F57: MOTOROLA MOTO G60 128GB 4G | G57: 6999 | H57: 0 | I57: 0 | J57: 0 | K57: 0 | L57: 0 | M57: 0 | N57: 0 | O57: 0 | P57: 0 | Q57: 0 | R57: 0 | S57: 0 | T57: 0 | U57: 0 | V57: 0 | W57: 0 | X57: 0 | Y57: 0 | Z57: 0 | AA57: 0 | AB57: 0 | AC57: 0 | AD57: 0 | AE57: 0 | AF57: 0 | AG57: 0 | AH57: 0 | AI57: 0 | AJ57: 0 | AK57: 0 | AL57: 0 | AM57: 0 | AN57: 0 | AO57: 0 | AP57: 0 | AQ57: 46199 | AR57: INDEFINIDO | AS57: =UPPER(TEXT(AQ57, " dd \ mmmm \ aa")&" - "&TEXT(AR57, " dd \ mmmm \ aa")) -> 26 JUNIO 26 - INDEFINIDO
B58: =ROW()-9 -> 49 | C58: NO RESURTIBLE | D58: MOTOROLA | E58: Motorola Moto G77 | F58: MOTOROLA MOTO G77 256GB 5G | G58: 7999 | H58: 4489 | I58: 4139 | J58: 3789 | K58: 3089 | L58: 2399 | M58: 4249 | N58: 3789 | O58: 3319 | P58: 2399 | Q58: 1469 | R58: 4019 | S58: 3439 | T58: 2859 | U58: 1699 | V58: 529 | W58: 3789 | X58: 3089 | Y58: 2389 | Z58: 999 | AA58: 0 | AB58: 3319 | AC58: 2389 | AD58: 1459 | AE58: 0 | AF58: 0 | AG58: 2159 | AH58: 639 | AI58: 0 | AJ58: 0 | AK58: 0 | AL58: 1689 | AM58: 0 | AN58: 0 | AO58: 0 | AP58: 0 | AQ58: 46266 | AR58: 46295 | AS58: =UPPER(TEXT(AQ58, " dd \ mmmm \ aa")&" - "&TEXT(AR58, " dd \ mmmm \ aa")) -> 01 SEPTIEMBRE 26 - 30 SEPTIEMBRE 26
B59: =ROW()-9 -> 50 | C59: NO RESURTIBLE | D59: MOTOROLA | E59: Motorola Razr 60 Ultra | F59: MOTOROLA RAZR 60 ULTRA 1T 5G | G59: 32999 | H59: 15229 | I59: 14999 | J59: 14769 | K59: 14319 | L59: 13869 | M59: 15079 | N59: 14769 | O59: 14469 | P59: 13869 | Q59: 13259 | R59: 14919 | S59: 14549 | T59: 14169 | U59: 13409 | V59: 12659 | W59: 14769 | X59: 14319 | Y59: 13869 | Z59: 12959 | AA59: 12049 | AB59: 14469 | AC59: 13859 | AD59: 13259 | AE59: 12049 | AF59: 10839 | AG59: 13709 | AH59: 12729 | AI59: 11749 | AJ59: 9779 | AK59: 7809 | AL59: 13409 | AM59: 12269 | AN59: 11139 | AO59: 8869 | AP59: 6599 | AQ59: 46266 | AR59: 46295 | AS59: =UPPER(TEXT(AQ59, " dd \ mmmm \ aa")&" - "&TEXT(AR59, " dd \ mmmm \ aa")) -> 01 SEPTIEMBRE 26 - 30 SEPTIEMBRE 26
B60: =ROW()-9 -> 51 | C60: NO RESURTIBLE | D60: OPPO | E60: Oppo A38 128GB | F60: OPPO A38 128GB 4G | G60: 3499 | H60: 99 | I60: 0 | J60: 0 | K60: 0 | L60: 0 | M60: 0 | N60: 0 | O60: 0 | P60: 0 | Q60: 0 | R60: 0 | S60: 0 | T60: 0 | U60: 0 | V60: 0 | W60: 0 | X60: 0 | Y60: 0 | Z60: 0 | AA60: 0 | AB60: 0 | AC60: 0 | AD60: 0 | AE60: 0 | AF60: 0 | AG60: 0 | AH60: 0 | AI60: 0 | AJ60: 0 | AK60: 0 | AL60: 0 | AM60: 0 | AN60: 0 | AO60: 0 | AP60: 0 | AQ60: 46227 | AR60: INDEFINIDO | AS60: =UPPER(TEXT(AQ60, " dd \ mmmm \ aa")&" - "&TEXT(AR60, " dd \ mmmm \ aa")) -> 24 JULIO 26 - INDEFINIDO
B61: =ROW()-9 -> 52 | C61: NO RESURTIBLE | D61: OPPO | E61: Oppo A40 | F61: OPPO A40 256GB 4G | G61: 3999 | H61: 1459 | I61: 1109 | J61: 759 | K61: 59 | L61: 0 | M61: 1219 | N61: 759 | O61: 299 | P61: 0 | Q61: 0 | R61: 989 | S61: 409 | T61: 0 | U61: 0 | V61: 0 | W61: 759 | X61: 59 | Y61: 0 | Z61: 0 | AA61: 0 | AB61: 289 | AC61: 0 | AD61: 0 | AE61: 0 | AF61: 0 | AG61: 0 | AH61: 0 | AI61: 0 | AJ61: 0 | AK61: 0 | AL61: 0 | AM61: 0 | AN61: 0 | AO61: 0 | AP61: 0 | AQ61: 46224 | AR61: INDEFINIDO | AS61: =UPPER(TEXT(AQ61, " dd \ mmmm \ aa")&" - "&TEXT(AR61, " dd \ mmmm \ aa")) -> 21 JULIO 26 - INDEFINIDO
B62: =ROW()-9 -> 53 | C62: NO RESURTIBLE | D62: OPPO | E62: Oppo A5 | F62: OPPO A5 256GB 4G | G62: 4499 | H62: 2549 | I62: 2199 | J62: 1849 | K62: 1149 | L62: 459 | M62: 2309 | N62: 1849 | O62: 1379 | P62: 459 | Q62: 0 | R62: 2079 | S62: 1499 | T62: 919 | U62: 0 | V62: 0 | W62: 1849 | X62: 1149 | Y62: 449 | Z62: 0 | AA62: 0 | AB62: 1379 | AC62: 449 | AD62: 0 | AE62: 0 | AF62: 0 | AG62: 219 | AH62: 0 | AI62: 0 | AJ62: 0 | AK62: 0 | AL62: 0 | AM62: 0 | AN62: 0 | AO62: 0 | AP62: 0 | AQ62: 46206 | AR62: INDEFINIDO | AS62: =UPPER(TEXT(AQ62, " dd \ mmmm \ aa")&" - "&TEXT(AR62, " dd \ mmmm \ aa")) -> 03 JULIO 26 - INDEFINIDO
B63: =ROW()-9 -> 54 | C63: NO RESURTIBLE | D63: OPPO | E63: Oppo A5 Pro 5G Bundle Enco Buds 3 | F63: OPPO A5 PRO 256GB 5G | G63: 7999 | H63: 3949 | I63: 3729 | J63: 3499 | K63: 3049 | L63: 2589 | M63: 3799 | N63: 3499 | O63: 3199 | P63: 2589 | Q63: 1989 | R63: 3649 | S63: 3269 | T63: 2889 | U63: 2139 | V63: 1379 | W63: 3499 | X63: 3039 | Y63: 2589 | Z63: 1679 | AA63: 779 | AB63: 3189 | AC63: 2589 | AD63: 1979 | AE63: 769 | AF63: 0 | AG63: 2439 | AH63: 1449 | AI63: 469 | AJ63: 0 | AK63: 0 | AL63: 2129 | AM63: 999 | AN63: 0 | AO63: 0 | AP63: 0 | AQ63: 46235 | AR63: 46299 | AS63: =UPPER(TEXT(AQ63, " dd \ mmmm \ aa")&" - "&TEXT(AR63, " dd \ mmmm \ aa")) -> 01 AGOSTO 26 - 04 OCTUBRE 26
B64: =ROW()-9 -> 55 | C64: RESURTIBLE | D64: OPPO | E64: Oppo A6 Bundle Enco Buds 3 | F64: OPPO A6 256GB 4G | G64: 9999 | H64: 5459 | I64: 5119 | J64: 4769 | K64: 4069 | L64: 3369 | M64: 5229 | N64: 4769 | O64: 4299 | P64: 3369 | Q64: 2439 | R64: 4999 | S64: 4419 | T64: 3829 | U64: 2669 | V64: 1509 | W64: 4759 | X64: 4069 | Y64: 3369 | Z64: 1969 | AA64: 579 | AB64: 4299 | AC64: 3369 | AD64: 2439 | AE64: 579 | AF64: 0 | AG64: 3129 | AH64: 1619 | AI64: 109 | AJ64: 0 | AK64: 0 | AL64: 2669 | AM64: 919 | AN64: 0 | AO64: 0 | AP64: 0 | AQ64: 46266 | AR64: 46299 | AS64: =UPPER(TEXT(AQ64, " dd \ mmmm \ aa")&" - "&TEXT(AR64, " dd \ mmmm \ aa")) -> 01 SEPTIEMBRE 26 - 04 OCTUBRE 26
B65: =ROW()-9 -> 56 | C65: NO RESURTIBLE | D65: OPPO | E65: OPPO A6K 256GB 5G | F65: OPPO A6K 256GB 5G | G65: 7499 | H65: 2969 | I65: 2619 | J65: 2269 | K65: 1569 | L65: 879 | M65: 2729 | N65: 2269 | O65: 1799 | P65: 879 | Q65: 0 | R65: 2499 | S65: 1919 | T65: 1339 | U65: 179 | V65: 0 | W65: 2269 | X65: 1569 | Y65: 869 | Z65: 0 | AA65: 0 | AB65: 1799 | AC65: 869 | AD65: 0 | AE65: 0 | AF65: 0 | AG65: 639 | AH65: 0 | AI65: 0 | AJ65: 0 | AK65: 0 | AL65: 169 | AM65: 0 | AN65: 0 | AO65: 0 | AP65: 0 | AQ65: 46259 | AR65: 46299 | AS65: =UPPER(TEXT(AQ65, " dd \ mmmm \ aa")&" - "&TEXT(AR65, " dd \ mmmm \ aa")) -> 25 AGOSTO 26 - 04 OCTUBRE 26
B66: =ROW()-9 -> 57 | C66: RESURTIBLE | D66: OPPO | E66: OPPO A6T 128GB 4G | F66: OPPO A6T 128GB 4G | G66: 6999 | H66: 1689 | I66: 1339 | J66: 989 | K66: 289 | L66: 0 | M66: 1449 | N66: 989 | O66: 519 | P66: 0 | Q66: 0 | R66: 1219 | S66: 639 | T66: 59 | U66: 0 | V66: 0 | W66: 989 | X66: 289 | Y66: 0 | Z66: 0 | AA66: 0 | AB66: 519 | AC66: 0 | AD66: 0 | AE66: 0 | AF66: 0 | AG66: 0 | AH66: 0 | AI66: 0 | AJ66: 0 | AK66: 0 | AL66: 0 | AM66: 0 | AN66: 0 | AO66: 0 | AP66: 0 | AQ66: 46259 | AR66: 46316 | AS66: =UPPER(TEXT(AQ66, " dd \ mmmm \ aa")&" - "&TEXT(AR66, " dd \ mmmm \ aa")) -> 25 AGOSTO 26 - 21 OCTUBRE 26
B67: =ROW()-9 -> 58 | C67: NO RESURTIBLE | D67: OPPO | E67: Oppo A6x | F67: OPPO A6X 128GB 4G | G67: 3699 | H67: 1509 | I67: 1159 | J67: 809 | K67: 109 | L67: 0 | M67: 1269 | N67: 809 | O67: 339 | P67: 0 | Q67: 0 | R67: 1039 | S67: 459 | T67: 0 | U67: 0 | V67: 0 | W67: 809 | X67: 109 | Y67: 0 | Z67: 0 | AA67: 0 | AB67: 339 | AC67: 0 | AD67: 0 | AE67: 0 | AF67: 0 | AG67: 0 | AH67: 0 | AI67: 0 | AJ67: 0 | AK67: 0 | AL67: 0 | AM67: 0 | AN67: 0 | AO67: 0 | AP67: 0 | AQ67: 46206 | AR67: 46299 | AS67: =UPPER(TEXT(AQ67, " dd \ mmmm \ aa")&" - "&TEXT(AR67, " dd \ mmmm \ aa")) -> 03 JULIO 26 - 04 OCTUBRE 26
B68: =ROW()-9 -> 59 | C68: NO RESURTIBLE | D68: OPPO | E68: Oppo A80 | F68: OPPO A80 256GB 5G | G68: 6999 | H68: 2049 | I68: 1829 | J68: 1599 | K68: 1149 | L68: 689 | M68: 1899 | N68: 1599 | O68: 1299 | P68: 689 | Q68: 89 | R68: 1749 | S68: 1369 | T68: 989 | U68: 239 | V68: 0 | W68: 1599 | X68: 1139 | Y68: 689 | Z68: 0 | AA68: 0 | AB68: 1299 | AC68: 689 | AD68: 89 | AE68: 0 | AF68: 0 | AG68: 539 | AH68: 0 | AI68: 0 | AJ68: 0 | AK68: 0 | AL68: 239 | AM68: 0 | AN68: 0 | AO68: 0 | AP68: 0 | AQ68: 46224 | AR68: INDEFINIDO | AS68: =UPPER(TEXT(AQ68, " dd \ mmmm \ aa")&" - "&TEXT(AR68, " dd \ mmmm \ aa")) -> 21 JULIO 26 - INDEFINIDO
B69: =ROW()-9 -> 60 | C69: NO RESURTIBLE | D69: OPPO | E69: Oppo Find X9 Pro | F69: OPPO FIND X9 PRO 5G | G69: 27999 | H69: 18549 | I69: 18319 | J69: 18099 | K69: 17649 | L69: 17189 | M69: 18399 | N69: 18099 | O69: 17799 | P69: 17189 | Q69: 16589 | R69: 18249 | S69: 17869 | T69: 17489 | U69: 16739 | V69: 15979 | W69: 18099 | X69: 17639 | Y69: 17189 | Z69: 16279 | AA69: 15379 | AB69: 17789 | AC69: 17189 | AD69: 16579 | AE69: 15369 | AF69: 14159 | AG69: 17039 | AH69: 16049 | AI69: 15069 | AJ69: 13099 | AK69: 11129 | AL69: 16729 | AM69: 15599 | AN69: 14459 | AO69: 12189 | AP69: 9919 | AQ69: 46204 | AR69: 46299 | AS69: =UPPER(TEXT(AQ69, " dd \ mmmm \ aa")&" - "&TEXT(AR69, " dd \ mmmm \ aa")) -> 01 JULIO 26 - 04 OCTUBRE 26
B70: =ROW()-9 -> 61 | C70: NO RESURTIBLE | D70: OPPO | E70: Oppo Reno 12 5G | F70: OPPO RENO 12 512GB 5G | G70: 11999 | H70: 5939 | I70: 5719 | J70: 5489 | K70: 5039 | L70: 4579 | M70: 5789 | N70: 5489 | O70: 5189 | P70: 4579 | Q70: 3979 | R70: 5639 | S70: 5259 | T70: 4879 | U70: 4129 | V70: 3369 | W70: 5489 | X70: 5029 | Y70: 4579 | Z70: 3669 | AA70: 2769 | AB70: 5179 | AC70: 4579 | AD70: 3969 | AE70: 2759 | AF70: 1549 | AG70: 4429 | AH70: 3439 | AI70: 2459 | AJ70: 489 | AK70: 0 | AL70: 4119 | AM70: 2989 | AN70: 1849 | AO70: 0 | AP70: 0 | AQ70: 46224 | AR70: INDEFINIDO | AS70: =UPPER(TEXT(AQ70, " dd \ mmmm \ aa")&" - "&TEXT(AR70, " dd \ mmmm \ aa")) -> 21 JULIO 26 - INDEFINIDO
B71: =ROW()-9 -> 62 | C71: NO RESURTIBLE | D71: OPPO | E71: Oppo Reno 12F 5G | F71: OPPO RENO 12 F 256GB 5G | G71: 8999 | H71: 2869 | I71: 2639 | J71: 2409 | K71: 1959 | L71: 1509 | M71: 2719 | N71: 2409 | O71: 2109 | P71: 1509 | Q71: 899 | R71: 2559 | S71: 2189 | T71: 1809 | U71: 1049 | V71: 299 | W71: 2409 | X71: 1959 | Y71: 1509 | Z71: 599 | AA71: 0 | AB71: 2109 | AC71: 1499 | AD71: 899 | AE71: 0 | AF71: 0 | AG71: 1349 | AH71: 369 | AI71: 0 | AJ71: 0 | AK71: 0 | AL71: 1049 | AM71: 0 | AN71: 0 | AO71: 0 | AP71: 0 | AQ71: 46224 | AR71: INDEFINIDO | AS71: =UPPER(TEXT(AQ71, " dd \ mmmm \ aa")&" - "&TEXT(AR71, " dd \ mmmm \ aa")) -> 21 JULIO 26 - INDEFINIDO
B72: =ROW()-9 -> 63 | C72: NO RESURTIBLE | D72: OPPO | E72: Oppo Reno 13 5G | F72: OPPO RENO 13 512GB 5G | G72: 14999 | H72: 8889 | I72: 8659 | J72: 8439 | K72: 7989 | L72: 7529 | M72: 8739 | N72: 8439 | O72: 8139 | P72: 7529 | Q72: 6929 | R72: 8589 | S72: 8209 | T72: 7829 | U72: 7079 | V72: 6319 | W72: 8439 | X72: 7979 | Y72: 7529 | Z72: 6619 | AA72: 5719 | AB72: 8129 | AC72: 7529 | AD72: 6919 | AE72: 5709 | AF72: 4499 | AG72: 7379 | AH72: 6389 | AI72: 5409 | AJ72: 3439 | AK72: 1469 | AL72: 7069 | AM72: 5939 | AN72: 4799 | AO72: 2529 | AP72: 259 | AQ72: 46224 | AR72: INDEFINIDO | AS72: =UPPER(TEXT(AQ72, " dd \ mmmm \ aa")&" - "&TEXT(AR72, " dd \ mmmm \ aa")) -> 21 JULIO 26 - INDEFINIDO
B73: =ROW()-9 -> 64 | C73: NO RESURTIBLE | D73: OPPO | E73: Oppo Reno 13F 5G | F73: OPPO RENO 13F 256GB 5G | G73: 9999 | H73: 5599 | I73: 5379 | J73: 5149 | K73: 4699 | L73: 4239 | M73: 5449 | N73: 5149 | O73: 4849 | P73: 4239 | Q73: 3639 | R73: 5299 | S73: 4919 | T73: 4539 | U73: 3789 | V73: 3029 | W73: 5149 | X73: 4689 | Y73: 4239 | Z73: 3329 | AA73: 2429 | AB73: 4849 | AC73: 4239 | AD73: 3639 | AE73: 2419 | AF73: 1209 | AG73: 4089 | AH73: 3099 | AI73: 2119 | AJ73: 149 | AK73: 0 | AL73: 3779 | AM73: 2649 | AN73: 1509 | AO73: 0 | AP73: 0 | AQ73: 46206 | AR73: INDEFINIDO | AS73: =UPPER(TEXT(AQ73, " dd \ mmmm \ aa")&" - "&TEXT(AR73, " dd \ mmmm \ aa")) -> 03 JULIO 26 - INDEFINIDO
B74: =ROW()-9 -> 65 | C74: NO RESURTIBLE | D74: OPPO | E74: Oppo Reno 14 5G Bundle Headphones | F74: OPPO RENO14 512GB 5G | G74: 14999 | H74: 8949 | I74: 8719 | J74: 8489 | K74: 8039 | L74: 7589 | M74: 8789 | N74: 8489 | O74: 8189 | P74: 7589 | Q74: 6979 | R74: 8639 | S74: 8259 | T74: 7889 | U74: 7129 | V74: 6379 | W74: 8489 | X74: 8039 | Y74: 7579 | Z74: 6679 | AA74: 5769 | AB74: 8189 | AC74: 7579 | AD74: 6979 | AE74: 5769 | AF74: 4559 | AG74: 7429 | AH74: 6449 | AI74: 5459 | AJ74: 3499 | AK74: 1529 | AL74: 7129 | AM74: 5989 | AN74: 4859 | AO74: 2589 | AP74: 319 | AQ74: 46204 | AR74: 46299 | AS74: =UPPER(TEXT(AQ74, " dd \ mmmm \ aa")&" - "&TEXT(AR74, " dd \ mmmm \ aa")) -> 01 JULIO 26 - 04 OCTUBRE 26
B75: =ROW()-9 -> 66 | C75: NO RESURTIBLE | D75: OPPO | E75: Oppo Reno 14F & Bundle | F75: OPPO RENO14 F 256GB 5G | G75: 9999 | H75: 5809 | I75: 5589 | J75: 5359 | K75: 4909 | L75: 4449 | M75: 5659 | N75: 5359 | O75: 5059 | P75: 4449 | Q75: 3849 | R75: 5509 | S75: 5129 | T75: 4749 | U75: 3999 | V75: 3239 | W75: 5359 | X75: 4899 | Y75: 4449 | Z75: 3539 | AA75: 2639 | AB75: 5059 | AC75: 4449 | AD75: 3849 | AE75: 2629 | AF75: 1419 | AG75: 4299 | AH75: 3309 | AI75: 2329 | AJ75: 359 | AK75: 0 | AL75: 3999 | AM75: 2859 | AN75: 1719 | AO75: 0 | AP75: 0 | AQ75: 46174 | AR75: 46299 | AS75: =UPPER(TEXT(AQ75, " dd \ mmmm \ aa")&" - "&TEXT(AR75, " dd \ mmmm \ aa")) -> 01 JUNIO 26 - 04 OCTUBRE 26
B76: =ROW()-9 -> 67 | C76: NPI | D76: OPPO | E76: Oppo Reno16 256GB Bdl Enco Buds 3 Pro | F76: OPPO RENO16 256GB 5G BDL ENCO BUDS 3 PRO | G76: 18999 | H76: 10909 | I76: 10679 | J76: 10459 | K76: 10009 | L76: 9549 | M76: 10759 | N76: 10459 | O76: 10159 | P76: 9549 | Q76: 8949 | R76: 10609 | S76: 10229 | T76: 9849 | U76: 9099 | V76: 8339 | W76: 10459 | X76: 9999 | Y76: 9549 | Z76: 8639 | AA76: 7739 | AB76: 10149 | AC76: 9549 | AD76: 8939 | AE76: 7729 | AF76: 6519 | AG76: 9399 | AH76: 8409 | AI76: 7429 | AJ76: 5459 | AK76: 3489 | AL76: 9089 | AM76: 7959 | AN76: 6819 | AO76: 4549 | AP76: 2279 | AQ76: 46266 | AR76: 46316 | AS76: =UPPER(TEXT(AQ76, " dd \ mmmm \ aa")&" - "&TEXT(AR76, " dd \ mmmm \ aa")) -> 01 SEPTIEMBRE 26 - 21 OCTUBRE 26
B77: =ROW()-9 -> 68 | C77: NPI | D77: OPPO | E77: Oppo Reno16 F & Bdl Enco Buds 3 | F77: OPPO RENO16 F 256GB 5G | G77: 15999 | H77: 8509 | I77: 8159 | J77: 7809 | K77: 7109 | L77: 6419 | M77: 8269 | N77: 7809 | O77: 7339 | P77: 6419 | Q77: 5489 | R77: 8039 | S77: 7459 | T77: 6879 | U77: 5719 | V77: 4549 | W77: 7809 | X77: 7109 | Y77: 6409 | Z77: 5019 | AA77: 3619 | AB77: 7339 | AC77: 6409 | AD77: 5479 | AE77: 3619 | AF77: 1759 | AG77: 6179 | AH77: 4659 | AI77: 3149 | AJ77: 119 | AK77: 0 | AL77: 5709 | AM77: 3969 | AN77: 2219 | AO77: 0 | AP77: 0 | AQ77: 46206 | AR77: 46316 | AS77: =UPPER(TEXT(AQ77, " dd \ mmmm \ aa")&" - "&TEXT(AR77, " dd \ mmmm \ aa")) -> 03 JULIO 26 - 21 OCTUBRE 26
B78: =ROW()-9 -> 69 | C78: NO RESURTIBLE | D78: SAMSUNG | E78: Samsung Galaxy A05 64GB 4G | F78: SAMSUNG GALAXY A05 64GB 4G | G78: 2499 | H78: 409 | I78: 189 | J78: 0 | K78: 0 | L78: 0 | M78: 259 | N78: 0 | O78: 0 | P78: 0 | Q78: 0 | R78: 109 | S78: 0 | T78: 0 | U78: 0 | V78: 0 | W78: 0 | X78: 0 | Y78: 0 | Z78: 0 | AA78: 0 | AB78: 0 | AC78: 0 | AD78: 0 | AE78: 0 | AF78: 0 | AG78: 0 | AH78: 0 | AI78: 0 | AJ78: 0 | AK78: 0 | AL78: 0 | AM78: 0 | AN78: 0 | AO78: 0 | AP78: 0 | AQ78: 46199 | AR78: INDEFINIDO | AS78: =UPPER(TEXT(AQ78, " dd \ mmmm \ aa")&" - "&TEXT(AR78, " dd \ mmmm \ aa")) -> 26 JUNIO 26 - INDEFINIDO
B79: =ROW()-9 -> 70 | C79: NO RESURTIBLE | D79: SAMSUNG | E79: Samsung Galaxy A07 128GB | F79: SAMSUNG GALAXY A07 128GB 4G | G79: 2999 | H79: 1649 | I79: 1299 | J79: 949 | K79: 249 | L79: 0 | M79: 1409 | N79: 949 | O79: 479 | P79: 0 | Q79: 0 | R79: 1179 | S79: 599 | T79: 19 | U79: 0 | V79: 0 | W79: 949 | X79: 249 | Y79: 0 | Z79: 0 | AA79: 0 | AB79: 479 | AC79: 0 | AD79: 0 | AE79: 0 | AF79: 0 | AG79: 0 | AH79: 0 | AI79: 0 | AJ79: 0 | AK79: 0 | AL79: 0 | AM79: 0 | AN79: 0 | AO79: 0 | AP79: 0 | AQ79: 46251 | AR79: INDEFINIDO | AS79: =UPPER(TEXT(AQ79, " dd \ mmmm \ aa")&" - "&TEXT(AR79, " dd \ mmmm \ aa")) -> 17 AGOSTO 26 - INDEFINIDO
B80: =ROW()-9 -> 71 | C80: NO RESURTIBLE | D80: SAMSUNG | E80: Samsung A16 128GB 4G | F80: SAMSUNG GALAXY A16 128GB 4G | G80: 4299 | H80: 2429 | I80: 2089 | J80: 1739 | K80: 1039 | L80: 339 | M80: 2199 | N80: 1739 | O80: 1269 | P80: 339 | Q80: 0 | R80: 1969 | S80: 1389 | T80: 809 | U80: 0 | V80: 0 | W80: 1739 | X80: 1039 | Y80: 339 | Z80: 0 | AA80: 0 | AB80: 1269 | AC80: 339 | AD80: 0 | AE80: 0 | AF80: 0 | AG80: 99 | AH80: 0 | AI80: 0 | AJ80: 0 | AK80: 0 | AL80: 0 | AM80: 0 | AN80: 0 | AO80: 0 | AP80: 0 | AQ80: 46251 | AR80: INDEFINIDO | AS80: =UPPER(TEXT(AQ80, " dd \ mmmm \ aa")&" - "&TEXT(AR80, " dd \ mmmm \ aa")) -> 17 AGOSTO 26 - INDEFINIDO
B81: =ROW()-9 -> 72 | C81: RESURTIBLE | D81: SAMSUNG | E81: Samsung A17 128GB 4G | F81: SAMSUNG GALAXY A17 128GB 4G | G81: 4499 | H81: 2759 | I81: 2409 | J81: 2059 | K81: 1369 | L81: 669 | M81: 2529 | N81: 2059 | O81: 1599 | P81: 669 | Q81: 0 | R81: 2299 | S81: 1709 | T81: 1129 | U81: 0 | V81: 0 | W81: 2059 | X81: 1359 | Y81: 669 | Z81: 0 | AA81: 0 | AB81: 1599 | AC81: 669 | AD81: 0 | AE81: 0 | AF81: 0 | AG81: 429 | AH81: 0 | AI81: 0 | AJ81: 0 | AK81: 0 | AL81: 0 | AM81: 0 | AN81: 0 | AO81: 0 | AP81: 0 | AQ81: 46251 | AR81: INDEFINIDO | AS81: =UPPER(TEXT(AQ81, " dd \ mmmm \ aa")&" - "&TEXT(AR81, " dd \ mmmm \ aa")) -> 17 AGOSTO 26 - INDEFINIDO
B82: =ROW()-9 -> 73 | C82: NPI | D82: SAMSUNG | E82: Samsung Galaxy A27 128GB 5G | F82: SAMSUNG GALAXY A27 128GB 5G | G82: 6599 | H82: 4459 | I82: 4109 | J82: 3759 | K82: 3059 | L82: 2369 | M82: 4219 | N82: 3759 | O82: 3289 | P82: 2359 | Q82: 1429 | R82: 3989 | S82: 3409 | T82: 2829 | U82: 1659 | V82: 499 | W82: 3759 | X82: 3059 | Y82: 2359 | Z82: 969 | AA82: 0 | AB82: 3289 | AC82: 2359 | AD82: 1429 | AE82: 0 | AF82: 0 | AG82: 2129 | AH82: 609 | AI82: 0 | AJ82: 0 | AK82: 0 | AL82: 1659 | AM82: 0 | AN82: 0 | AO82: 0 | AP82: 0 | AQ82: 46251 | AR82: INDEFINIDO | AS82: =UPPER(TEXT(AQ82, " dd \ mmmm \ aa")&" - "&TEXT(AR82, " dd \ mmmm \ aa")) -> 17 AGOSTO 26 - INDEFINIDO
B83: =ROW()-9 -> 74 | C83: NO RESURTIBLE | D83: SAMSUNG | E83: Samsung Galaxy A34 5G 128GB | F83: SAMSUNG GALAXY A34 128GB 5G | G83: 7999 | H83: 409 | I83: 189 | J83: 0 | K83: 0 | L83: 0 | M83: 259 | N83: 0 | O83: 0 | P83: 0 | Q83: 0 | R83: 109 | S83: 0 | T83: 0 | U83: 0 | V83: 0 | W83: 0 | X83: 0 | Y83: 0 | Z83: 0 | AA83: 0 | AB83: 0 | AC83: 0 | AD83: 0 | AE83: 0 | AF83: 0 | AG83: 0 | AH83: 0 | AI83: 0 | AJ83: 0 | AK83: 0 | AL83: 0 | AM83: 0 | AN83: 0 | AO83: 0 | AP83: 0 | AQ83: 46199 | AR83: INDEFINIDO | AS83: =UPPER(TEXT(AQ83, " dd \ mmmm \ aa")&" - "&TEXT(AR83, " dd \ mmmm \ aa")) -> 26 JUNIO 26 - INDEFINIDO
B84: =ROW()-9 -> 75 | C84: NO RESURTIBLE | D84: SAMSUNG | E84: Samsung Galaxy A35 128GB | F84: SAMSUNG GALAXY A35 128GB 5G | G84: 6999 | H84: 3869 | I84: 3639 | J84: 3419 | K84: 2959 | L84: 2509 | M84: 3719 | N84: 3419 | O84: 3109 | P84: 2509 | Q84: 1899 | R84: 3569 | S84: 3189 | T84: 2809 | U84: 2049 | V84: 1299 | W84: 3409 | X84: 2959 | Y84: 2509 | Z84: 1599 | AA84: 689 | AB84: 3109 | AC84: 2509 | AD84: 1899 | AE84: 689 | AF84: 0 | AG84: 2349 | AH84: 1369 | AI84: 389 | AJ84: 0 | AK84: 0 | AL84: 2049 | AM84: 919 | AN84: 0 | AO84: 0 | AP84: 0 | AQ84: 46199 | AR84: INDEFINIDO | AS84: =UPPER(TEXT(AQ84, " dd \ mmmm \ aa")&" - "&TEXT(AR84, " dd \ mmmm \ aa")) -> 26 JUNIO 26 - INDEFINIDO
B85: =ROW()-9 -> 76 | C85: NO RESURTIBLE | D85: SAMSUNG | E85: Samsung Galaxy A36 128GB | F85: SAMSUNG GALAXY A36 128GB 5G | G85: 7499 | H85: 4669 | I85: 4319 | J85: 3969 | K85: 3279 | L85: 2579 | M85: 4439 | N85: 3969 | O85: 3509 | P85: 2579 | Q85: 1649 | R85: 4199 | S85: 3619 | T85: 3039 | U85: 1879 | V85: 719 | W85: 3969 | X85: 3269 | Y85: 2579 | Z85: 1179 | AA85: 0 | AB85: 3509 | AC85: 2569 | AD85: 1639 | AE85: 0 | AF85: 0 | AG85: 2339 | AH85: 829 | AI85: 0 | AJ85: 0 | AK85: 0 | AL85: 1869 | AM85: 129 | AN85: 0 | AO85: 0 | AP85: 0 | AQ85: 46251 | AR85: INDEFINIDO | AS85: =UPPER(TEXT(AQ85, " dd \ mmmm \ aa")&" - "&TEXT(AR85, " dd \ mmmm \ aa")) -> 17 AGOSTO 26 - INDEFINIDO
B86: =ROW()-9 -> 77 | C86: NO RESURTIBLE | D86: SAMSUNG | E86: Samsung Galaxy A37 256GB | F86: SAMSUNG GALAXY A37 256GB 5G | G86: 9999 | H86: 7309 | I86: 6959 | J86: 6609 | K86: 5909 | L86: 5219 | M86: 7069 | N86: 6609 | O86: 6139 | P86: 5219 | Q86: 4289 | R86: 6839 | S86: 6259 | T86: 5679 | U86: 4519 | V86: 3349 | W86: 6609 | X86: 5909 | Y86: 5209 | Z86: 3819 | AA86: 2419 | AB86: 6139 | AC86: 5209 | AD86: 4279 | AE86: 2419 | AF86: 559 | AG86: 4979 | AH86: 3459 | AI86: 1949 | AJ86: 0 | AK86: 0 | AL86: 4509 | AM86: 2759 | AN86: 1019 | AO86: 0 | AP86: 0 | AQ86: 46251 | AR86: INDEFINIDO | AS86: =UPPER(TEXT(AQ86, " dd \ mmmm \ aa")&" - "&TEXT(AR86, " dd \ mmmm \ aa")) -> 17 AGOSTO 26 - INDEFINIDO
B87: =ROW()-9 -> 78 | C87: NO RESURTIBLE | D87: SAMSUNG | E87: Samsung Galaxy A56 256GB | F87: SAMSUNG GALAXY A56 256GB 5G | G87: 10999 | H87: 8009 | I87: 7659 | J87: 7309 | K87: 6619 | L87: 5919 | M87: 7779 | N87: 7309 | O87: 6849 | P87: 5919 | Q87: 4989 | R87: 7539 | S87: 6959 | T87: 6379 | U87: 5219 | V87: 4059 | W87: 7309 | X87: 6609 | Y87: 5909 | Z87: 4519 | AA87: 3119 | AB87: 6839 | AC87: 5909 | AD87: 4979 | AE87: 3119 | AF87: 1259 | AG87: 5679 | AH87: 4169 | AI87: 2649 | AJ87: 0 | AK87: 0 | AL87: 5209 | AM87: 3469 | AN87: 1719 | AO87: 0 | AP87: 0 | AQ87: 46251 | AR87: INDEFINIDO | AS87: =UPPER(TEXT(AQ87, " dd \ mmmm \ aa")&" - "&TEXT(AR87, " dd \ mmmm \ aa")) -> 17 AGOSTO 26 - INDEFINIDO
B88: =ROW()-9 -> 79 | C88: RESURTIBLE | D88: SAMSUNG | E88: Samsung Galaxy A57 256GB | F88: SAMSUNG GALAXY A57 256GB 5G | G88: 11999 | H88: 8909 | I88: 8559 | J88: 8209 | K88: 7509 | L88: 6819 | M88: 8669 | N88: 8209 | O88: 7739 | P88: 6809 | Q88: 5889 | R88: 8439 | S88: 7859 | T88: 7279 | U88: 6119 | V88: 4949 | W88: 8209 | X88: 7509 | Y88: 6809 | Z88: 5419 | AA88: 4019 | AB88: 7739 | AC88: 6809 | AD88: 5879 | AE88: 4019 | AF88: 2159 | AG88: 6579 | AH88: 5059 | AI88: 3549 | AJ88: 519 | AK88: 0 | AL88: 6109 | AM88: 4359 | AN88: 2619 | AO88: 0 | AP88: 0 | AQ88: 46251 | AR88: INDEFINIDO | AS88: =UPPER(TEXT(AQ88, " dd \ mmmm \ aa")&" - "&TEXT(AR88, " dd \ mmmm \ aa")) -> 17 AGOSTO 26 - INDEFINIDO
B89: =ROW()-9 -> 80 | C89: NO RESURTIBLE | D89: SAMSUNG | E89: Samsung Galaxy S25 Fe 128GB | F89: SAMSUNG GALAXY S25 FE 128GB 5G | G89: 15499 | H89: 11949 | I89: 11719 | J89: 11499 | K89: 11049 | L89: 10589 | M89: 11799 | N89: 11499 | O89: 11199 | P89: 10589 | Q89: 9989 | R89: 11649 | S89: 11269 | T89: 10889 | U89: 10139 | V89: 9379 | W89: 11499 | X89: 11039 | Y89: 10589 | Z89: 9679 | AA89: 8779 | AB89: 11189 | AC89: 10589 | AD89: 9979 | AE89: 8769 | AF89: 7559 | AG89: 10439 | AH89: 9449 | AI89: 8469 | AJ89: 6499 | AK89: 4529 | AL89: 10129 | AM89: 8999 | AN89: 7859 | AO89: 5589 | AP89: 3319 | AQ89: 46251 | AR89: INDEFINIDO | AS89: =UPPER(TEXT(AQ89, " dd \ mmmm \ aa")&" - "&TEXT(AR89, " dd \ mmmm \ aa")) -> 17 AGOSTO 26 - INDEFINIDO
... B91: =ROW()-9 -> 82 | C91: RESURTIBLE | D91: SAMSUNG | E91: Samsung Galaxy S26 256GB | F91: SAMSUNG GALAXY S26 256GB 5G | G91: 22499 | H91: 17539 | I91: 17319 | J91: 17089 | K91: 16639 | L91: 16179 | M91: 17389 | N91: 17089 | O91: 16789 | P91: 16179 | Q91: 15579 | R91: 17239 | S91: 16859 | T91: 16479 | U91: 15729 | V91: 14969 | W91: 17089 | X91: 16629 | Y91: 16179 | Z91: 15269 | AA91: 14369 | AB91: 16779 | AC91: 16179 | AD91: 15569 | AE91: 14359 | AF91: 13149 | AG91: 16029 | AH91: 15039 | AI91: 14059 | AJ91: 12089 | AK91: 10129 | AL91: 15719 | AM91: 14589 | AN91: 13449 | AO91: 11179 | AP91: 8909 | AQ91: 46251 | AR91: INDEFINIDO | AS91: =UPPER(TEXT(AQ91, " dd \ mmmm \ aa")&" - "&TEXT(AR91, " dd \ mmmm \ aa")) -> 17 AGOSTO 26 - INDEFINIDO
B92: =ROW()-9 -> 83 | C92: NPI | D92: SAMSUNG | E92: Samsung Galaxy S26 FE 256GB 5G | F92: SAMSUNG GALAXY S26 FE 256GB 5G | G92: 19299 | H92: 12989 | I92: 12759 | J92: 12539 | K92: 12089 | L92: 11629 | M92: 12839 | N92: 12539 | O92: 12239 | P92: 11629 | Q92: 11029 | R92: 12689 | S92: 12309 | T92: 11929 | U92: 11179 | V92: 10419 | W92: 12539 | X92: 12079 | Y92: 11629 | Z92: 10719 | AA92: 9819 | AB92: 12229 | AC92: 11629 | AD92: 11019 | AE92: 9809 | AF92: 8599 | AG92: 11479 | AH92: 10489 | AI92: 9509 | AJ92: 7539 | AK92: 5569 | AL92: 11169 | AM92: 10039 | AN92: 8899 | AO92: 6629 | AP92: 4359 | AQ92: 46237 | AR92: 46326 | AS92: =UPPER(TEXT(AQ92, " dd \ mmmm \ aa")&" - "&TEXT(AR92, " dd \ mmmm \ aa")) -> 03 AGOSTO 26 - 31 OCTUBRE 26
B93: =ROW()-9 -> 84 | C93: RESURTIBLE | D93: SAMSUNG | E93: Samsung Galaxy S26 Ultra 512GB | F93: SAMSUNG GALAXY S26 ULTRA 512GB 5G | G93: 37999 | H93: 25709 | I93: 25359 | J93: 25009 | K93: 24309 | L93: 23619 | M93: 25469 | N93: 25009 | O93: 24539 | P93: 23619 | Q93: 22689 | R93: 25239 | S93: 24659 | T93: 24079 | U93: 22919 | V93: 21749 | W93: 25009 | X93: 24309 | Y93: 23609 | Z93: 22219 | AA93: 20819 | AB93: 24539 | AC93: 23609 | AD93: 22679 | AE93: 20819 | AF93: 18959 | AG93: 23379 | AH93: 21859 | AI93: 20349 | AJ93: 17319 | AK93: 14299 | AL93: 22909 | AM93: 21159 | AN93: 19419 | AO93: 15929 | AP93: 12429 | AQ93: 46251 | AR93: INDEFINIDO | AS93: =UPPER(TEXT(AQ93, " dd \ mmmm \ aa")&" - "&TEXT(AR93, " dd \ mmmm \ aa")) -> 17 AGOSTO 26 - INDEFINIDO
B94: =ROW()-9 -> 85 | C94: RESURTIBLE | D94: SAMSUNG | E94: Samsung Galaxy Z Flip8 512GB | F94: SAMSUNG GALAXY ZFLIP 8 512GB 5G | G94: 32999 | H94: 23039 | I94: 22809 | J94: 22579 | K94: 22129 | L94: 21679 | M94: 22879 | N94: 22579 | O94: 22279 | P94: 21679 | Q94: 21069 | R94: 22729 | S94: 22359 | T94: 21979 | U94: 21219 | V94: 20469 | W94: 22579 | X94: 22129 | Y94: 21669 | Z94: 20769 | AA94: 19859 | AB94: 22279 | AC94: 21669 | AD94: 21069 | AE94: 19859 | AF94: 18649 | AG94: 21519 | AH94: 20539 | AI94: 19549 | AJ94: 17589 | AK94: 15619 | AL94: 21219 | AM94: 20079 | AN94: 18949 | AO94: 16679 | AP94: 14409 | AQ94: 46231 | AR94: 46295 | AS94: =UPPER(TEXT(AQ94, " dd \ mmmm \ aa")&" - "&TEXT(AR94, " dd \ mmmm \ aa")) -> 28 JULIO 26 - 30 SEPTIEMBRE 26
B95: =ROW()-9 -> 86 | C95: RESURTIBLE | D95: SAMSUNG | E95: Samsung Galaxy Z Fold8 512GB | F95: SAMSUNG GALAXY ZFOLD 8 512GB 5G | G95: 48499 | H95: 34969 | I95: 34739 | J95: 34519 | K95: 34069 | L95: 33609 | M95: 34819 | N95: 34519 | O95: 34219 | P95: 33609 | Q95: 33009 | R95: 34669 | S95: 34289 | T95: 33909 | U95: 33159 | V95: 32399 | W95: 34519 | X95: 34059 | Y95: 33609 | Z95: 32699 | AA95: 31799 | AB95: 34209 | AC95: 33609 | AD95: 32999 | AE95: 31789 | AF95: 30579 | AG95: 33459 | AH95: 32469 | AI95: 31489 | AJ95: 29519 | AK95: 27549 | AL95: 33149 | AM95: 32019 | AN95: 30879 | AO95: 28609 | AP95: 26339 | AQ95: 46231 | AR95: 46295 | AS95: =UPPER(TEXT(AQ95, " dd \ mmmm \ aa")&" - "&TEXT(AR95, " dd \ mmmm \ aa")) -> 28 JULIO 26 - 30 SEPTIEMBRE 26
B96: =ROW()-9 -> 87 | C96: RESURTIBLE | D96: SAMSUNG | E96: Samsung Galaxy Z Fold8 Ultra 512GB | F96: SAMSUNG GALAXY ZFOLD 8 ULTRA 512GB 5G | G96: 53499 | H96: 38819 | I96: 38589 | J96: 38369 | K96: 37919 | L96: 37459 | M96: 38669 | N96: 38369 | O96: 38069 | P96: 37459 | Q96: 36859 | R96: 38519 | S96: 38139 | T96: 37759 | U96: 37009 | V96: 36249 | W96: 38369 | X96: 37909 | Y96: 37459 | Z96: 36549 | AA96: 35649 | AB96: 38059 | AC96: 37459 | AD96: 36849 | AE96: 35639 | AF96: 34429 | AG96: 37309 | AH96: 36319 | AI96: 35339 | AJ96: 33369 | AK96: 31399 | AL96: 36999 | AM96: 35869 | AN96: 34729 | AO96: 32459 | AP96: 30189 | AQ96: 46231 | AR96: 46295 | AS96: =UPPER(TEXT(AQ96, " dd \ mmmm \ aa")&" - "&TEXT(AR96, " dd \ mmmm \ aa")) -> 28 JULIO 26 - 30 SEPTIEMBRE 26
B97: =ROW()-9 -> 88 | C97: NO RESURTIBLE | D97: XIAOMI | E97: Xiaomi Redmi 15 | F97: XIAOMI REDMI 15 256GB 4G | G97: 4499 | H97: 2399 | I97: 2169 | J97: 1949 | K97: 1489 | L97: 1039 | M97: 2249 | N97: 1939 | O97: 1639 | P97: 1039 | Q97: 429 | R97: 2099 | S97: 1719 | T97: 1339 | U97: 579 | V97: 0 | W97: 1939 | X97: 1489 | Y97: 1039 | Z97: 129 | AA97: 0 | AB97: 1639 | AC97: 1039 | AD97: 429 | AE97: 0 | AF97: 0 | AG97: 879 | AH97: 0 | AI97: 0 | AJ97: 0 | AK97: 0 | AL97: 579 | AM97: 0 | AN97: 0 | AO97: 0 | AP97: 0 | AQ97: 46266 | AR97: 46295 | AS97: =UPPER(TEXT(AQ97, " dd \ mmmm \ aa")&" - "&TEXT(AR97, " dd \ mmmm \ aa")) -> 01 SEPTIEMBRE 26 - 30 SEPTIEMBRE 26
B98: =ROW()-9 -> 89 | C98: NO RESURTIBLE | D98: XIAOMI | E98: Xiaomi Redmi 15C | F98: XIAOMI REDMI 15C 128GB 4G | G98: 2999 | H98: 1089 | I98: 739 | J98: 389 | K98: 0 | L98: 0 | M98: 859 | N98: 389 | O98: 0 | P98: 0 | Q98: 0 | R98: 619 | S98: 39 | T98: 0 | U98: 0 | V98: 0 | W98: 389 | X98: 0 | Y98: 0 | Z98: 0 | AA98: 0 | AB98: 0 | AC98: 0 | AD98: 0 | AE98: 0 | AF98: 0 | AG98: 0 | AH98: 0 | AI98: 0 | AJ98: 0 | AK98: 0 | AL98: 0 | AM98: 0 | AN98: 0 | AO98: 0 | AP98: 0 | AQ98: 46266 | AR98: 46295 | AS98: =UPPER(TEXT(AQ98, " dd \ mmmm \ aa")&" - "&TEXT(AR98, " dd \ mmmm \ aa")) -> 01 SEPTIEMBRE 26 - 30 SEPTIEMBRE 26
B99: =ROW()-9 -> 90 | C99: NPI | D99: XIAOMI | E99: Xiaomi Redmi 17 128GB 4G | F99: XIAOMI REDMI 17 128GB 4G | G99: 4999 | H99: 2219 | I99: 1869 | J99: 1519 | K99: 829 | L99: 129 | M99: 1989 | N99: 1519 | O99: 1059 | P99: 129 | Q99: 0 | R99: 1749 | S99: 1169 | T99: 589 | U99: 0 | V99: 0 | W99: 1519 | X99: 819 | Y99: 119 | Z99: 0 | AA99: 0 | AB99: 1049 | AC99: 119 | AD99: 0 | AE99: 0 | AF99: 0 | AG99: 0 | AH99: 0 | AI99: 0 | AJ99: 0 | AK99: 0 | AL99: 0 | AM99: 0 | AN99: 0 | AO99: 0 | AP99: 0 | AQ99: 46266 | AR99: 46295 | AS99: =UPPER(TEXT(AQ99, " dd \ mmmm \ aa")&" - "&TEXT(AR99, " dd \ mmmm \ aa")) -> 01 SEPTIEMBRE 26 - 30 SEPTIEMBRE 26
B100: =ROW()-9 -> 91 | C100: RESURTIBLE | D100: XIAOMI | E100: Xiaomi Redmi A7 Pro | F100: XIAOMI REDMI A7 PRO 128GB 4G | G100: 3299 | H100: 1299 | I100: 949 | J100: 609 | K100: 0 | L100: 0 | M100: 1069 | N100: 599 | O100: 139 | P100: 0 | Q100: 0 | R100: 839 | S100: 259 | T100: 0 | U100: 0 | V100: 0 | W100: 599 | X100: 0 | Y100: 0 | Z100: 0 | AA100: 0 | AB100: 139 | AC100: 0 | AD100: 0 | AE100: 0 | AF100: 0 | AG100: 0 | AH100: 0 | AI100: 0 | AJ100: 0 | AK100: 0 | AL100: 0 | AM100: 0 | AN100: 0 | AO100: 0 | AP100: 0 | AQ100: 46266 | AR100: 46295 | AS100: =UPPER(TEXT(AQ100, " dd \ mmmm \ aa")&" - "&TEXT(AR100, " dd \ mmmm \ aa")) -> 01 SEPTIEMBRE 26 - 30 SEPTIEMBRE 26
B101: =ROW()-9 -> 92 | C101: NO RESURTIBLE | D101: XIAOMI | E101: Xiaomi Redmi Note 12 | F101: XIAOMI REDMI NOTE 12 128GB 4G | G101: 6499 | H101: 1399 | I101: 1249 | J101: 949 | K101: 549 | L101: 149 | M101: 1249 | N101: 949 | O101: 749 | P101: 149 | Q101: 0 | R101: 1099 | S101: 749 | T101: 449 | U101: 50 | V101: 0 | W101: 949 | X101: 549 | Y101: 149 | Z101: 0 | AA101: 0 | AB101: 699 | AC101: 149 | AD101: 0 | AE101: 0 | AF101: 0 | AG101: 0 | AH101: 0 | AI101: 0 | AJ101: 0 | AK101: 0 | AL101: 0 | AM101: 0 | AN101: 0 | AO101: 0 | AP101: 0 | AQ101: 45962 | AR101: INDEFINIDO | AS101: =UPPER(TEXT(AQ101, " dd \ mmmm \ aa")&" - "&TEXT(AR101, " dd \ mmmm \ aa")) -> 01 NOVIEMBRE 25 - INDEFINIDO
B102: =ROW()-9 -> 93 | C102: NO RESURTIBLE | D102: XIAOMI | E102: Xiaomi Note 14 | F102: XIAOMI REDMI NOTE 14 256GB 4G | G102: 5999 | H102: 2679 | I102: 2459 | J102: 2229 | K102: 1779 | L102: 1329 | M102: 2529 | N102: 2229 | O102: 1929 | P102: 1319 | Q102: 719 | R102: 2379 | S102: 1999 | T102: 1629 | U102: 869 | V102: 109 | W102: 2229 | X102: 1779 | Y102: 1319 | Z102: 419 | AA102: 0 | AB102: 1929 | AC102: 1319 | AD102: 719 | AE102: 0 | AF102: 0 | AG102: 1169 | AH102: 189 | AI102: 0 | AJ102: 0 | AK102: 0 | AL102: 869 | AM102: 0 | AN102: 0 | AO102: 0 | AP102: 0 | AQ102: 46266 | AR102: 46295 | AS102: =UPPER(TEXT(AQ102, " dd \ mmmm \ aa")&" - "&TEXT(AR102, " dd \ mmmm \ aa")) -> 01 SEPTIEMBRE 26 - 30 SEPTIEMBRE 26
B103: =ROW()-9 -> 94 | C103: NO RESURTIBLE | D103: XIAOMI | E103: Xiaomi Note 14 Pro 5G Bundle Audifonos | F103: XIAOMI REDMI NOTE 14 PRO 256GB 5G | G103: 9999 | H103: 5389 | I103: 5169 | J103: 4939 | K103: 4489 | L103: 4029 | M103: 5239 | N103: 4939 | O103: 4639 | P103: 4029 | Q103: 3429 | R103: 5089 | S103: 4709 | T103: 4329 | U103: 3579 | V103: 2819 | W103: 4939 | X103: 4479 | Y103: 4029 | Z103: 3119 | AA103: 2219 | AB103: 4629 | AC103: 4029 | AD103: 3419 | AE103: 2209 | AF103: 999 | AG103: 3879 | AH103: 2889 | AI103: 1909 | AJ103: 0 | AK103: 0 | AL103: 3569 | AM103: 2439 | AN103: 1299 | AO103: 0 | AP103: 0 | AQ103: 46266 | AR103: 46295 | AS103: =UPPER(TEXT(AQ103, " dd \ mmmm \ aa")&" - "&TEXT(AR103, " dd \ mmmm \ aa")) -> 01 SEPTIEMBRE 26 - 30 SEPTIEMBRE 26
B104: =ROW()-9 -> 95 | C104: NO RESURTIBLE | D104: XIAOMI | E104: Xiaomi Redmi Note 15 | F104: XIAOMI REDMI NOTE 15 256GB 4G | G104: 5999 | H104: 2649 | I104: 2429 | J104: 2199 | K104: 1749 | L104: 1289 | M104: 2499 | N104: 2199 | O104: 1899 | P104: 1289 | Q104: 689 | R104: 2349 | S104: 1969 | T104: 1589 | U104: 839 | V104: 79 | W104: 2199 | X104: 1739 | Y104: 1289 | Z104: 379 | AA104: 0 | AB104: 1889 | AC104: 1289 | AD104: 679 | AE104: 0 | AF104: 0 | AG104: 1139 | AH104: 149 | AI104: 0 | AJ104: 0 | AK104: 0 | AL104: 829 | AM104: 0 | AN104: 0 | AO104: 0 | AP104: 0 | AQ104: 46266 | AR104: 46295 | AS104: =UPPER(TEXT(AQ104, " dd \ mmmm \ aa")&" - "&TEXT(AR104, " dd \ mmmm \ aa")) -> 01 SEPTIEMBRE 26 - 30 SEPTIEMBRE 26
B105: =ROW()-9 -> 96 | C105: NO RESURTIBLE | D105: XIAOMI | E105: Redmi Note 15 Pro 5G + Buds 6 Active + Smart Band 9 Active | F105: XIAOMI REDMI NOTE 15 PRO 512GB 5G | G105: 9999 | H105: 5609 | I105: 5379 | J105: 5149 | K105: 4699 | L105: 4249 | M105: 5459 | N105: 5149 | O105: 4849 | P105: 4249 | Q105: 3639 | R105: 5299 | S105: 4929 | T105: 4549 | U105: 3789 | V105: 3039 | W105: 5149 | X105: 4699 | Y105: 4249 | Z105: 3339 | AA105: 2429 | AB105: 4849 | AC105: 4249 | AD105: 3639 | AE105: 2429 | AF105: 1219 | AG105: 4089 | AH105: 3109 | AI105: 2129 | AJ105: 159 | AK105: 0 | AL105: 3789 | AM105: 2649 | AN105: 1519 | AO105: 0 | AP105: 0 | AQ105: 46266 | AR105: 46295 | AS105: =UPPER(TEXT(AQ105, " dd \ mmmm \ aa")&" - "&TEXT(AR105, " dd \ mmmm \ aa")) -> 01 SEPTIEMBRE 26 - 30 SEPTIEMBRE 26
B106: =ROW()-9 -> 97 | C106: NO RESURTIBLE | D106: XIAOMI | E106: Redmi Note 15 Pro 5G + Buds 8 Active + Smart Band 9 Active | F106: XIAOMI REDMI NOTE 15 PRO 512GB 5G | G106: 9999 | H106: 5609 | I106: 5379 | J106: 5149 | K106: 4699 | L106: 4249 | M106: 5459 | N106: 5149 | O106: 4849 | P106: 4249 | Q106: 3639 | R106: 5299 | S106: 4929 | T106: 4549 | U106: 3789 | V106: 3039 | W106: 5149 | X106: 4699 | Y106: 4249 | Z106: 3339 | AA106: 2429 | AB106: 4849 | AC106: 4249 | AD106: 3639 | AE106: 2429 | AF106: 1219 | AG106: 4089 | AH106: 3109 | AI106: 2129 | AJ106: 159 | AK106: 0 | AL106: 3789 | AM106: 2649 | AN106: 1519 | AO106: 0 | AP106: 0 | AQ106: 46266 | AR106: 46295 | AS106: =UPPER(TEXT(AQ106, " dd \ mmmm \ aa")&" - "&TEXT(AR106, " dd \ mmmm \ aa")) -> 01 SEPTIEMBRE 26 - 30 SEPTIEMBRE 26
B107: =ROW()-9 -> 98 | C107: NPI | D107: XIAOMI | E107: Xiaomi Redmi Note 17 Bundle Sound Pock | F107: XIAOMI REDMI NOTE 17 BUNDLE SOUND POCK | G107: 6499 | H107: 2959 | I107: 2609 | J107: 2259 | K107: 1569 | L107: 869 | M107: 2729 | N107: 2259 | O107: 1799 | P107: 869 | Q107: 0 | R107: 2489 | S107: 1909 | T107: 1329 | U107: 169 | V107: 0 | W107: 2259 | X107: 1559 | Y107: 869 | Z107: 0 | AA107: 0 | AB107: 1789 | AC107: 859 | AD107: 0 | AE107: 0 | AF107: 0 | AG107: 629 | AH107: 0 | AI107: 0 | AJ107: 0 | AK107: 0 | AL107: 159 | AM107: 0 | AN107: 0 | AO107: 0 | AP107: 0 | AQ107: 46266 | AR107: 46295 | AS107: =UPPER(TEXT(AQ107, " dd \ mmmm \ aa")&" - "&TEXT(AR107, " dd \ mmmm \ aa")) -> 01 SEPTIEMBRE 26 - 30 SEPTIEMBRE 26
B108: =ROW()-9 -> 99 | C108: NO RESURTIBLE | D108: ZTE | E108: Axon 60 | F108: ZTE AXON 60 256GB 4G | G108: 3499 | H108: 899 | I108: 669 | J108: 439 | K108: 0 | L108: 0 | M108: 749 | N108: 439 | O108: 139 | P108: 0 | Q108: 0 | R108: 589 | S108: 219 | T108: 0 | U108: 0 | V108: 0 | W108: 439 | X108: 0 | Y108: 0 | Z108: 0 | AA108: 0 | AB108: 139 | AC108: 0 | AD108: 0 | AE108: 0 | AF108: 0 | AG108: 0 | AH108: 0 | AI108: 0 | AJ108: 0 | AK108: 0 | AL108: 0 | AM108: 0 | AN108: 0 | AO108: 0 | AP108: 0 | AQ108: 46206 | AR108: INDEFINIDO | AS108: =UPPER(TEXT(AQ108, " dd \ mmmm \ aa")&" - "&TEXT(AR108, " dd \ mmmm \ aa")) -> 03 JULIO 26 - INDEFINIDO
B109: =ROW()-9 -> 100 | C109: NO RESURTIBLE | D109: ZTE | E109: Axon 60 Lite | F109: ZTE AXON 60 LITE 256GB 4G | G109: 2999 | H109: 659 | I109: 429 | J109: 199 | K109: 0 | L109: 0 | M109: 499 | N109: 199 | O109: 0 | P109: 0 | Q109: 0 | R109: 349 | S109: 0 | T109: 0 | U109: 0 | V109: 0 | W109: 199 | X109: 0 | Y109: 0 | Z109: 0 | AA109: 0 | AB109: 0 | AC109: 0 | AD109: 0 | AE109: 0 | AF109: 0 | AG109: 0 | AH109: 0 | AI109: 0 | AJ109: 0 | AK109: 0 | AL109: 0 | AM109: 0 | AN109: 0 | AO109: 0 | AP109: 0 | AQ109: 46206 | AR109: INDEFINIDO | AS109: =UPPER(TEXT(AQ109, " dd \ mmmm \ aa")&" - "&TEXT(AR109, " dd \ mmmm \ aa")) -> 03 JULIO 26 - INDEFINIDO
...

Sheet Precios
D1: SIN LANZAR- NO ESTA EN CATALOGO--REVISAR FECHAS | E1: OPPO RENO 14 512GB 5G BDL HEADPHONES | G1: Ármalo Negocios 299 | L1: Ármalo Negocios 399 | Q1: Ármalo Negocios 499 | V1: Ármalo Negocios 599 | AA1: Ármalo Negocios 799 | AF1: Ármalo Negocios 1299 | AK1: Ármalo Negocios 1499 | AP1: VIGENCIA
G2: 299 | L2: 399 | Q2: 499 | V2: 599 | AA2: 799 | AF2: 1299 | AK2: 1499
B3: Oferta | C3: Marca | D3: Modelo | E3: Familia | F3: Full price | G3: 12 Meses | H3: 18 Meses | I3: 24 Meses | J3: 36 Meses | K3: 48 Meses | L3: 12 Meses2 | M3: 18 Meses3 | N3: 24 Meses4 | O3: 36 Meses5 | P3: 48 Meses6 | Q3: 12 Meses7 | R3: 18 Meses8 | S3: 24 Meses9 | T3: 36 Meses10 | U3: 48 Meses11 | V3: 12 Meses12 | W3: 18 Meses13 | X3: 24 Meses14 | Y3: 36 Meses15 | Z3: 48 Meses16 | AA3: 12 Meses17 | AB3: 18 Meses18 | AC3: 24 Meses19 | AD3: 36 Meses20 | AE3: 48 Meses21 | AF3: 12 Meses22 | AG3: 18 Meses23 | AH3: 24 Meses24 | AI3: 36 Meses25 | AJ3: 48 Meses26 | AK3: 12 Meses27 | AL3: 18 Meses28 | AM3: 24 Meses29 | AN3: 36 Meses30 | AO3: 48 Meses31 | AP3: Fecha Inicio | AQ3: Fecha Fin
A4: =_xlfn.TEXTJOIN("",,F4:AO4)=_xlfn.TEXTJOIN("",,F3:AO3) -> FALSE | B4: YArmalo Neg V1 | C4: ALCATEL | D4: Alcatel 1SE 32GB | E4: ALCATEL 1 SE 32GB 4G | F4: 2949 | G4: 2499 | H4: 2299 | I4: 1999 | J4: 1799 | K4: 1799 | L4: 2299 | M4: 1999 | N4: 1699 | O4: 1499 | P4: 1499 | Q4: 1999 | R4: 1799 | S4: 1499 | T4: 1299 | U4: 1299 | V4: 1699 | W4: 1399 | X4: 1099 | Y4: 799 | Z4: 799 | AA4: 799 | AB4: 399 | AC4: 0 | AD4: 0 | AE4: 0 | AF4: 0 | AG4: 0 | AH4: 0 | AI4: 0 | AJ4: 0 | AK4: 0 | AL4: 0 | AM4: 0 | AN4: 0 | AO4: 0 | AP4: 45135 | AQ4: 54789 | AR4: =IF(E3=E4,AP4-AQ3,0) -> 0
A5: =_xlfn.TEXTJOIN("",,F5:AO5)=_xlfn.TEXTJOIN("",,F4:AO4) -> FALSE | B5: YArmalo Neg V1 | C5: ALCATEL | D5: Alcatel 1SE 64GB | E5: ALCATEL 1 SE 64GB 4G | F5: 2880 | G5: 1999 | H5: 1699 | I5: 1499 | J5: 1299 | K5: 1299 | L5: 1799 | M5: 1499 | N5: 1199 | O5: 899 | P5: 899 | Q5: 1499 | R5: 1299 | S5: 999 | T5: 699 | U5: 699 | V5: 1199 | W5: 899 | X5: 599 | Y5: 299 | Z5: 299 | AA5: 299 | AB5: 0 | AC5: 0 | AD5: 0 | AE5: 0 | AF5: 0 | AG5: 0 | AH5: 0 | AI5: 0 | AJ5: 0 | AK5: 0 | AL5: 0 | AM5: 0 | AN5: 0 | AO5: 0 | AP5: 45239 | AQ5: 54789 | AR5: =IF(E4=E5,AP5-AQ4,0) -> 0
A6: =_xlfn.TEXTJOIN("",,F6:AO6)=_xlfn.TEXTJOIN("",,F5:AO5) -> FALSE | B6: YArmalo Neg V1 | C6: ALCATEL | D6: Alcatel 1B 5002M | E6: ALCATEL 1B 5002M | F6: 1717.4604 | G6: 1399 | H6: 1099 | I6: 899 | J6: 699 | K6: 699 | L6: 1199 | M6: 899 | N6: 599 | O6: 399 | P6: 399 | Q6: 899 | R6: 699 | S6: 399 | T6: 199 | U6: 199 | V6: 599 | W6: 299 | X6: 0 | Y6: 0 | Z6: 0 | AA6: 0 | AB6: 0 | AC6: 0 | AD6: 0 | AE6: 0 | AF6: 0 | AG6: 0 | AH6: 0 | AI6: 0 | AJ6: 0 | AK6: 0 | AL6: 0 | AM6: 0 | AN6: 0 | AO6: 0 | AP6: 45239 | AQ6: 54789 | AR6: =IF(E5=E6,AP6-AQ5,0) -> 0
A7: =_xlfn.TEXTJOIN("",,F7:AO7)=_xlfn.TEXTJOIN("",,F6:AO6) -> FALSE | B7: YArmalo Neg V1 | C7: ALCATEL | D7: Alcatel 3 20 | E7: ALCATEL 3 2020 | F7: 3649 | G7: 2299 | H7: 2099 | I7: 1799 | J7: 1599 | K7: 1599 | L7: 2099 | M7: 1799 | N7: 1499 | O7: 1299 | P7: 1299 | Q7: 1799 | R7: 1599 | S7: 1299 | T7: 1099 | U7: 1099 | V7: 1499 | W7: 1199 | X7: 899 | Y7: 599 | Z7: 599 | AA7: 599 | AB7: 199 | AC7: 0 | AD7: 0 | AE7: 0 | AF7: 0 | AG7: 0 | AH7: 0 | AI7: 0 | AJ7: 0 | AK7: 0 | AL7: 0 | AM7: 0 | AN7: 0 | AO7: 0 | AP7: 45239 | AQ7: 54789 | AR7: =IF(E6=E7,AP7-AQ6,0) -> 0
A8: =_xlfn.TEXTJOIN("",,F8:AO8)=_xlfn.TEXTJOIN("",,F7:AO7) -> FALSE | B8: ZArmalo Neg 2.0 Precio base | C8: APPLE | D8: Apple iPhone 11 64GB | E8: APPLE IPHONE 11 64GB 4G | F8: 10999 | G8: 3849 | H8: 3499 | I8: 3149 | J8: 2499 | K8: 1799 | L8: 3649 | M8: 3149 | N8: 2699 | O8: 1799 | P8: 899 | Q8: 3399 | R8: 2849 | S8: 2249 | T8: 1099 | U8: 0 | V8: 3149 | W8: 2499 | X8: 1799 | Y8: 449 | Z8: 0 | AA8: 2699 | AB8: 1799 | AC8: 899 | AD8: 0 | AE8: 0 | AF8: 1549 | AG8: 99 | AH8: 0 | AI8: 0 | AJ8: 0 | AK8: 1099 | AL8: 0 | AM8: 0 | AN8: 0 | AO8: 0 | AP8: 46059 | AQ8: 54789 | AR8: =IF(E7=E8,AP8-AQ7,0) -> 0
A9: =_xlfn.TEXTJOIN("",,F9:AO9)=_xlfn.TEXTJOIN("",,F8:AO8) -> FALSE | B9: YArmalo Neg V1 | C9: APPLE | D9: Apple iPhone 11 Pro 256GB | E9: APPLE IPHONE 11 PRO 256GB 4G | F9: 31320 | G9: 9299 | H9: 9099 | I9: 8899 | J9: 8699 | K9: 8699 | L9: 9199 | M9: 8899 | N9: 8599 | O9: 8299 | P9: 8299 | Q9: 8899 | R9: 8699 | S9: 8399 | T9: 8099 | U9: 8099 | V9: 8599 | W9: 8299 | X9: 7999 | Y9: 7699 | Z9: 7699 | AA9: 7699 | AB9: 7299 | AC9: 6899 | AD9: 6499 | AE9: 6499 | AF9: 4999 | AG9: 4299 | AH9: 3699 | AI9: 2999 | AJ9: 2999 | AK9: 4399 | AL9: 3599 | AM9: 2899 | AN9: 2099 | AO9: 2099 | AP9: 45195 | AQ9: 54789 | AR9: =IF(E8=E9,AP9-AQ8,0) -> 0
A10: =_xlfn.TEXTJOIN("",,F10:AO10)=_xlfn.TEXTJOIN("",,F9:AO9) -> FALSE | B10: YArmalo Neg V1 | C10: APPLE | D10: Apple iPhone 11 Pro 64GB | E10: APPLE IPHONE 11 PRO 64GB 4G | F10: 27360 | G10: 9299 | H10: 9099 | I10: 8899 | J10: 8699 | K10: 8699 | L10: 9199 | M10: 8899 | N10: 8599 | O10: 8299 | P10: 8299 | Q10: 8899 | R10: 8599 | S10: 8399 | T10: 8099 | U10: 8099 | V10: 8599 | W10: 8299 | X10: 7999 | Y10: 7699 | Z10: 7699 | AA10: 7699 | AB10: 7299 | AC10: 6899 | AD10: 6399 | AE10: 6399 | AF10: 4899 | AG10: 4299 | AH10: 3599 | AI10: 2999 | AJ10: 2999 | AK10: 4299 | AL10: 3599 | AM10: 2799 | AN10: 2099 | AO10: 2099 | AP10: 45195 | AQ10: 54789 | AR10: =IF(E9=E10,AP10-AQ9,0) -> 0
A11: =_xlfn.TEXTJOIN("",,F11:AO11)=_xlfn.TEXTJOIN("",,F10:AO10) -> FALSE | B11: YArmalo Neg V1 | C11: APPLE | D11: Apple iPhone 11 Pro Max 64GB | E11: APPLE IPHONE 11 PRO MAX 64GB 4G | F11: 29880 | G11: 25399 | H11: 25199 | I11: 24999 | J11: 24799 | K11: 24799 | L11: 25299 | M11: 24999 | N11: 24699 | O11: 24399 | P11: 24399 | Q11: 24999 | R11: 24799 | S11: 24499 | T11: 24199 | U11: 24199 | V11: 24699 | W11: 24399 | X11: 24099 | Y11: 23799 | Z11: 23799 | AA11: 23799 | AB11: 23399 | AC11: 22999 | AD11: 22599 | AE11: 22599 | AF11: 21099 | AG11: 20399 | AH11: 19799 | AI11: 19099 | AJ11: 19099 | AK11: 20499 | AL11: 19699 | AM11: 18999 | AN11: 18199 | AO11: 18199 | AP11: 45135 | AQ11: 54789 | AR11: =IF(E10=E11,AP11-AQ10,0) -> 0
A12: =_xlfn.TEXTJOIN("",,F12:AO12)=_xlfn.TEXTJOIN("",,F11:AO11) -> FALSE | B12: YArmalo Neg V1 | C12: APPLE | D12: Apple iPhone 12 256GB | E12: APPLE IPHONE 12 256GB 4G | F12: 29160 | G12: 22499 | H12: 22299 | I12: 22099 | J12: 21899 | K12: 21899 | L12: 22399 | M12: 22099 | N12: 21799 | O12: 21499 | P12: 21499 | Q12: 22099 | R12: 21799 | S12: 21599 | T12: 21299 | U12: 21299 | V12: 21799 | W12: 21499 | X12: 21199 | Y12: 20899 | Z12: 20899 | AA12: 20899 | AB12: 20399 | AC12: 19999 | AD12: 19599 | AE12: 19599 | AF12: 18099 | AG12: 17499 | AH12: 16799 | AI12: 16199 | AJ12: 16199 | AK12: 17499 | AL12: 16799 | AM12: 15999 | AN12: 15299 | AO12: 15299 | AP12: 45218 | AQ12: 54789 | AR12: =IF(E11=E12,AP12-AQ11,0) -> 0
A13: =_xlfn.TEXTJOIN("",,F13:AO13)=_xlfn.TEXTJOIN("",,F12:AO12) -> FALSE | B13: YArmalo Neg V1 | C13: APPLE | D13: Apple iPhone 12 Mini 128GB | E13: APPLE IPHONE 12 MINI 128GB | F13: 21499 | G13: 13599 | H13: 13399 | I13: 13199 | J13: 12899 | K13: 12899 | L13: 13499 | M13: 13199 | N13: 12899 | O13: 12599 | P13: 12599 | Q13: 13199 | R13: 12899 | S13: 12699 | T13: 12399 | U13: 12399 | V13: 12899 | W13: 12599 | X13: 12299 | Y13: 11899 | Z13: 11899 | AA13: 11899 | AB13: 11499 | AC13: 11099 | AD13: 10699 | AE13: 10699 | AF13: 9199 | AG13: 8599 | AH13: 7899 | AI13: 7299 | AJ13: 7299 | AK13: 8599 | AL13: 7899 | AM13: 7099 | AN13: 6399 | AO13: 6399 | AP13: 45195 | AQ13: 54789 | AR13: =IF(E12=E13,AP13-AQ12,0) -> 0
A14: =_xlfn.TEXTJOIN("",,F14:AO14)=_xlfn.TEXTJOIN("",,F13:AO13) -> FALSE | B14: YArmalo Neg V1 | C14: APPLE | D14: Apple iPhone 12 Mini 256GB | E14: APPLE IPHONE 12 MINI 256GB 4G | F14: 24499 | G14: 22699 | H14: 22499 | I14: 22299 | J14: 22099 | K14: 22099 | L14: 22599 | M14: 22299 | N14: 21999 | O14: 21699 | P14: 21699 | Q14: 22299 | R14: 21999 | S14: 21799 | T14: 21499 | U14: 21499 | V14: 21999 | W14: 21699 | X14: 21399 | Y14: 21099 | Z14: 21099 | AA14: 21099 | AB14: 20599 | AC14: 20199 | AD14: 19799 | AE14: 19799 | AF14: 18299 | AG14: 17699 | AH14: 16999 | AI14: 16399 | AJ14: 16399 | AK14: 17699 | AL14: 16999 | AM14: 16199 | AN14: 15499 | AO14: 15499 | AP14: 45135 | AQ14: 54789 | AR14: =IF(E13=E14,AP14-AQ13,0) -> 0
A15: =_xlfn.TEXTJOIN("",,F15:AO15)=_xlfn.TEXTJOIN("",,F14:AO14) -> FALSE | B15: YArmalo Neg V1 | C15: APPLE | D15: Apple iPhone 12 Mini 64GB | E15: APPLE IPHONE 12 MINI 64GB 4G | F15: 19999 | G15: 18599 | H15: 18399 | I15: 18199 | J15: 17999 | K15: 17999 | L15: 18499 | M15: 18199 | N15: 17899 | O15: 17599 | P15: 17599 | Q15: 18199 | R15: 17899 | S15: 17699 | T15: 17399 | U15: 17399 | V15: 17899 | W15: 17599 | X15: 17299 | Y15: 16999 | Z15: 16999 | AA15: 16999 | AB15: 16599 | AC15: 16099 | AD15: 15699 | AE15: 15699 | AF15: 14199 | AG15: 13599 | AH15: 12899 | AI15: 12299 | AJ15: 12299 | AK15: 13599 | AL15: 12899 | AM15: 12099 | AN15: 11399 | AO15: 11399 | AP15: 45146 | AQ15: 54789 | AR15: =IF(E14=E15,AP15-AQ14,0) -> 0
... A79: =_xlfn.TEXTJOIN("",,F79:AO79)=_xlfn.TEXTJOIN("",,F78:AO78) -> FALSE | B79: Armalo Neg 2.0 Promo | C79: GOOGLE | D79: Google Pixel 10 128GB | E79: GOOGLE PIXEL 10 128GB 5G | F79: 19999 | G79: 12179 | H79: 11949 | I79: 11719 | J79: 11269 | K79: 10819 | L79: 12019 | M79: 11719 | N79: 11419 | O79: 10819 | P79: 10209 | Q79: 11869 | R79: 11489 | S79: 11119 | T79: 10359 | U79: 9599 | V79: 11719 | W79: 11269 | X79: 10809 | Y79: 9909 | Z79: 8999 | AA79: 11419 | AB79: 10809 | AC79: 10209 | AD79: 8999 | AE79: 7789 | AF79: 10659 | AG79: 9679 | AH79: 8689 | AI79: 6729 | AJ79: 4759 | AK79: 10359 | AL79: 9219 | AM79: 8089 | AN79: 5819 | AO79: 3549 | AP79: 46204 | AQ79: 46329 | AR79: =IF(E78=E79,AP79-AQ78,0) -> 0
A80: =_xlfn.TEXTJOIN("",,F80:AO80)=_xlfn.TEXTJOIN("",,#REF!) -> #REF! | B80: ZArmalo Neg 2.0 Precio base | C80: GOOGLE | D80: Google Pixel 10 128GB | E80: GOOGLE PIXEL 10 128GB 5G | F80: 19999 | G80: 17099 | H80: 16899 | I80: 16699 | J80: 16249 | K80: 15799 | L80: 16999 | M80: 16699 | N80: 16399 | O80: 15799 | P80: 15249 | Q80: 16849 | R80: 16449 | S80: 16099 | T80: 15399 | U80: 14649 | V80: 16699 | W80: 16249 | X80: 15799 | Y80: 14949 | Z80: 14049 | AA80: 16399 | AB80: 15799 | AC80: 15249 | AD80: 14049 | AE80: 12899 | AF80: 15649 | AG80: 14699 | AH80: 13749 | AI80: 11899 | AJ80: 9999 | AK80: 15349 | AL80: 14299 | AM80: 13199 | AN80: 10999 | AO80: 8849 | AP80: 46330 | AQ80: 54789 | AR80: =IF(#REF!=E80,AP80-#REF!,0) -> #REF!
A81: =_xlfn.TEXTJOIN("",,F81:AO81)=_xlfn.TEXTJOIN("",,F80:AO80) -> FALSE | B81: Armalo Neg 2.0 Promo | C81: GOOGLE | D81: Google Pixel 10 256GB | E81: GOOGLE PIXEL 10 256GB 5G | F81: 22499 | G81: 13289 | H81: 13069 | I81: 12839 | J81: 12389 | K81: 11939 | L81: 13139 | M81: 12839 | N81: 12539 | O81: 11929 | P81: 11329 | Q81: 12989 | R81: 12609 | S81: 12239 | T81: 11479 | U81: 10719 | V81: 12839 | W81: 12389 | X81: 11929 | Y81: 11029 | Z81: 10119 | AA81: 12539 | AB81: 11929 | AC81: 11329 | AD81: 10119 | AE81: 8909 | AF81: 11779 | AG81: 10799 | AH81: 9809 | AI81: 7849 | AJ81: 5879 | AK81: 11479 | AL81: 10339 | AM81: 9209 | AN81: 6939 | AO81: 4669 | AP81: 46204 | AQ81: 46329 | AR81: =IF(E80=E81,AP81-AQ80,0) -> 0
A82: =_xlfn.TEXTJOIN("",,F82:AO82)=_xlfn.TEXTJOIN("",,#REF!) -> #REF! | B82: ZArmalo Neg 2.0 Precio base | C82: GOOGLE | D82: Google Pixel 10 256GB | E82: GOOGLE PIXEL 10 256GB 5G | F82: 22499 | G82: 19299 | H82: 19099 | I82: 18899 | J82: 18449 | K82: 17999 | L82: 19149 | M82: 18899 | N82: 18599 | O82: 17999 | P82: 17449 | Q82: 18999 | R82: 18649 | S82: 18299 | T82: 17549 | U82: 16849 | V82: 18899 | W82: 18449 | X82: 17999 | Y82: 17149 | Z82: 16249 | AA82: 18599 | AB82: 17999 | AC82: 17399 | AD82: 16249 | AE82: 15099 | AF82: 17849 | AG82: 16899 | AH82: 15949 | AI82: 14049 | AJ82: 12199 | AK82: 17549 | AL82: 16449 | AM82: 15399 | AN82: 13199 | AO82: 10999 | AP82: 46330 | AQ82: 54789 | AR82: =IF(#REF!=E82,AP82-#REF!,0) -> #REF!
A83: =_xlfn.TEXTJOIN("",,F83:AO83)=_xlfn.TEXTJOIN("",,F82:AO82) -> FALSE | B83: Armalo Neg 2.0 Promo | C83: GOOGLE | D83: Google Pixel 10 Pro 256GB | E83: GOOGLE PIXEL 10 PRO 256GB 5G | F83: 28499 | G83: 16039 | H83: 15809 | I83: 15589 | J83: 15139 | K83: 14679 | L83: 15889 | M83: 15589 | N83: 15289 | O83: 14679 | P83: 14079 | Q83: 15739 | R83: 15359 | S83: 14979 | T83: 14229 | U83: 13469 | V83: 15589 | W83: 15129 | X83: 14679 | Y83: 13769 | Z83: 12869 | AA83: 15279 | AB83: 14679 | AC83: 14069 | AD83: 12859 | AE83: 11649 | AF83: 14529 | AG83: 13539 | AH83: 12559 | AI83: 10589 | AJ83: 8619 | AK83: 14219 | AL83: 13089 | AM83: 11949 | AN83: 9679 | AO83: 7409 | AP83: 46204 | AQ83: 46329 | AR83: =IF(E82=E83,AP83-AQ82,0) -> 0
A84: =_xlfn.TEXTJOIN("",,F84:AO84)=_xlfn.TEXTJOIN("",,#REF!) -> #REF! | B84: ZArmalo Neg 2.0 Precio base | C84: GOOGLE | D84: Google Pixel 10 Pro 256GB | E84: GOOGLE PIXEL 10 PRO 256GB 5G | F84: 28499 | G84: 24549 | H84: 24349 | I84: 24149 | J84: 23699 | K84: 23249 | L84: 24449 | M84: 24149 | N84: 23849 | O84: 23249 | P84: 22699 | Q84: 24299 | R84: 23899 | S84: 23549 | T84: 22849 | U84: 22099 | V84: 24149 | W84: 23699 | X84: 23249 | Y84: 22399 | Z84: 21499 | AA84: 23849 | AB84: 23249 | AC84: 22699 | AD84: 21499 | AE84: 20349 | AF84: 23099 | AG84: 22149 | AH84: 21249 | AI84: 19349 | AJ84: 17449 | AK84: 22849 | AL84: 21749 | AM84: 20649 | AN84: 18449 | AO84: 16299 | AP84: 46330 | AQ84: 54789 | AR84: =IF(#REF!=E84,AP84-#REF!,0) -> #REF!
A85: =_xlfn.TEXTJOIN("",,F85:AO85)=_xlfn.TEXTJOIN("",,F84:AO84) -> FALSE | B85: Armalo Neg 2.0 Promo | C85: GOOGLE | D85: Google Pixel 10 Pro 512GB | E85: GOOGLE PIXEL 10 PRO 512GB 5G | F85: 31499 | G85: 18519 | H85: 18289 | I85: 18059 | J85: 17609 | K85: 17159 | L85: 18369 | M85: 18059 | N85: 17759 | O85: 17159 | P85: 16549 | Q85: 18209 | R85: 17839 | S85: 17459 | T85: 16699 | U85: 15949 | V85: 18059 | W85: 17609 | X85: 17159 | Y85: 16249 | Z85: 15339 | AA85: 17759 | AB85: 17149 | AC85: 16549 | AD85: 15339 | AE85: 14129 | AF85: 16999 | AG85: 16019 | AH85: 15029 | AI85: 13069 | AJ85: 11099 | AK85: 16699 | AL85: 15559 | AM85: 14429 | AN85: 12159 | AO85: 9889 | AP85: 46204 | AQ85: 46329 | AR85: =IF(E84=E85,AP85-AQ84,0) -> 0
A86: =_xlfn.TEXTJOIN("",,F86:AO86)=_xlfn.TEXTJOIN("",,#REF!) -> #REF! | B86: ZArmalo Neg 2.0 Precio base | C86: GOOGLE | D86: Google Pixel 10 Pro 512GB | E86: GOOGLE PIXEL 10 PRO 512GB 5G | F86: 31499 | G86: 27199 | H86: 26999 | I86: 26749 | J86: 26349 | K86: 25899 | L86: 27049 | M86: 26749 | N86: 26499 | O86: 25899 | P86: 25299 | Q86: 26899 | R86: 26549 | S86: 26199 | T86: 25449 | U86: 24749 | V86: 26749 | W86: 26349 | X86: 25899 | Y86: 24999 | Z86: 24149 | AA86: 26499 | AB86: 25899 | AC86: 25299 | AD86: 24149 | AE86: 22999 | AF86: 25749 | AG86: 24799 | AH86: 23849 | AI86: 21949 | AJ86: 20049 | AK86: 25449 | AL86: 24349 | AM86: 23249 | AN86: 21099 | AO86: 18899 | AP86: 46330 | AQ86: 54789 | AR86: =IF(#REF!=E86,AP86-#REF!,0) -> #REF!
A87: =_xlfn.TEXTJOIN("",,F87:AO87)=_xlfn.TEXTJOIN("",,F86:AO86) -> FALSE | B87: Armalo Neg 2.0 Promo | C87: GOOGLE | D87: Google Pixel 10 Pro XL 256GB | E87: GOOGLE PIXEL 10 PRO XL 256GB 5G | F87: 30999 | G87: 19119 | H87: 18889 | I87: 18669 | J87: 18209 | K87: 17759 | L87: 18969 | M87: 18659 | N87: 18359 | O87: 17759 | P87: 17149 | Q87: 18819 | R87: 18439 | S87: 18059 | T87: 17299 | U87: 16549 | V87: 18659 | W87: 18209 | X87: 17759 | Y87: 16849 | Z87: 15939 | AA87: 18359 | AB87: 17759 | AC87: 17149 | AD87: 15939 | AE87: 14729 | AF87: 17599 | AG87: 16619 | AH87: 15639 | AI87: 13669 | AJ87: 11699 | AK87: 17299 | AL87: 16169 | AM87: 15029 | AN87: 12759 | AO87: 10489 | AP87: 46204 | AQ87: 46329 | AR87: =IF(E86=E87,AP87-AQ86,0) -> 0
A88: =_xlfn.TEXTJOIN("",,F88:AO88)=_xlfn.TEXTJOIN("",,#REF!) -> #REF! | B88: ZArmalo Neg 2.0 Precio base | C88: GOOGLE | D88: Google Pixel 10 Pro XL 256GB | E88: GOOGLE PIXEL 10 PRO XL 256GB 5G | F88: 30999 | G88: 26749 | H88: 26549 | I88: 26349 | J88: 25899 | K88: 25449 | L88: 26599 | M88: 26349 | N88: 26049 | O88: 25449 | P88: 24899 | Q88: 26449 | R88: 26099 | S88: 25749 | T88: 24999 | U88: 24299 | V88: 26349 | W88: 25899 | X88: 25449 | Y88: 24599 | Z88: 23699 | AA88: 26049 | AB88: 25449 | AC88: 24849 | AD88: 23699 | AE88: 22549 | AF88: 25299 | AG88: 24349 | AH88: 23399 | AI88: 21549 | AJ88: 19649 | AK88: 24999 | AL88: 23949 | AM88: 22849 | AN88: 20649 | AO88: 18449 | AP88: 46330 | AQ88: 54789 | AR88: =IF(#REF!=E88,AP88-#REF!,0) -> #REF!
A89: =_xlfn.TEXTJOIN("",,F89:AO89)=_xlfn.TEXTJOIN("",,F88:AO88) -> FALSE | B89: Armalo Neg 2.0 Promo | C89: GOOGLE | D89: Google Pixel 10 Pro XL 512GB | E89: GOOGLE PIXEL 10 PRO XL 512GB 5G | F89: 33999 | G89: 21009 | H89: 20789 | I89: 20559 | J89: 20109 | K89: 19649 | L89: 20859 | M89: 20559 | N89: 20259 | O89: 19649 | P89: 19049 | Q89: 20709 | R89: 20329 | S89: 19949 | T89: 19199 | U89: 18439 | V89: 20559 | W89: 20099 | X89: 19649 | Y89: 18739 | Z89: 17839 | AA89: 20249 | AB89: 19649 | AC89: 19039 | AD89: 17829 | AE89: 16619 | AF89: 19499 | AG89: 18509 | AH89: 17529 | AI89: 15559 | AJ89: 13589 | AK89: 19189 | AL89: 18059 | AM89: 16919 | AN89: 14649 | AO89: 12379 | AP89: 46204 | AQ89: 46329 | AR89: =IF(E88=E89,AP89-AQ88,0) -> 0
A90: =_xlfn.TEXTJOIN("",,F90:AO90)=_xlfn.TEXTJOIN("",,#REF!) -> #REF! | B90: ZArmalo Neg 2.0 Precio base | C90: GOOGLE | D90: Google Pixel 10 Pro XL 512GB | E90: GOOGLE PIXEL 10 PRO XL 512GB 5G | F90: 33999 | G90: 29399 | H90: 29199 | I90: 28949 | J90: 28499 | K90: 28099 | L90: 29249 | M90: 28949 | N90: 28649 | O90: 28099 | P90: 27499 | Q90: 29099 | R90: 28749 | S90: 28399 | T90: 27649 | U90: 26899 | V90: 28949 | W90: 28499 | X90: 28099 | Y90: 27199 | Z90: 26349 | AA90: 28649 | AB90: 28099 | AC90: 27499 | AD90: 26349 | AE90: 25199 | AF90: 27949 | AG90: 26999 | AH90: 26049 | AI90: 24149 | AJ90: 22249 | AK90: 27649 | AL90: 26549 | AM90: 25449 | AN90: 23299 | AO90: 21099 | AP90: 46330 | AQ90: 54789 | AR90: =IF(#REF!=E90,AP90-#REF!,0) -> #REF!
